Workbook

Sheet DISCLAIMER
C12: DISCLAIMER
C14: The content of this model is intended for discussion and illustrative purposes only.
C15: This model does not represent advice or a recommendation to enter into any investment and/or to make a financial decision.
C16: The viewers should consider obtaining independent professional advice before making any financial decisions.
P311: =$F311*P$5 -> 0

Sheet Guideline
B2: ='1. Project Summary'!B2 -> Projections - Serious Shea
B3: ='1. Project Summary'!B3 -> (in EUR, unless otherwise stated)
B5: General
B7: Introduction:
B8: This model provides an indicative 31-year financial forecast for Serious Shea's ARR project in Senegal (henceforth referred to as the "Project").
B9: The model includes the main costs for a VCS and CCB project.
B10: The net cash flows of the Project correspond to the net cash available to the project, after accounting for the main expenses including project development costs, ARR implementation costs, processing center costs, etc.
B11: The model does not account for taxes, and therefore, ignores the impact of tax losses carryforward, deferred tax assets, and deferred tax liabilities.
B12: The model ignores the impact of forex gains and losses.
B13: All financial figures are in EUR (unless stated otherwise).
B15: Formatting guideline:
B16: In black: formula-based cells.
B17: In blue: hard-coded inputs.
B18: In purple: key parameters but linked to other tabs.
... B127: This tab summarizes the output of EP Carbon's carbon accounting model. It is linked to the "4.1 Revenue Build - VCU" tab.
J280: =$F280*J$5 -> 0

Sheet 1. Project Summary
B2: ="Projections - "&Project_Name -> Projections - Serious Shea
B3: (in EUR, unless otherwise stated)
B5: Key Model Assumptions | E5: Unit | G5: Notes
B6: Project Info
C7: Project Name | F7: Serious Shea
C8: Location | F8: Senegal
C9: Project Start Date | E9: date | F9: 44927
C10: Project Validation Date | E10: date | F10: 45292
B12: Model assumptions
C13: Nominal or real terms | F13: Nominal | G13: Choose "Real" if the user would like to exclude the inflation impact.
C14: Discount rate | E14: % | F14: ='11.WACC'!D43 -> 0.135 | G14: Based on the proponent's estimated discount rate.
C15: Inflation rate | E15: % per annum | F15: =IF($F$13="Real",0,2%) -> 0.02 | G15: Based on the European Union's last 10-year average inflation rate as the cost and revenue estimates are in EUR.
C16: USD/EUR exchange rate | F16: =1.1015 -> 1.1015 | G16: Exchange rate as of April 27, 2023 by Bloomberg
B18: Revenue assumptions
C19: Carbon Credit Price
B20: 1 | C20: Scenario 1: Low Price | E20: EUR | F20: =8/F16 -> 7.2628234 | G20: Based on the similar project in Africa.
B21: 2 | C21: Scenario 2: Medium Price | E21: EUR | F21: 10 | G21: Based on the Proponent's expected pricing scenarios.
B22: 3 | C22: Scenario 3: High Price | E22: EUR | F22: =13.8/$F$16 -> 12.52837 | G22: Based on the lowest range of the ARR carbon prices published by Abatable
B23: 4 | C23: Scenario 4: Trove - Low Demand, Loose Supply | E23: EUR | F23: 9.9 | G23: Pricing scenario requested by Mirova. Source: Trove Intelligence
B24: 5 | C24: Scenario 5: Trove - High Demand, Loose Supply | E24: EUR | F24: 10.2 | G24: Pricing scenario requested by Mirova. Source: Trove Intelligence
B25: 6 | C25: Scenario 6: Trove - Low Demand,Tight Supply | E25: EUR | F25: 11.3 | G25: Pricing scenario requested by Mirova. Source: Trove Intelligence
B26: 7 | C26: Scenario 7: Trove - High Demand, Tight Supply | E26: EUR | F26: 11.9 | G26: Pricing scenario requested by Mirova. Source: Trove Intelligence
C28: User to Select Scenario for Carbon Credit Price | E28: EUR/VCU | F28: Scenario 2: Medium Price | G28: Choose the Carbon Credit Price Scenario here.
C29: Carbon Credit Price Increase | E29: % per annum | F29: =F15 -> 0.02 | G29: We assume that the carbon price will increase in-line with the inflation rate.
C31: Carbon Crediting Scenarios | F31: Total VCUs
B32: 1 | C32: Scenario 1: Low Crediting Scenario | E32: VCU | F32: ='4.1 Revenue Build - VCU'!E32 -> 6540628 | G32: These crediting scenarios originate from the carbon accounting model produced by EP Carbon.
B33: 2 | C33: Scenario 2: High Crediting Scenario | E33: VCU | F33: ='4.1 Revenue Build - VCU'!E33 -> 8089676
B34: 3 | C34: Scenario 3: Maximum Mitigation Potential | E34: VCU | F34: ='4.1 Revenue Build - VCU'!E34 -> 9753568
C36: User to Select Scenario for Carbon Crediting | F36: Scenario 2: High Crediting Scenario | G36: Choose the ARR VCU crediting scenario here.
B38: Cash Flow Summary | E38: Total | F38: Year 1-5 | G38: Year 6-10 | H38: Year 11-15 | I38: Year 16-20 | J38: Year 21-25 | K38: Year 26-31
B40: Cash Inflows
C41: ='2. NPV'!C9 -> Revenue from ARR | E41: =SUM(F41:K41) -> 1.123071e+08 | F41: =SUM('2. NPV'!H9:L9) -> 8435987.6 | G41: =SUM('2. NPV'!M9:Q9) -> 5848102.6 | H41: =SUM('2. NPV'!R9:V9) -> 19784719 | I41: =SUM('2. NPV'!W9:AA9) -> 21843928 | J41: =SUM('2. NPV'!AB9:AF9) -> 24117462 | K41: =SUM('2. NPV'!AG9:AL9) -> 32276901
C42: ='2. NPV'!C10 -> Revenue from Productive Activities | E42: =SUM(F42:K42) -> 7.7437181e+08 | F42: =SUM('2. NPV'!H10:L10) -> 31030346 | G42: =SUM('2. NPV'!M10:Q10) -> 1.0526043e+08 | H42: =SUM('2. NPV'!R10:V10) -> 1.2338335e+08 | I42: =SUM('2. NPV'!W10:AA10) -> 1.3959694e+08 | J42: =SUM('2. NPV'!AB10:AF10) -> 1.5794113e+08 | K42: =SUM('2. NPV'!AG10:AL10) -> 2.1715961e+08
C43: Grant Funding | E43: =SUM(F43:K43) -> 0 | F43: =SUM('2. NPV'!H11:L11) -> 0 | G43: =SUM('2. NPV'!M11:Q11) -> 0 | H43: =SUM('2. NPV'!R11:V11) -> 0 | I43: =SUM('2. NPV'!W11:AA11) -> 0 | J43: =SUM('2. NPV'!AB11:AF11) -> 0 | K43: =SUM('2. NPV'!AG11:AL11) -> 0
C44: Other Income | E44: =SUM(F44:K44) -> 0 | F44: =SUM('2. NPV'!H12:L12)+SUM('2. NPV'!H13:L13) -> 0 | G44: =SUM('2. NPV'!M13:Q13)+SUM('2. NPV'!M12:Q12) -> 0 | H44: =SUM('2. NPV'!R13:V13)+SUM('2. NPV'!R12:V12) -> 0 | I44: =SUM('2. NPV'!W13:AA13)+SUM('2. NPV'!W12:AA12) -> 0 | J44: =SUM('2. NPV'!AB13:AF13)+SUM('2. NPV'!AB12:AF12) -> 0 | K44: =SUM('2. NPV'!AG13:AL13)+SUM('2. NPV'!AG12:AL12) -> 0
B45: Total Cash Inflows | E45: =SUM(F45:L45) -> 8.8667891e+08 | F45: =SUM(F40:F44) -> 39466333 | G45: =SUM(G40:G44) -> 1.1110853e+08 | H45: =SUM(H40:H44) -> 1.4316807e+08 | I45: =SUM(I40:I44) -> 1.6144087e+08 | J45: =SUM(J40:J44) -> 1.8205859e+08 | K45: =SUM(K40:K44) -> 2.4943652e+08
B47: Cash Outflows
C48: Project Development Costs | E48: =SUM(F48:K48) -> 512173.4 | F48: =SUM('2. NPV'!H18:L18) -> 512173.4 | G48: =SUM('2. NPV'!M18:Q18) -> 0 | H48: =SUM('2. NPV'!R18:V18) -> 0 | I48: =SUM('2. NPV'!W18:AA18) -> 0 | J48: =SUM('2. NPV'!AB18:AF18) -> 0 | K48: =SUM('2. NPV'!AG18:AL18) -> 0
C49: Project Monitoring Costs | E49: =SUM(F49:K49) -> 5301107.4 | F49: =SUM('2. NPV'!H19:L19) -> 308221.78 | G49: =SUM('2. NPV'!M19:Q19) -> 722149.15 | H49: =SUM('2. NPV'!R19:V19) -> 859863.79 | I49: =SUM('2. NPV'!W19:AA19) -> 975798.49 | J49: =SUM('2. NPV'!AB19:AF19) -> 1021885.1 | K49: =SUM('2. NPV'!AG19:AL19) -> 1413189
C50: ARR Activity Costs | E50: =SUM(F50:K50) -> 71731731 | F50: =SUM('2. NPV'!H21:L26) -> 15122046 | G50: =SUM('2. NPV'!M21:Q26) -> 16547196 | H50: =SUM('2. NPV'!R21:V26) -> 8279448 | I50: =SUM('2. NPV'!W21:AA26) -> 8698429 | J50: =SUM('2. NPV'!AB21:AF26) -> 9758300.6 | K50: =SUM('2. NPV'!AG21:AL26) -> 13326312
C51: Productive Activity Costs | E51: =SUM(F51:K51) -> 1.272979e+08 | F51: =SUM('2. NPV'!H28:L31) -> 8178445.2 | G51: =SUM('2. NPV'!M28:Q31) -> 19821824 | H51: =SUM('2. NPV'!R28:V31) -> 19175841 | I51: =SUM('2. NPV'!W28:AA31) -> 21680231 | J51: =SUM('2. NPV'!AB28:AF31) -> 24556364 | K51: =SUM('2. NPV'!AG28:AL31) -> 33885194
C52: Increase in Net Working Capital | E52: =SUM(F52:K52) -> 9306349.9 | F52: =SUM('2. NPV'!H32:L32) -> 3251562.7 | G52: =SUM('2. NPV'!M32:Q32) -> 2289310.4 | H52: =SUM('2. NPV'!R32:V32) -> 728116.24 | I52: =SUM('2. NPV'!W32:AA32) -> 823796.69 | J52: =SUM('2. NPV'!AB32:AF32) -> 932050.34 | K52: =SUM('2. NPV'!AG32:AL32) -> 1281513.6
C53: Other expenses | E53: =SUM(F53:K53) -> 0 | F53: =SUM('2. NPV'!H33:L35) -> 0 | G53: =SUM('2. NPV'!M33:Q35) -> 0 | H53: =SUM('2. NPV'!R33:V35) -> 0 | I53: =SUM('2. NPV'!W33:AA35) -> 0 | J53: =SUM('2. NPV'!AB33:AF35) -> 0 | K53: =SUM('2. NPV'!AG33:AL35) -> 0
B54: Total Cash Outflows | E54: =SUM(E48:E53) -> 2.1414926e+08 | F54: =SUM(F48:F53) -> 27372449 | G54: =SUM(G48:G53) -> 39380479 | H54: =SUM(H48:H53) -> 29043269 | I54: =SUM(I48:I53) -> 32178255 | J54: =SUM(J48:J53) -> 36268600 | K54: =SUM(K48:K53) -> 49906208
B56: Net Cash Flow in Period | E56: =E45-E54 -> 6.7252965e+08 | F56: =F45-F54 -> 12093884 | G56: =G45-G54 -> 71728056 | H56: =H45-H54 -> 1.141248e+08 | I56: =I45-I54 -> 1.2926261e+08 | J56: =J45-J54 -> 1.4578999e+08 | K56: =K45-K54 -> 1.9953031e+08
B57: Beginning Cash Balance | E57: =F57 -> 0 | F57: ='2. NPV'!H39 -> 0 | G57: =F58 -> 12093884 | H57: =G58 -> 83821939 | I57: =H58 -> 1.9794674e+08 | J57: =I58 -> 3.2720936e+08 | K57: =J58 -> 4.7299934e+08
B58: Ending Cash Balance | E58: =E57+E56 -> 6.7252965e+08 | F58: =F57+F56 -> 12093884 | G58: =G57+G56 -> 83821939 | H58: =H57+H56 -> 1.9794674e+08 | I58: =I57+I56 -> 3.2720936e+08 | J58: =J57+J56 -> 4.7299934e+08 | K58: =K57+K56 -> 6.7252965e+08
B61: Return Summary | F61: Year 1-5 | G61: Year 6-10 | H61: Year 11-15 | I61: Year 16-20 | J61: Year 21-25 | K61: Year 26-31
B63: Net Cash Flow in Period | E63: =SUM(F63:K63) -> 6.7252965e+08 | F63: =F56 -> 12093884 | G63: =G56 -> 71728056 | H63: =H56 -> 1.141248e+08 | I63: =I56 -> 1.2926261e+08 | J63: =J56 -> 1.4578999e+08 | K63: =K56 -> 1.9953031e+08
B64: Discounted cash flow | E64: =SUM(F64:K64) -> 71659177 | F64: =SUM('2. NPV'!H54:L54) -> 5996164.5 | G64: =SUM('2. NPV'!M54:Q54) -> 22524539 | H64: =SUM('2. NPV'!R54:V54) -> 19533675 | I64: =SUM('2. NPV'!W54:AA54) -> 11753413 | J64: =SUM('2. NPV'!AB54:AF54) -> 7034274.6 | K64: =SUM('2. NPV'!AG54:AL54) -> 4817110.5
B66: NPV (31-year, pre-tax) | D66: USD | E66: ='2. NPV'!E60 -> 71659177
B67: IRR (31-year, pre-tax) | D67: % | E67: ='2. NPV'!E61 -> 0
B68: Discounted payback period | D68: Year | E68: ='2. NPV'!E62 -> 2.678633
B69: Capital requirement | D69: USD | E69: ='2. NPV'!E63 -> 1700000
B70: First 5-year Cash Flow (before discounting) | D70: USD | E70: =F56 -> 12093884
B71: First 10-year Cash Flow (before discounting) | D71: USD | E71: =SUM(F56:G56) -> 83821939
B74: Sensitivity Tables
C76: NPV Sensitivity | E76: Carbon Pricing Scenarios
E77: Low Price | F77: Medium Price | G77: High Price
C78: Carbon Crediting Scenarios | D78: Scenario 1: | E78: 68603327 | F78: 72313243 | G78: 75740147 | H78: << hardcoded
D79: Scenario 2: | E79: 71631568 | F79: 76523441 | G79: 81042137
D80: Scenario 3: | E80: 74884123 | F80: 81045506 | G80: 86736866
C82: IRR Sensitivity | E82: Carbon Pricing Scenarios
E83: =E77 -> Low Price | F83: =F77 -> Medium Price | G83: =G77 -> High Price
C84: Carbon Crediting Scenarios | D84: Scenario 1: | E84: 0.80352225 | F84: 0.82755482 | G84: 0.84987914 | H84: << hardcoded
D85: Scenario 2: | E85: 0.84927832 | F85: 0.89304635 | G85: 0.93484492
D86: Scenario 3: | E86: 0.90134108 | F86: 0.96980576 | G86: 1.037694
C88: Revenue | E88: Carbon Pricing Scenarios
E89: =E83 -> Low Price | F89: =F83 -> Medium Price | G89: =G83 -> High Price
C90: Carbon Crediting Scenarios | D90: Scenario 1: | E90: 1.0466175e+08 | F90: 1.403374e+08 | G90: 1.7329152e+08 | H90: << hardcoded
D91: Scenario 2: | E91: 1.2902356e+08 | F91: 1.7388056e+08 | G91: 2.1531563e+08
D92: Scenario 3: | E92: 1.5518994e+08 | F92: 2.099084e+08 | G92: 2.6045264e+08

Sheet 2. NPV
B2: ='1. Project Summary'!B2 -> Projections - Serious Shea
B3: ='1. Project Summary'!B3 -> (in EUR, unless otherwise stated)
B5: Net Present Value Calculations | D5: Unit | F5: Total | H5: =H47 -> 2024 | I5: =I47 -> 2025 | J5: =J47 -> 2026 | K5: =K47 -> 2027 | L5: =L47 -> 2028 | M5: =M47 -> 2029 | N5: =N47 -> 2030 | O5: =O47 -> 2031 | ... AL5: =AL47 -> 2054
F6: 2024-2054 | H6: Estimate | I6: Estimate | J6: Estimate | K6: Estimate | L6: Estimate | M6: Estimate | N6: Estimate | O6: Estimate | P6: Estimate | Q6: Estimate | R6: Estimate | S6: Estimate | T6: Estimate | U6: Estimate | V6: Estimate | W6: Estimate | X6: Estimate | Y6: Estimate | Z6: Estimate | AA6: Estimate | AB6: Estimate | AC6: Estimate | AD6: Estimate | AE6: Estimate | AF6: Estimate | AG6: Estimate | AH6: Estimate | AI6: Estimate | AJ6: Estimate | AK6: Estimate | AL6: Estimate
H7: =+'4.1 Revenue Build - VCU'!H$7 -> 1 | I7: =+'4.1 Revenue Build - VCU'!I$7 -> 2 | J7: =+'4.1 Revenue Build - VCU'!J$7 -> 3 | K7: =+'4.1 Revenue Build - VCU'!K$7 -> 4 | L7: =+'4.1 Revenue Build - VCU'!L$7 -> 5 | M7: =+'4.1 Revenue Build - VCU'!M$7 -> 6 | N7: =+'4.1 Revenue Build - VCU'!N$7 -> 7 | O7: =+'4.1 Revenue Build - VCU'!O$7 -> 8 | ... AL7: =+'4.1 Revenue Build - VCU'!AL$7 -> 31
C8: Cash Inflows
C9: Revenue from ARR | D9: EUR | F9: =SUM(H9:AL9) -> 1.123071e+08 | H9: ='4.1 Revenue Build - VCU'!H51 -> 3000000 | I9: ='4.1 Revenue Build - VCU'!I51 -> 2000000 | J9: ='4.1 Revenue Build - VCU'!J51 -> 2663550.9 | K9: ='4.1 Revenue Build - VCU'!K51 -> 609898.7 | L9: ='4.1 Revenue Build - VCU'!L51 -> 162538.01 | M9: ='4.1 Revenue Build - VCU'!M51 -> 366908.13 | N9: ='4.1 Revenue Build - VCU'!N51 -> 872190.27 | O9: ='4.1 Revenue Build - VCU'!O51 -> 754272.96 | ... AL9: ='4.1 Revenue Build - VCU'!AL51 -> 5649274.5
C10: Revenue from Productive Activities | D10: EUR | F10: =SUM(H10:AL10) -> 7.7437181e+08 | H10: ='4.2 Revenue Build - Other'!H40 -> 0 | I10: ='4.2 Revenue Build - Other'!I40 -> 640513.53 | J10: ='4.2 Revenue Build - Other'!J40 -> 6217535.7 | K10: ='4.2 Revenue Build - Other'!K40 -> 11217333 | L10: ='4.2 Revenue Build - Other'!L40 -> 12954963 | M10: ='4.2 Revenue Build - Other'!M40 -> 19267436 | N10: ='4.2 Revenue Build - Other'!N40 -> 20128254 | O10: ='4.2 Revenue Build - Other'!O40 -> 21020070 | ... AL10: ='4.2 Revenue Build - Other'!AL40 -> 38463729
C11: Grant Funding | D11: EUR | F11: =SUM(H11:AL11) -> 0
C12: Other income 1 | D12: EUR | F12: =SUM(H12:AL12) -> 0
C13: Other income 2 | D13: EUR | F13: =SUM(H13:AL13) -> 0
C14: Total Cash Inflows | F14: =SUM(H14:AL14) -> 8.8667891e+08 | H14: =SUM(H9:H13) -> 3000000 | I14: =SUM(I9:I13) -> 2640513.5 | J14: =SUM(J9:J13) -> 8881086.6 | K14: =SUM(K9:K13) -> 11827232 | L14: =SUM(L9:L13) -> 13117501 | M14: =SUM(M9:M13) -> 19634345 | N14: =SUM(N9:N13) -> 21000444 | O14: =SUM(O9:O13) -> 21774343 | ... AL14: =SUM(AL9:AL13) -> 44113003
C16: Cash Outflows
C17: Project Development and Monitoring Expenses
C18: Project Development Cost | D18: EUR | F18: =SUM(H18:AL18) -> 512173.4 | H18: ='5.1 Project Dev''t & Monitoring'!H24 -> 280980.48 | I18: ='5.1 Project Dev''t & Monitoring'!I24 -> 231192.92 | J18: ='5.1 Project Dev''t & Monitoring'!J24 -> 0 | K18: ='5.1 Project Dev''t & Monitoring'!K24 -> 0 | L18: ='5.1 Project Dev''t & Monitoring'!L24 -> 0 | M18: ='5.1 Project Dev''t & Monitoring'!M24 -> 0 | N18: ='5.1 Project Dev''t & Monitoring'!N24 -> 0 | O18: ='5.1 Project Dev''t & Monitoring'!O24 -> 0 | ... AL18: ='5.1 Project Dev''t & Monitoring'!AL24 -> 0
C19: Project Monitoring Cost | D19: EUR | F19: =SUM(H19:AL19) -> 5301107.4 | H19: ='5.1 Project Dev''t & Monitoring'!H57 -> 4167.0449 | I19: ='5.1 Project Dev''t & Monitoring'!I57 -> 66589.378 | J19: ='5.1 Project Dev''t & Monitoring'!J57 -> 60545.601 | K19: ='5.1 Project Dev''t & Monitoring'!K57 -> 91926.762 | L19: ='5.1 Project Dev''t & Monitoring'!L57 -> 84992.992 | M19: ='5.1 Project Dev''t & Monitoring'!M57 -> 119898.36 | N19: ='5.1 Project Dev''t & Monitoring'!N57 -> 114452.43 | O19: ='5.1 Project Dev''t & Monitoring'!O57 -> 170434.99 | ... AL19: ='5.1 Project Dev''t & Monitoring'!AL57 -> 225950.3
C20: ARR Costs
C21: ='5.2 Cost Build - ARR'!C134 -> Nursery - CAPEX | D21: EUR | F21: =SUM(H21:AL21) -> 1101992.1 | H21: ='5.2 Cost Build - ARR'!H134 -> 545540.62 | I21: ='5.2 Cost Build - ARR'!I134 -> 556451.44 | J21: ='5.2 Cost Build - ARR'!J134 -> 0 | K21: ='5.2 Cost Build - ARR'!K134 -> 0 | L21: ='5.2 Cost Build - ARR'!L134 -> 0 | M21: ='5.2 Cost Build - ARR'!M134 -> 0 | N21: ='5.2 Cost Build - ARR'!N134 -> 0 | O21: ='5.2 Cost Build - ARR'!O134 -> 0 | ... AL21: ='5.2 Cost Build - ARR'!AL134 -> 0
C22: ='5.2 Cost Build - ARR'!C135 -> Nursery - OPEX | D22: EUR | F22: =SUM(H22:AL22) -> 10716324 | H22: ='5.2 Cost Build - ARR'!H135 -> 816000 | I22: ='5.2 Cost Build - ARR'!I135 -> 1331712 | J22: ='5.2 Cost Build - ARR'!J135 -> 1358346.2 | K22: ='5.2 Cost Build - ARR'!K135 -> 1385513.2 | L22: ='5.2 Cost Build - ARR'!L135 -> 1413223.4 | M22: ='5.2 Cost Build - ARR'!M135 -> 1441487.9 | N22: ='5.2 Cost Build - ARR'!N135 -> 1470317.7 | O22: ='5.2 Cost Build - ARR'!O135 -> 1499724 | ... AL22: ='5.2 Cost Build - ARR'!AL135 -> 0
C23: ='5.2 Cost Build - ARR'!C136 -> Plantation & Transportation Cost | D23: EUR | F23: =SUM(H23:AL23) -> 5465325.4 | H23: ='5.2 Cost Build - ARR'!H136 -> 0 | I23: ='5.2 Cost Build - ARR'!I136 -> 416160 | J23: ='5.2 Cost Build - ARR'!J136 -> 679173.12 | K23: ='5.2 Cost Build - ARR'!K136 -> 692756.58 | L23: ='5.2 Cost Build - ARR'!L136 -> 706611.71 | M23: ='5.2 Cost Build - ARR'!M136 -> 720743.95 | N23: ='5.2 Cost Build - ARR'!N136 -> 735158.83 | O23: ='5.2 Cost Build - ARR'!O136 -> 749862 | ... AL23: ='5.2 Cost Build - ARR'!AL136 -> 0
C24: ='5.2 Cost Build - ARR'!C137 -> Maintenance cost | D24: EUR | F24: =SUM(H24:AL24) -> 3625378.3 | H24: ='5.2 Cost Build - ARR'!H137 -> 0 | I24: ='5.2 Cost Build - ARR'!I137 -> 0 | J24: ='5.2 Cost Build - ARR'!J137 -> 90202.68 | K24: ='5.2 Cost Build - ARR'!K137 -> 239217.51 | L24: ='5.2 Cost Build - ARR'!L137 -> 394156.85 | M24: ='5.2 Cost Build - ARR'!M137 -> 459474.27 | N24: ='5.2 Cost Build - ARR'!N137 -> 468663.75 | O24: ='5.2 Cost Build - ARR'!O137 -> 478037.03 | ... AL24: ='5.2 Cost Build - ARR'!AL137 -> 0
C25: ='5.2 Cost Build - ARR'!C138 -> Plantation Overhead | D25: EUR | F25: =SUM(H25:AL25) -> 43560757 | H25: ='5.2 Cost Build - ARR'!H138 -> 396060 | I25: ='5.2 Cost Build - ARR'!I138 -> 674967.48 | J25: ='5.2 Cost Build - ARR'!J138 -> 701931.74 | K25: ='5.2 Cost Build - ARR'!K138 -> 928306.66 | L25: ='5.2 Cost Build - ARR'!L138 -> 1044410.7 | M25: ='5.2 Cost Build - ARR'!M138 -> 1074613.7 | N25: ='5.2 Cost Build - ARR'!N138 -> 1188547.6 | O25: ='5.2 Cost Build - ARR'!O138 -> 1215202.8 | ... AL25: ='5.2 Cost Build - ARR'!AL138 -> 1969694.3
C26: ='5.2 Cost Build - ARR'!C144 -> Office Equipment & Vehicles | D26: EUR | F26: =SUM(H26:AL26) -> 7261954.5 | H26: ='5.2 Cost Build - ARR'!H144 -> 364670 | I26: ='5.2 Cost Build - ARR'!I144 -> 49894.2 | J26: ='5.2 Cost Build - ARR'!J144 -> 91166.85 | K26: ='5.2 Cost Build - ARR'!K144 -> 93337.474 | L26: ='5.2 Cost Build - ARR'!L144 -> 152235.78 | M26: ='5.2 Cost Build - ARR'!M144 -> 97863.138 | N26: ='5.2 Cost Build - ARR'!N144 -> 162697.69 | O26: ='5.2 Cost Build - ARR'!O144 -> 168248.03 | ... AL26: ='5.2 Cost Build - ARR'!AL144 -> 385438.51
C27: Productive Activity Costs
C28: ='5.3 Cost Build - Productive'!C128 -> Processing Centers - CAPEX | D28: EUR | F28: =SUM(H28:AL28) -> 8115482.1 | H28: ='5.3 Cost Build - Productive'!H128 -> 0 | I28: ='5.3 Cost Build - Productive'!I128 -> 735993.72 | J28: ='5.3 Cost Build - Productive'!J128 -> 772793.41 | K28: ='5.3 Cost Build - Productive'!K128 -> 811433.08 | L28: ='5.3 Cost Build - Productive'!L128 -> 852004.73 | M28: ='5.3 Cost Build - Productive'!M128 -> 894604.97 | N28: ='5.3 Cost Build - Productive'!N128 -> 939335.21 | O28: ='5.3 Cost Build - Productive'!O128 -> 986301.98 | ... AL28: ='5.3 Cost Build - Productive'!AL128 -> 0
C29: ='5.3 Cost Build - Productive'!C130 -> Processing Centers - OPEX | D29: EUR | F29: =SUM(H29:AL29) -> 50604091 | H29: ='5.3 Cost Build - Productive'!H130 -> 0 | I29: ='5.3 Cost Build - Productive'!I130 -> 97100.681 | J29: ='5.3 Cost Build - Productive'!J130 -> 407826.8 | K29: ='5.3 Cost Build - Productive'!K130 -> 691635.3 | L29: ='5.3 Cost Build - Productive'!L130 -> 814380.43 | M29: ='5.3 Cost Build - Productive'!M130 -> 1168019.3 | N29: ='5.3 Cost Build - Productive'!N130 -> 1251339.1 | O29: ='5.3 Cost Build - Productive'!O130 -> 1338590.6 | ... AL29: ='5.3 Cost Build - Productive'!AL130 -> 2572831
C30: ='5.3 Cost Build - Productive'!C131 -> Productive Activities' Overhead | D30: EUR | F30: =SUM(H30:AL30) -> 57052660 | H30: ='5.3 Cost Build - Productive'!H131 -> 22740 | I30: ='5.3 Cost Build - Productive'!I131 -> 181609.8 | J30: ='5.3 Cost Build - Productive'!J131 -> 392907.97 | K30: ='5.3 Cost Build - Productive'!K131 -> 568939.19 | L30: ='5.3 Cost Build - Productive'!L131 -> 762870.12 | M30: ='5.3 Cost Build - Productive'!M131 -> 959745.18 | N30: ='5.3 Cost Build - Productive'!N131 -> 1163276.5 | O30: ='5.3 Cost Build - Productive'!O131 -> 1373376.8 | ... AL30: ='5.3 Cost Build - Productive'!AL131 -> 2799261.6
C31: ='5.2 Cost Build - ARR'!C144 -> Office Equipment & Vehicles | D31: EUR | F31: =SUM(H31:AL31) -> 11525667 | H31: ='5.3 Cost Build - Productive'!H136 -> 206162 | I31: ='5.3 Cost Build - Productive'!I136 -> 196747.2 | J31: ='5.3 Cost Build - Productive'!J136 -> 219663.23 | K31: ='5.3 Cost Build - Productive'!K136 -> 212068.12 | L31: ='5.3 Cost Build - Productive'!L136 -> 231569.44 | M31: ='5.3 Cost Build - Productive'!M136 -> 228763.68 | N31: ='5.3 Cost Build - Productive'!N136 -> 243915.52 | O31: ='5.3 Cost Build - Productive'!O136 -> 252214.78 | ... AL31: ='5.3 Cost Build - Productive'!AL136 -> 643344.37
C32: Increase in Net Working Capital | D32: EUR | F32: =SUM(H32:AL32) -> 9306349.9 | H32: =-'7.CFS'!H13 -> -5589.0411 | I32: =-'7.CFS'!I13 -> 105077.16 | J32: =-'7.CFS'!J13 -> 1457551.4 | K32: =-'7.CFS'!K13 -> 1295934.9 | L32: =-'7.CFS'!L13 -> 398588.24 | M32: =-'7.CFS'!M13 -> 1648233.4 | N32: =-'7.CFS'!N13 -> 150754.39 | O32: =-'7.CFS'!O13 -> 155229.49 | ... AL32: =-'7.CFS'!AL13 -> 226984.15
C33: Other expenses 1 | D33: EUR | F33: =SUM(H33:AL33) -> 0
C34: Other expenses 2 | D34: EUR | F34: =SUM(H34:AL34) -> 0
C35: Other expenses 3 | D35: EUR | F35: =SUM(H35:AL35) -> 0
C36: Total Cash Outflows | F36: =SUM(F17:F35) -> 2.1414926e+08 | H36: =SUM(H17:H35) -> 2630731.1 | I36: =SUM(I17:I35) -> 4643496 | J36: =SUM(J17:J35) -> 6232109.1 | K36: =SUM(K17:K35) -> 7011068.7 | L36: =SUM(L17:L35) -> 6855044.4 | M36: =SUM(M17:M35) -> 8813447.8 | N36: =SUM(N17:N35) -> 7888458.6 | O36: =SUM(O17:O35) -> 8387222.4 | ... AL36: =SUM(AL17:AL35) -> 8823504.2
C38: Net Cash Flow in Period | D38: EUR | F38: =SUM(H38:AL38) -> 6.7252965e+08 | H38: =H14-H36 -> 369268.89 | I38: =I14-I36 -> -2002982.4 | J38: =J14-J36 -> 2648977.5 | K38: =K14-K36 -> 4816162.9 | L38: =L14-L36 -> 6262457 | M38: =M14-M36 -> 10820897 | N38: =N14-N36 -> 13111985 | O38: =O14-O36 -> 13387120 | ... AL38: =AL14-AL36 -> 35289499
C39: Beginning Cash Balance | D39: EUR | H39: =G40 -> 0 | I39: =H40 -> 369268.89 | J39: =I40 -> -1633713.6 | K39: =J40 -> 1015263.9 | L39: =K40 -> 5831426.8 | M39: =L40 -> 12093884 | N39: =M40 -> 22914781 | O39: =N40 -> 36026766 | ... AL39: =AK40 -> 6.3724015e+08
C40: Ending Cash Balance | D40: EUR | G40: 0 | H40: =H38+H39 -> 369268.89 | I40: =I38+I39 -> -1633713.6 | J40: =J38+J39 -> 1015263.9 | K40: =K38+K39 -> 5831426.8 | L40: =L38+L39 -> 12093884 | M40: =M38+M39 -> 22914781 | N40: =N38+N39 -> 36026766 | O40: =O38+O39 -> 49413886 | ... AL40: =AL38+AL39 -> 6.7252965e+08
C43: Project Returns | D43: Unit
C44: NPV Date | D44: date | E44: 44927
C45: Discount Rate | D45: % | E45: ='1. Project Summary'!$F$14 -> 0.135
C47: Year | D47: year | H47: 2024 | I47: =H47+1 -> 2025 | J47: =I47+1 -> 2026 | K47: =J47+1 -> 2027 | L47: =K47+1 -> 2028 | M47: =L47+1 -> 2029 | N47: =M47+1 -> 2030 | O47: =N47+1 -> 2031 | P47: =O47+1 -> 2032 | ... AL47: =AK47+1 -> 2054
C48: Period Start Date | D48: date | E48: =H48 -> 45292 | H48: =DATE(H$47,1,1) -> 45292 | I48: =DATE(I$47,1,1) -> 45658 | J48: =DATE(J$47,1,1) -> 46023 | K48: =DATE(K$47,1,1) -> 46388 | L48: =DATE(L$47,1,1) -> 46753 | M48: =DATE(M$47,1,1) -> 47119 | N48: =DATE(N$47,1,1) -> 47484 | O48: =DATE(O$47,1,1) -> 47849 | ... AL48: =DATE(AL$47,1,1) -> 56250
C49: Period End Date | D49: date | E49: =AL49 -> 56614 | H49: =EOMONTH(H$48,12-1) -> 45657 | I49: =EOMONTH(I$48,12-1) -> 46022 | J49: =EOMONTH(J$48,12-1) -> 46387 | K49: =EOMONTH(K$48,12-1) -> 46752 | L49: =EOMONTH(L$48,12-1) -> 47118 | M49: =EOMONTH(M$48,12-1) -> 47483 | N49: =EOMONTH(N$48,12-1) -> 47848 | O49: =EOMONTH(O$48,12-1) -> 48213 | ... AL49: =EOMONTH(AL$48,12-1) -> 56614
C50: Days from NPV to Period End | D50: days | H50: =H49-NPV_Date+1 -> 731 | I50: =I49-NPV_Date+1 -> 1096 | J50: =J49-NPV_Date+1 -> 1461 | K50: =K49-NPV_Date+1 -> 1826 | L50: =L49-NPV_Date+1 -> 2192 | M50: =M49-NPV_Date+1 -> 2557 | N50: =N49-NPV_Date+1 -> 2922 | O50: =O49-NPV_Date+1 -> 3287 | ... AL50: =AL49-NPV_Date+1 -> 11688
C51: Discount Factor | D51: factor | H51: =IF(H$50<0,0,1/(1+Discount_Rate)^(H$50/365)) -> 0.77599264 | I51: =IF(I$50<0,0,1/(1+Discount_Rate)^(I$50/365)) -> 0.68369396 | J51: =IF(J$50<0,0,1/(1+Discount_Rate)^(J$50/365)) -> 0.60237353 | K51: =IF(K$50<0,0,1/(1+Discount_Rate)^(K$50/365)) -> 0.53072558 | L51: =IF(L$50<0,0,1/(1+Discount_Rate)^(L$50/365)) -> 0.46743743 | M51: =IF(M$50<0,0,1/(1+Discount_Rate)^(M$50/365)) -> 0.41183914 | N51: =IF(N$50<0,0,1/(1+Discount_Rate)^(N$50/365)) -> 0.36285387 | O51: =IF(O$50<0,0,1/(1+Discount_Rate)^(O$50/365)) -> 0.31969504 | ... AL51: =IF(AL$50<0,0,1/(1+Discount_Rate)^(AL$50/365)) -> 0.017335128
C53: Net Cash Flow (pre-tax) | D53: EUR | F53: =SUM(H53:AL53) -> 6.7252965e+08 | H53: =H38 -> 369268.89 | I53: =I38 -> -2002982.4 | J53: =J38 -> 2648977.5 | K53: =K38 -> 4816162.9 | L53: =L38 -> 6262457 | M53: =M38 -> 10820897 | N53: =N38 -> 13111985 | O53: =O38 -> 13387120 | ... AL53: =AL38 -> 35289499
C54: Discounted cash flow | F54: =SUM(H54:AL54) -> 71659177 | H54: =H53*H51 -> 286549.94 | I54: =I53*I51 -> -1369427 | J54: =J53*J51 -> 1595673.9 | K54: =K53*K51 -> 2556060.8 | L54: =L53*L51 -> 2927306.8 | M54: =M53*M51 -> 4456468.8 | N54: =N53*N51 -> 4757734.6 | O54: =O53*O51 -> 4279795.9 | ... AL54: =AL53*AL51 -> 611747.97
C56: Cumulative cash flow | H56: =H54 -> 286549.94 | I56: =H56+I54 -> -1082877.1 | J56: =I56+J54 -> 512796.88 | K56: =J56+K54 -> 3068857.7 | L56: =K56+L54 -> 5996164.5 | M56: =L56+M54 -> 10452633 | N56: =M56+N54 -> 15210368 | O56: =N56+O54 -> 19490164 | P56: =O56+P54 -> 23648091 | ... AL56: =AK56+AL54 -> 71659177
C57: Year fraction | H57: =IF(H56<0,0,-G56/H54) -> 0 | I57: =IF(I56<0,0,-H56/I54) -> 0 | J57: =IF(J56<0,0,-I56/J54) -> 0.67863304 | K57: =IF(K56<0,0,-J56/K54) -> -0.20061998 | L57: =IF(L56<0,0,-K56/L54) -> -1.0483553 | M57: =IF(M56<0,0,-L56/M54) -> -1.3454968 | N57: =IF(N56<0,0,-M56/N54) -> -2.196977 | O57: =IF(O56<0,0,ABS(N56)/O54) -> 3.5539938 | P57: =IF(P56<0,0,ABS(O56)/P54) -> 4.6874713 | Q57: =IF(Q56<0,0,ABS(P56)/Q54) -> 4.8532674 | R57: =IF(R56<0,0,ABS(Q56)/R54) -> 6.0661091 | S57: =IF(S56<0,0,ABS(R56)/S54) -> 7.7757351 | T57: =IF(T56<0,0,ABS(S56)/T54) -> 9.641732 | U57: =IF(U56<0,0,ABS(T56)/U54) -> 11.813849 | V57: =IF(V56<0,0,ABS(U56)/V54) -> 14.170305 | ... AL57: =IF(AL56<0,0,ABS(AK56)/AL54) -> 116.1384
C60: NPV (31-year, pre-tax) | D60: EUR | E60: =SUM(H54:AL54) -> 71659177
C61: IRR (31-year, pre-tax) | D61: %
C62: Discounted payback period | D62: years | E62: {=IFERROR(COUNTIF(I56:AL56,"<0")+INDEX(I57:AL57,(COUNTIF(I56:AL56,"<0")+1)),">31")+1} -> 2.678633
C63: Capital requirement (inc. pre-sales) | D63: EUR | E63: =-ROUNDUP(MIN(H40:AL40),-5) -> 1700000
Q300: =$G300*Q$5 -> 0

Sheet 3. Assumptions
B2: ='1. Project Summary'!B2 -> Projections - Serious Shea
B3: ='1. Project Summary'!B3 -> (in EUR, unless otherwise stated)
B5: Revenue Assumptions | D5: Unit
B7: Revenues from Productive Activities | E7: Price | F7: Price CAGR | G7: Revenue Attributable to Serious Shea
B8: 1 | C8: Refined Oil | D8: EUR per metric ton | E8: 30000 | F8: 0.025 | G8: 1 | I8: Based on the benchmark price discounted to ~60-70%
B9: 2 | C9: Moringa Leaves | D9: EUR per metric ton | E9: 5000 | F9: 0.025 | G9: 1 | I9: Based on the benchmark price discounted to ~60-70%
B10: 3 | C10: Dry Mangos | D10: EUR per metric ton | E10: 3500 | F10: 0.025 | G10: 0.3 | I10: Based on the benchmark price discounted to ~60-70%
B11: 4 | C11: Shea Butter | D11: EUR per metric ton | E11: 2000 | F11: 0.025 | G11: 0.3 | I11: Based on the benchmark price discounted to ~60-70%
B12: 5 | C12: Fertilisers Compost | D12: EUR per metric ton | E12: 100 | F12: 0.025 | G12: 1 | I12: Based on the benchmark price discounted to ~20%
B13: 6 | C13: Biochar | D13: EUR per metric ton
B15: Revenue from Processing Fee
B16: 3 | C16: Dry Mangos | D16: EUR per metric ton | E16: 100 | F16: 0.025
B17: 4 | C17: Shea Butter | D17: EUR per metric ton | E17: 200 | F17: 0.025
B19: Cost Inputs/Assumptions | D19: Unit
B20: 5.1 Project Development & Monitoring
B21: Timing Assumptions
C22: First Year of Credit Issuance | D22: years | F22: 3 | G22: The model assumes the First Year of Credit Issuance will happen in 2025.
C23: Interval between Credit Issuances/Sales after First Issuance | D23: years | F23: 1 | G23: The Projects assumes that verifications and credit issuances will take place in the same years. This can be changed to 2 years depending on the sales & marketing strategy.
C24: Year of Validation | D24: years | F24: 2 | G24: The typical timeline that we see for project development from Feasibility Assessment to Validation is 12-18 months. We assume that the Project will be validated in 2024.
C25: First Verification Year | D25: years | F25: 2 | G25: Same time as validation.
C26: Verification Interval Thereafter | D26: years | F26: 2
C27: Frequency of Revisions | D27: years | F27: 6 | G27: The baseline revision is subject to changes by Verra. We assume it will happen every 6 years based on its existing guideline.
B29: Project Development Work
C30: Feasibility assessment | D30: USD | F30: 73250 | G30: Feasibility Assessment Fee to EP Carbon | H30: Low | I30: High
C31: Work plan | D31: USD | F31: =AVERAGE(H31:I31) -> 5000 | H31: 0 | I31: 10000 | J31: Provisional estimates included in the Feasibility Assessment proposal
C32: Project Description Document | D32: USD | F32: =AVERAGE(H32:I32) -> 200000 | H32: =250000-H34 -> 170000 | I32: =350000-I34 -> 230000 | J32: Provisional estimates included in the Feasibility Assessment proposal
C33: Audit support to issuance | D33: USD | F33: =AVERAGE(H33:I33) -> 62500 | H33: 50000 | I33: 75000 | J33: Provisional estimates included in the Feasibility Assessment proposal
C34: First MIR | D34: USD | F34: =AVERAGE(H34:I34) -> 100000 | H34: 80000 | I34: 120000 | J34: Provisional estimates included in the Feasibility Assessment proposal (PDD + MIR ranges between US$250k and US$350k)
C35: VCS + CCB Validation | D35: USD | F35: 22500 | G35: Estimated fee to VCS for the assessment of the Project's conformance to VCS rules and applied methodology. CCB Validation is US$2,500 per CCB Standards Fee Schedule v3.4.
C36: Additional costs for CCB | D36: USD | F36: 100000 | G36: EP Carbon estimate.
B38: Project Monitoring Work
C39: Verra Registry Account Opening Fee VCS | D39: USD | F39: 500 | G39: VCS Program Fee Schedule v4.3 | I39: https://verra.org/wp-content/uploads/2023/03/Program-Fee-Schedule-v4.3-FINAL.pdf
C40: VCS Account maintenance fee | D40: USD per annum | F40: 500 | G40: VCS Program Fee Schedule v4.3
C41: VCS Pipeline Listing request fee | D41: USD | F41: 1000 | G41: VCS Program Fee Schedule v4.3
C42: VCS Project registeration request review fee | D42: USD | F42: 2500 | G42: VCS Program Fee Schedule v4.3
C43: VCU Issuance levy | D43: USD per VCU | F43: 0.2 | G43: VCS Program Fee Schedule v4.3
C44: CCB Label fee | D44: USD per label | F44: 0.07 | G44: CCB Program Fee Schedule v3.5 | I44: https://verra.org/wp-content/uploads/2023/03/CCB-Standards-Fee-Schedule-v3.5-final.pdf
C45: CCB Account maintenance fee | D45: USD | F45: 500 | G45: CCB Program Fee Schedule v3.5
C46: VCS Verification | D46: USD | F46: 15000 | G46: EP Carbon estimate for the verification audit and audit preparation
C47: CCB Verification | D47: USD | F47: 5000 | G47: CCB Program Fee Schedule v3.5 | I47: For each application for CCB certfication
C48: VCS Baseline Revision and Validation | D48: USD | F48: 18000 | G48: EP Carbon estimate.
C49: Subsequent MIRs Cost per Year | D49: USD | F49: 50000 | G49: EP Carbon estimate.
B51: 5.2 Cost Build - ARR
E52: 2023 | F52: =E52+1 -> 2024 | G52: =F52+1 -> 2025 | H52: =G52+1 -> 2026 | I52: =H52+1 -> 2027 | J52: =I52+1 -> 2028 | K52: =J52+1 -> 2029 | L52: =K52+1 -> 2030 | M52: =L52+1 -> 2031 | ... O52: =N52+1 -> 2033
C53: Trees Produced | D53: # of trees | E53: 1000000 | F53: 1600000 | G53: 1600000 | H53: 1600000 | I53: 1600000 | J53: 1600000 | K53: 1600000 | L53: 1600000 | M53: =0 -> 0 | N53: =M53 -> 0 | O53: =N53 -> 0
C54: Total Trees Produced | D54: # of trees | E54: =SUM($E53:E$53) -> 1000000 | F54: =SUM($E53:F$53) -> 2600000 | G54: =SUM($E53:G$53) -> 4200000 | H54: =SUM($E53:H$53) -> 5800000 | I54: =SUM($E53:I$53) -> 7400000 | J54: =SUM($E53:J$53) -> 9000000 | K54: =SUM($E53:K$53) -> 10600000 | L54: =SUM($E53:L$53) -> 12200000 | ... O54: =SUM($E53:O$53) -> 12200000
C56: Tree Loss | E56: 0.15
B58: Nursery Costs
C59: Land required per nursery | D59: ha | E59: 15
C60: Production capacity per nursery | D60: seedlings per annum | E60: 1000000
C63: Nursery CAPEX | E63: Unit cost (EUR) | F63: Quantity | G63: Cost (EUR)
C64: Land Acquisition | D64: per ha | E64: 5000 | F64: 15 | G64: =E64*F64 -> 75000 | H64: Land
C65: Fence | D65: per meter | E65: 10 | F65: 3700 | G65: =E65*F65 -> 37000 | H65: Buildings
C66: Shelters (40,000 sq.m) | D66: per unit | E66: 1000 | F66: 50 | G66: =E66*F66 -> 50000 | H66: Buildings
C67: Office and Storage | D67: per unit | E67: 25000 | F67: 2 | G67: =E67*F67 -> 50000 | H67: Buildings
C68: Wells | D68: per item | E68: 10937.5 | F68: 2 | G68: =E68*F68 -> 21875 | H68: Irrigation
C69: Solar Water Pump | D69: per item | E69: 15000 | F69: 2 | G69: =E69*F69 -> 30000 | H69: Irrigation
C70: Water Storage (10m3) | D70: per item | E70: 2343.75 | F70: 5 | G70: =E70*F70 -> 11718.75 | H70: Irrigation
C71: Pipes and Drip | D71: Lot | E71: 50000 | F71: 1 | G71: =E71*F71 -> 50000 | H71: Irrigation
C72: Water Tanks (800L) | D72: per item | E72: 800 | F72: 30 | G72: =E72*F72 -> 24000 | H72: Irrigation
C73: Nursery Trays | D73: Per item | E73: 5 | F73: =1000000/50 -> 20000 | G73: =E73*F73 -> 100000 | H73: Nursery Trays
C74: Pick-up Truck | D74: per item | E74: 31250 | F74: 1 | G74: =E74*F74 -> 31250 | H74: Vehicles
C75: Tractor | D75: per item | E75: 20000 | F75: 2 | G75: =E75*F75 -> 40000 | H75: Vehicles
C76: Trailers for Seedling Transport | D76: per item | E76: 7000 | F76: 2 | G76: =E76*F76 -> 14000 | H76: Vehicles
C77: Total CAPEX per nursery | G77: =SUM(G64:G76) -> 534843.75
E79: 2023 | F79: =E79+1 -> 2024 | G79: =F79+1 -> 2025 | H79: =G79+1 -> 2026 | I79: =H79+1 -> 2027 | J79: =I79+1 -> 2028 | K79: =J79+1 -> 2029 | L79: =K79+1 -> 2030 | M79: =L79+1 -> 2031 | ... O79: =N79+1 -> 2033
C80: Nurseries to be added | E80: 1 | F80: 1 | G80: 0 | H80: 0 | I80: 0 | J80: =I80 -> 0 | K80: =J80 -> 0 | L80: =K80 -> 0 | M80: =L80 -> 0 | N80: =M80 -> 0 | O80: =N80 -> 0
C81: Total nurseries | E81: =SUM($E$80:E80) -> 1 | F81: =SUM($E$80:F80) -> 2 | G81: =SUM($E$80:G80) -> 2 | H81: =SUM($E$80:H80) -> 2 | I81: =SUM($E$80:I80) -> 2 | J81: =SUM($E$80:J80) -> 2 | K81: =SUM($E$80:K80) -> 2 | L81: =SUM($E$80:L80) -> 2 | ... O81: =SUM($E$80:O80) -> 2
C83: Nursery OPEX
E84: Unit cost
C85: Opex Nursery, Production fees to Cooperatives | D85: EUR per tree | E85: 0.5
C86: Supplies | D86: EUR per tree | E86: 0.3
B88: Plantation Costs
C90: Plantation OPEX | E90: Unit cost
C91: Plantation and Transport fee to the Cooperatives | D91: EUR per tree | E91: 0.4
C92: Maintenance by Cooperatives | D92: EUR per tree | E92: 0.1
B94: Plantation Overhead
B97: Salary | D97: Annual Salary | E97: Annual Salary CAGR | G97: ='2. NPV'!H$5 -> 2024 | H97: ='2. NPV'!I$5 -> 2025 | I97: ='2. NPV'!J$5 -> 2026 | J97: ='2. NPV'!K$5 -> 2027 | K97: ='2. NPV'!L$5 -> 2028 | L97: ='2. NPV'!M$5 -> 2029 | M97: ='2. NPV'!N$5 -> 2030 | N97: ='2. NPV'!O$5 -> 2031 | O97: 2031 & Beyond
C98: Country Manager | D98: 50000 | E98: 0.02 | F98: Headcount | G98: 1 | H98: 1 | I98: 1 | J98: 1 | K98: 1 | L98: 1 | M98: 1 | N98: 1 | O98: 1
C99: Director of Reforestation Operations | D99: 25000 | E99: 0.02 | F99: Headcount | G99: =0 -> 0 | H99: 1 | I99: 1 | J99: 1 | K99: 1 | L99: 1 | M99: 1 | N99: 1 | O99: 1
C100: CFO | D100: 25000 | E100: 0.02 | F100: Headcount | G100: 1 | H100: 1 | I100: 1 | J100: 1 | K100: 1 | L100: 1 | M100: 1 | N100: 1 | O100: 1
C101: Director of HR | D101: 25000 | E101: 0.02 | F101: Headcount | G101: =0 -> 0 | H101: 1 | I101: 1 | J101: 1 | K101: 1 | L101: 1 | M101: 1 | N101: 1 | O101: 1
C102: Director of Partnership&ITC | D102: 25000 | E102: 0.02 | F102: Headcount | G102: 1 | H102: 1 | I102: 1 | J102: 1 | K102: 1 | L102: 1 | M102: 1 | N102: 1 | O102: 1
C103: Managers | D103: 10000 | E103: 0.02 | F103: Headcount | G103: 10 | H103: 4 | I103: 4 | J103: 4 | K103: 6 | L103: 6 | M103: 8 | N103: 8 | O103: 8
C104: Technical Staff | D104: 8000 | E104: 0.02 | F104: Headcount | G104: =4 -> 4 | H104: 4 | I104: 4 | J104: 4 | K104: 6 | L104: 6 | M104: 8 | N104: 8 | O104: 8
C105: Forest Engineer | D105: 8000 | E105: 0.02 | F105: Headcount | G105: 2 | H105: 2 | I105: 2 | J105: 2 | K105: 3 | L105: 3 | M105: 4 | N105: 4 | O105: 4
C106: Employees | D106: 3000 | E106: 0.02 | F106: Headcount | G106: =8 -> 8 | H106: 8 | I106: 8 | J106: 8 | K106: 12 | L106: 12 | M106: 16 | N106: 16 | O106: 16
C107: Executive Secretary | D107: 4000 | E107: 0.02 | F107: Headcount | G107: 1 | H107: 1 | I107: 1 | J107: 1 | K107: 1 | L107: 1 | M107: 1 | N107: 1 | O107: 1
C108: Secretaries | D108: 3000 | E108: 0.02 | F108: Headcount | G108: 7 | H108: 3 | I108: 3 | J108: 3 | K108: 4 | L108: 4 | M108: 5 | N108: 5 | O108: 5
C109: Trainees/Students | D109: 1200 | E109: 0.02 | F109: Headcount | G109: 10 | H109: 10 | I109: 10 | J109: 10 | K109: 15 | L109: 15 | M109: 20 | N109: 20 | O109: 20
C110: Drivers | D110: 2500 | E110: 0.02 | F110: Headcount | G110: 4 | H110: 4 | I110: 4 | J110: 4 | K110: 6 | L110: 6 | M110: 8 | N110: 8 | O110: 8
C111: Accountant | D111: 2500 | E111: 0.02 | F111: Headcount | G111: 2 | H111: 2 | I111: 2 | J111: 2 | K111: 3 | L111: 3 | M111: 4 | N111: 4 | O111: 4
C112: Field Agent | D112: 2500 | E112: 0.02 | F112: Headcount | G112: 2 | H112: 2 | I112: 2 | J112: 2 | K112: 3 | L112: 3 | M112: 4 | N112: 4 | O112: 4
C113: Maintenance Personnel | D113: 1500 | E113: 0.02 | F113: Headcount | G113: 8 | H113: 4 | I113: 4 | J113: 4 | K113: 6 | L113: 6 | M113: 8 | N113: 8 | O113: 8
C114: Security | D114: 1500 | E114: 0.02 | F114: Headcount | G114: 8 | H114: 5 | I114: 5 | J114: 5 | K114: 7 | L114: 7 | M114: 7 | N114: 7 | O114: 7
F115: Total headcount | G115: =SUM(G98:G114) -> 69 | H115: =SUM(H98:H114) -> 54 | I115: =SUM(I98:I114) -> 54 | J115: =SUM(J98:J114) -> 54 | K115: =SUM(K98:K114) -> 77 | L115: =SUM(L98:L114) -> 77 | M115: =SUM(M98:M114) -> 98 | N115: =SUM(N98:N114) -> 98 | O115: =SUM(O98:O114) -> 98
B117: Production and Harvesting Service Fees for Moringa | E117: Unit cost (EUR)
C118: Production | D118: per kg | E118: 0.5
C119: Harvesting | D119: per kg | E119: =E118 -> 0.5
B121: Rental | G121: ='2. NPV'!H$5 -> 2024 | H121: ='2. NPV'!I$5 -> 2025 | I121: ='2. NPV'!J$5 -> 2026 | J121: ='2. NPV'!K$5 -> 2027 | K121: ='2. NPV'!L$5 -> 2028 | L121: 2028 & Beyond
...

Sheet 4.1 Revenue Build - VCU
B2: ='1. Project Summary'!B2 -> Projections - Serious Shea
B3: ='1. Project Summary'!B3 -> (in EUR, unless otherwise stated)
B5: Revenue Build | D5: Unit | H5: ='2. NPV'!H5 -> 2024 | I5: ='2. NPV'!I5 -> 2025 | J5: ='2. NPV'!J5 -> 2026 | K5: ='2. NPV'!K5 -> 2027 | L5: ='2. NPV'!L5 -> 2028 | M5: ='2. NPV'!M5 -> 2029 | N5: ='2. NPV'!N5 -> 2030 | O5: ='2. NPV'!O5 -> 2031 | ... AL5: ='2. NPV'!AL5 -> 2054
H6: =Period_Start -> 1 | I6: =H6+1 -> 2 | J6: =I6+1 -> 3 | K6: =J6+1 -> 4 | L6: =K6+1 -> 5 | M6: =L6+1 -> 6 | N6: =M6+1 -> 7 | O6: =N6+1 -> 8 | P6: =O6+1 -> 9 | ... AL6: =AK6+1 -> 31
C7: Year count | H7: 1 | I7: =+H7+1 -> 2 | J7: =+I7+1 -> 3 | K7: =+J7+1 -> 4 | L7: =+K7+1 -> 5 | M7: =+L7+1 -> 6 | N7: =+M7+1 -> 7 | O7: =+N7+1 -> 8 | P7: =+O7+1 -> 9 | ... AL7: =+AK7+1 -> 31
C8: Credit Issuance Dates
C9: First Year of Credit Issuance | D9: year | E9: ='3. Assumptions'!F22 -> 3
C10: Interval between Credit Issuances | D10: year | E10: ='3. Assumptions'!F23 -> 1
C11: Year for Flag Credit Issuance | H11: =IF('4.1 Revenue Build - VCU'!H$6=34,1,IF('4.1 Revenue Build - VCU'!H6<'4.1 Revenue Build - VCU'!$E$9,0,IF('4.1 Revenue Build - VCU'!H6='4.1 Revenue Build - VCU'!$E$9,1,IF(MOD('4.1 Revenue Build - VCU'!H$6-'4.1 Revenue Build - VCU'!$E$9,'4.1 Revenue Build - VCU'!$E$10)=0,1,0)))) -> 0 | I11: =IF('4.1 Revenue Build - VCU'!I$6=34,1,IF('4.1 Revenue Build - VCU'!I6<'4.1 Revenue Build - VCU'!$E$9,0,IF('4.1 Revenue Build - VCU'!I6='4.1 Revenue Build - VCU'!$E$9,1,IF(MOD('4.1 Revenue Build - VCU'!I$6-'4.1 Revenue Build - VCU'!$E$9,'4.1 Revenue Build - VCU'!$E$10)=0,1,0)))) -> 0 | J11: =IF('4.1 Revenue Build - VCU'!J$6=34,1,IF('4.1 Revenue Build - VCU'!J6<'4.1 Revenue Build - VCU'!$E$9,0,IF('4.1 Revenue Build - VCU'!J6='4.1 Revenue Build - VCU'!$E$9,1,IF(MOD('4.1 Revenue Build - VCU'!J$6-'4.1 Revenue Build - VCU'!$E$9,'4.1 Revenue Build - VCU'!$E$10)=0,1,0)))) -> 1 | K11: =IF('4.1 Revenue Build - VCU'!K$6=34,1,IF('4.1 Revenue Build - VCU'!K6<'4.1 Revenue Build - VCU'!$E$9,0,IF('4.1 Revenue Build - VCU'!K6='4.1 Revenue Build - VCU'!$E$9,1,IF(MOD('4.1 Revenue Build - VCU'!K$6-'4.1 Revenue Build - VCU'!$E$9,'4.1 Revenue Build - VCU'!$E$10)=0,1,0)))) -> 1 | L11: =IF('4.1 Revenue Build - VCU'!L$6=34,1,IF('4.1 Revenue Build - VCU'!L6<'4.1 Revenue Build - VCU'!$E$9,0,IF('4.1 Revenue Build - VCU'!L6='4.1 Revenue Build - VCU'!$E$9,1,IF(MOD('4.1 Revenue Build - VCU'!L$6-'4.1 Revenue Build - VCU'!$E$9,'4.1 Revenue Build - VCU'!$E$10)=0,1,0)))) -> 1 | M11: =IF('4.1 Revenue Build - VCU'!M$6=34,1,IF('4.1 Revenue Build - VCU'!M6<'4.1 Revenue Build - VCU'!$E$9,0,IF('4.1 Revenue Build - VCU'!M6='4.1 Revenue Build - VCU'!$E$9,1,IF(MOD('4.1 Revenue Build - VCU'!M$6-'4.1 Revenue Build - VCU'!$E$9,'4.1 Revenue Build - VCU'!$E$10)=0,1,0)))) -> 1 | N11: =IF('4.1 Revenue Build - VCU'!N$6=34,1,IF('4.1 Revenue Build - VCU'!N6<'4.1 Revenue Build - VCU'!$E$9,0,IF('4.1 Revenue Build - VCU'!N6='4.1 Revenue Build - VCU'!$E$9,1,IF(MOD('4.1 Revenue Build - VCU'!N$6-'4.1 Revenue Build - VCU'!$E$9,'4.1 Revenue Build - VCU'!$E$10)=0,1,0)))) -> 1 | O11: =IF('4.1 Revenue Build - VCU'!O$6=34,1,IF('4.1 Revenue Build - VCU'!O6<'4.1 Revenue Build - VCU'!$E$9,0,IF('4.1 Revenue Build - VCU'!O6='4.1 Revenue Build - VCU'!$E$9,1,IF(MOD('4.1 Revenue Build - VCU'!O$6-'4.1 Revenue Build - VCU'!$E$9,'4.1 Revenue Build - VCU'!$E$10)=0,1,0)))) -> 1 | ... AL11: =IF('4.1 Revenue Build - VCU'!AL$6=34,1,IF('4.1 Revenue Build - VCU'!AL6<'4.1 Revenue Build - VCU'!$E$9,0,IF('4.1 Revenue Build - VCU'!AL6='4.1 Revenue Build - VCU'!$E$9,1,IF(MOD('4.1 Revenue Build - VCU'!AL$6-'4.1 Revenue Build - VCU'!$E$9,'4.1 Revenue Build - VCU'!$E$10)=0,1,0)))) -> 1
C13: Credit Price Escalation | D13: % | E13: ='1. Project Summary'!F29 -> 0.02 | H13: 0 | I13: =E13 -> 0.02 | J13: =I13 -> 0.02 | K13: =J13 -> 0.02 | L13: =K13 -> 0.02 | M13: =L13 -> 0.02 | N13: =M13 -> 0.02 | O13: =N13 -> 0.02 | P13: =O13 -> 0.02 | Q13: =P13 -> 0.02 | ... AL13: =AK13 -> 0.02
C15: ARR
C17: Carbon Price Scenario Chosen | D17: =MATCH(E17,C20:C26,0) -> 2 | E17: ='1. Project Summary'!F28 -> Scenario 2: Medium Price
C19: Carbon Credit Price
B20: 1 | C20: ='1. Project Summary'!C20 -> Scenario 1: Low Price | D20: EUR | E20: ='1. Project Summary'!F20 -> 7.2628234 | H20: =$E20*(1+H13) -> 7.2628234 | I20: =H20*(1+I$13) -> 7.4080799 | J20: =I20*(1+J$13) -> 7.5562415 | K20: =J20*(1+K$13) -> 7.7073663 | L20: =K20*(1+L$13) -> 7.8615136 | M20: =L20*(1+M$13) -> 8.0187439 | N20: =M20*(1+N$13) -> 8.1791188 | O20: =N20*(1+O$13) -> 8.3427012 | P20: =O20*(1+P$13) -> 8.5095552 | ... AL20: =AK20*(1+AL$13) -> 13.155599
B21: 2 | C21: ='1. Project Summary'!C21 -> Scenario 2: Medium Price | D21: EUR | E21: ='1. Project Summary'!F21 -> 10 | H21: =$E21*(1+H13) -> 10 | I21: =H21*(1+I$13) -> 10.2 | J21: =I21*(1+J$13) -> 10.404 | K21: =J21*(1+K$13) -> 10.61208 | L21: =K21*(1+L$13) -> 10.824322 | M21: =L21*(1+M$13) -> 11.040808 | N21: =M21*(1+N$13) -> 11.261624 | O21: =N21*(1+O$13) -> 11.486857 | P21: =O21*(1+P$13) -> 11.716594 | ... AL21: =AK21*(1+AL$13) -> 18.113616
B22: 3 | C22: ='1. Project Summary'!C22 -> Scenario 3: High Price | D22: EUR | E22: ='1. Project Summary'!F22 -> 12.52837 | H22: =$E22*(1+H13) -> 12.52837 | I22: =H22*(1+I$13) -> 12.778938 | J22: =I22*(1+J$13) -> 13.034517 | K22: =J22*(1+K$13) -> 13.295207 | L22: =K22*(1+L$13) -> 13.561111 | M22: =L22*(1+M$13) -> 13.832333 | N22: =M22*(1+N$13) -> 14.10898 | O22: =N22*(1+O$13) -> 14.39116 | P22: =O22*(1+P$13) -> 14.678983 | ... AL22: =AK22*(1+AL$13) -> 22.693409
B23: 4 | C23: Scenario 4: Trove - Low Demand, Loose Supply | E23: ='1. Project Summary'!F23 -> 9.9 | H23: =E23 -> 9.9 | I23: 6.6778877 | J23: 7.4881851 | K23: 8.5998389 | L23: 9.8261279 | M23: 10.948756 | N23: 12.073852 | O23: 13.100757 | P23: 13.916354 | Q23: 14.62504 | R23: 15.736281 | S23: 16.806204 | T23: 18.268082 | U23: 19.801796 | V23: 21.33551 | W23: 22.80098 | X23: 24.144327 | Y23: 25.397878 | Z23: 26.525714 | AA23: 27.473959 | AB23: 28.267755 | AC23: 28.896327 | AD23: 29.381224 | AE23: 29.740408 | AF23: 29.955918 | AG23: 30.063673 | AH23: 30.13551 | AI23: 30.171429 | AJ23: =AI23 -> 30.171429 | AK23: =AJ23 -> 30.171429 | AL23: =AK23 -> 30.171429
B24: 5 | C24: Scenario 5: Trove - High Demand, Loose Supply | E24: ='1. Project Summary'!F24 -> 10.2 | H24: =E24 -> 10.2 | I24: 9.834449 | J24: 11.720163 | K24: 13.516082 | L24: 15.254531 | M24: 16.99298 | N24: 18.867918 | O24: 21.033796 | P24: 23.555265 | Q24: 26.371265 | R24: 29.402776 | S24: 32.373224 | T24: 35.156898 | U24: 37.76098 | V24: 40.199837 | W24: 42.401633 | X24: 44.423837 | Y24: 46.413714 | Z24: 48.4 | AA24: 50.314449 | AB24: 52.178612 | AC24: 53.970939 | AD24: 55.583673 | AE24: 56.912653 | AF24: 57.900408 | AG24: 58.564898 | AH24: 58.942041 | AI24: 59.139592 | AJ24: =AI24 -> 59.139592 | AK24: =AJ24 -> 59.139592 | AL24: =AK24 -> 59.139592
B25: 6 | C25: Scenario 6: Trove - Low Demand,Tight Supply | E25: ='1. Project Summary'!F25 -> 11.3 | H25: =E25 -> 11.3 | I25: 8.3837786 | J25: 9.4336044 | K25: 10.879176 | L25: 12.514144 | M25: 14.18452 | N25: 15.8752 | O25: 17.446579 | P25: 18.712371 | Q25: 19.700089 | R25: 21.077346 | S25: 22.25502 | T25: 23.864163 | U25: 25.387102 | V25: 26.787918 | W25: 28.001959 | X25: 29.057959 | Y25: 30.042122 | Z25: 31.040653 | AA25: 32.11102 | AB25: 33.264 | AC25: 34.485224 | AD25: 35.710041 | AE25: 36.830694 | AF25: 37.70351 | AG25: 38.28898 | AH25: 38.662531 | AI25: 38.852898 | AJ25: =AI25 -> 38.852898 | AK25: =AJ25 -> 38.852898 | AL25: =AK25 -> 38.852898
B26: 7 | C26: Scenario 7: Trove - High Demand, Tight Supply | E26: ='1. Project Summary'!F26 -> 11.9 | H26: =E26 -> 11.9 | I26: 12.266122 | J26: 14.672653 | K26: 17.043265 | L26: 19.338449 | M26: 21.597714 | N26: 23.821061 | O26: 26.403592 | P26: 29.370449 | Q26: 32.807837 | R26: 36.708571 | S26: 40.896653 | T26: 45.19249 | U26: 49.430857 | V26: 53.457306 | W26: 56.937796 | X26: 59.804082 | Y26: 62.023837 | Z26: 63.701224 | AA26: 64.940408 | AB26: 65.949714 | AC26: 66.937469 | AD26: 67.971918 | AE26: 69.078204 | AF26: 70.116245 | AG26: 70.963918 | AH26: 71.585306 | AI26: 71.980408 | AJ26: =AI26 -> 71.980408 | AK26: =AJ26 -> 71.980408 | AL26: =AK26 -> 71.980408
C27: Applicable Credit Price | E27: =H27 -> 10 | H27: =CHOOSE($D$17,H20,H21,H22,H23,H24,H25,H26) -> 10 | I27: =CHOOSE($D$17,I20,I21,I22,I23,I24,I25,I26) -> 10.2 | J27: =CHOOSE($D$17,J20,J21,J22,J23,J24,J25,J26) -> 10.404 | K27: =CHOOSE($D$17,K20,K21,K22,K23,K24,K25,K26) -> 10.61208 | L27: =CHOOSE($D$17,L20,L21,L22,L23,L24,L25,L26) -> 10.824322 | M27: =CHOOSE($D$17,M20,M21,M22,M23,M24,M25,M26) -> 11.040808 | N27: =CHOOSE($D$17,N20,N21,N22,N23,N24,N25,N26) -> 11.261624 | O27: =CHOOSE($D$17,O20,O21,O22,O23,O24,O25,O26) -> 11.486857 | ... AL27: =CHOOSE($D$17,AL20,AL21,AL22,AL23,AL24,AL25,AL26) -> 18.113616
C29: Carbon Crediting Scenario Chosen | D29: =MATCH(E29,C32:C34,0) -> 2 | E29: ='1. Project Summary'!F36 -> Scenario 2: High Crediting Scenario
C31: Carbon Crediting Scenarios | E31: Total VCUs
B32: 1 | C32: ='1. Project Summary'!C32 -> Scenario 1: Low Crediting Scenario | D32: VCU | E32: =SUM(H32:AL32) -> 6540628 | H32: ='12. VCU Volume'!E41 -> 0 | I32: ='12. VCU Volume'!F41 -> 1640 | J32: ='12. VCU Volume'!G41 -> 35324 | K32: ='12. VCU Volume'!H41 -> 69008 | L32: ='12. VCU Volume'!I41 -> 102696 | M32: ='12. VCU Volume'!J41 -> 140060 | N32: ='12. VCU Volume'!K41 -> 177428 | O32: ='12. VCU Volume'!L41 -> 214792 | ... AL32: ='12. VCU Volume'!AI41 -> 252160
B33: 2 | C33: ='1. Project Summary'!C33 -> Scenario 2: High Crediting Scenario | D33: VCU | E33: =SUM(H33:AL33) -> 8089676 | H33: ='12. VCU Volume'!E42 -> 0 | I33: ='12. VCU Volume'!F42 -> 2028 | J33: ='12. VCU Volume'!G42 -> 43692 | K33: ='12. VCU Volume'!H42 -> 85356 | L33: ='12. VCU Volume'!I42 -> 127016 | M33: ='12. VCU Volume'!J42 -> 173232 | N33: ='12. VCU Volume'!K42 -> 219448 | O33: ='12. VCU Volume'!L42 -> 265664 | ... AL33: ='12. VCU Volume'!AI42 -> 311880
B34: 3 | C34: ='1. Project Summary'!C34 -> Scenario 3: Maximum Mitigation Potential | D34: VCU | E34: =SUM(H34:AL34) -> 9753568 | H34: ='12. VCU Volume'!E43 -> 0 | I34: ='12. VCU Volume'!F43 -> 2448 | J34: ='12. VCU Volume'!G43 -> 52676 | K34: ='12. VCU Volume'!H43 -> 102908 | L34: ='12. VCU Volume'!I43 -> 153140 | M34: ='12. VCU Volume'!J43 -> 208864 | N34: ='12. VCU Volume'!K43 -> 264584 | O34: ='12. VCU Volume'!L43 -> 320304 | ... AL34: ='12. VCU Volume'!AI43 -> 376028
C36: Applicable Credit Volume | D36: VCU | E36: =SUM(H36:AL36) -> 8089676 | H36: =CHOOSE($D$29,H32,H33,H34) -> 0 | I36: =CHOOSE($D$29,I32,I33,I34) -> 2028 | J36: =CHOOSE($D$29,J32,J33,J34) -> 43692 | K36: =CHOOSE($D$29,K32,K33,K34) -> 85356 | L36: =CHOOSE($D$29,L32,L33,L34) -> 127016 | M36: =CHOOSE($D$29,M32,M33,M34) -> 173232 | N36: =CHOOSE($D$29,N32,N33,N34) -> 219448 | O36: =CHOOSE($D$29,O32,O33,O34) -> 265664 | ... AL36: =CHOOSE($D$29,AL32,AL33,AL34) -> 311880
C38: Cummulative VCUs | D38: VCU | H38: =SUM($H$36:H$36) -> 0 | I38: =SUM($H$36:I$36) -> 2028 | J38: =SUM($H$36:J$36) -> 45720 | K38: =SUM($H$36:K$36) -> 131076 | L38: =SUM($H$36:L$36) -> 258092 | M38: =SUM($H$36:M$36) -> 431324 | N38: =SUM($H$36:N$36) -> 650772 | O38: =SUM($H$36:O$36) -> 916436 | ... AL38: =SUM($H$36:AL$36) -> 8089676
C39: VCUs to be issued | D39: VCU | E39: =SUM(H39:AL39) -> 8089676 | H39: =IF(H$11=0,0,H$38-SUM(#REF!)) -> 0 | I39: =IF(I$11=0,0,I$38-SUM($H39:H$39)) -> 0 | J39: =IF(J$11=0,0,J$38-SUM($H39:I$39)) -> 45720 | K39: =IF(K$11=0,0,K$38-SUM($H39:J$39)) -> 85356 | L39: =IF(L$11=0,0,L$38-SUM($H39:K$39)) -> 127016 | M39: =IF(M$11=0,0,M$38-SUM($H39:L$39)) -> 173232 | N39: =IF(N$11=0,0,N$38-SUM($H39:M$39)) -> 219448 | O39: =IF(O$11=0,0,O$38-SUM($H39:N$39)) -> 265664 | P39: =IF(P$11=0,0,P$38-SUM($H39:O$39)) -> 311880 | ... AL39: =IF(AL$11=0,0,AL$38-SUM($H39:AK$39)) -> 311880
C40: VCUs attributable to Mirova | D40: VCU | E40: =SUM(J40:AL40) -> 1000000 | J40: =MIN(OFFSET(J$54,$E$10,0),J39) -> 30000 | K40: =MIN(OFFSET(K$54,$E$10,0),K39) -> 75000 | L40: =MIN(OFFSET(L$54,$E$10,0),L39) -> 112000 | M40: =MIN(OFFSET(M$54,$E$10,0),M39) -> 140000 | N40: =MIN(OFFSET(N$54,$E$10,0),N39) -> 142000 | O40: =MIN(OFFSET(O$54,$E$10,0),O39) -> 200000 | P40: =MIN(OFFSET(P$54,$E$10,0),P39) -> 301000 | Q40: =IF(Q38>1000000,1000000-SUM($H40:P40),Q39)*Q11 -> 0 | R40: =IF(R38>1000000,1000000-SUM($H40:Q40),R39)*R11 -> 0 | S40: =IF(S38>1000000,1000000-SUM($H40:R40),S39)*S11 -> 0 | T40: =IF(T38>1000000,1000000-SUM($H40:S40),T39)*T11 -> 0 | U40: =IF(U38<1000000,U39,0) -> 0 | V40: =IF(V38<1000000,V39,0) -> 0
C41: VCUs attributable to Others | D41: VCU | E41: =SUM(H41:AL41) -> 7089676 | H41: =H39-H40 -> 0 | I41: =I39-I40 -> 0 | J41: =J39-J40 -> 15720 | K41: =K39-K40 -> 10356 | L41: =L39-L40 -> 15016 | M41: =M39-M40 -> 33232 | N41: =N39-N40 -> 77448 | O41: =O39-O40 -> 65664 | ... AL41: =AL39-AL40 -> 311880
C43: ARR Revenue (to be recognized)
C44: Revenue attributable to Mirova | D44: EUR | E44: =SUM(H44:AL44) -> 10000000 | H44: =H40*$E$21 -> 0 | I44: =I40*$E$21 -> 0 | J44: =J40*$E$21 -> 300000 | K44: =K40*$E$21 -> 750000 | L44: =L40*$E$21 -> 1120000 | M44: =M40*$E$21 -> 1400000 | N44: =N40*$E$21 -> 1420000 | O44: =O40*$E$21 -> 2000000 | ... AL44: =AL40*$E$21 -> 0
C45: Revenue attributable to Others | D45: EUR | E45: =SUM(H45:AL45) -> 1.043071e+08 | H45: =H41*H27 -> 0 | I45: =I41*I27 -> 0 | J45: =J41*J27 -> 163550.88 | K45: =K41*K27 -> 109898.7 | L45: =L41*L27 -> 162538.01 | M45: =M41*M27 -> 366908.13 | N45: =N41*N27 -> 872190.27 | O45: =O41*O27 -> 754272.96 | ... AL45: =AL41*AL27 -> 5649274.5
C46: ARR Revenue | D46: EUR | E46: =SUM(H46:AK46) -> 1.0865783e+08 | H46: =SUM(H44:H45) -> 0 | I46: =SUM(I44:I45) -> 0 | J46: =SUM(J44:J45) -> 463550.88 | K46: =SUM(K44:K45) -> 859898.7 | L46: =SUM(L44:L45) -> 1282538 | M46: =SUM(M44:M45) -> 1766908.1 | N46: =SUM(N44:N45) -> 2292190.3 | O46: =SUM(O44:O45) -> 2754273 | ... AL46: =SUM(AL44:AL45) -> 5649274.5
C48: ARR Revenue (cash based)
C49: Prepayment from Mirova | D49: EUR | E49: =SUM(H49:AL49) -> 8000000 | H49: 3000000 | I49: 2000000 | J49: 2500000 | K49: 500000
C50: Revenue from Others | D50: EUR | E50: =SUM(H50:AL50) -> 1.043071e+08 | H50: =H45 -> 0 | I50: =I45 -> 0 | J50: =J45 -> 163550.88 | K50: =K45 -> 109898.7 | L50: =L45 -> 162538.01 | M50: =M45 -> 366908.13 | N50: =N45 -> 872190.27 | O50: =O45 -> 754272.96 | ... AL50: =AL45 -> 5649274.5
C51: ARR Revenue (cash) | D51: EUR | E51: =SUM(E49:E50) -> 1.123071e+08 | H51: =SUM(H49:H50) -> 3000000 | I51: =SUM(I49:I50) -> 2000000 | J51: =SUM(J49:J50) -> 2663550.9 | K51: =SUM(K49:K50) -> 609898.7 | L51: =SUM(L49:L50) -> 162538.01 | M51: =SUM(M49:M50) -> 366908.13 | N51: =SUM(N49:N50) -> 872190.27 | O51: =SUM(O49:O50) -> 754272.96 | ... AL51: =SUM(AL49:AL50) -> 5649274.5
D54: Assuming: | F54: Total
C55: Repayment Schedule to Mirova | D55: 1-yr interval between Credit Issuances | F55: =SUM(H55:AL55) -> 1000000 | J55: 30000 | K55: 75000 | L55: 112000 | M55: 140000 | N55: 142000 | O55: 200000 | P55: 301000
C56: Repayment Schedule to Mirova | D56: 2-yr interval between Credit Issuances | F56: =SUM(H56:AL56) -> 1000000 | J56: =J55 -> 30000 | K56: =0 -> 0 | L56: =SUM(K55:L55) -> 187000 | M56: =0 -> 0 | N56: =SUM(M55:N55) -> 282000 | O56: =0 -> 0 | P56: =SUM(O55:P55) -> 501000
C57: Repayment Schedule to Mirova | D57: 3-yr interval between Credit Issuances | F57: =SUM(H57:AL57) -> 1000000 | J57: =J56 -> 30000 | K57: =0 -> 0 | L57: =0 -> 0 | M57: =SUM(K55:M55) -> 327000 | N57: =0 -> 0 | O57: =0 -> 0 | P57: =SUM(N55:P55) -> 643000
Q281: =$F281*Q$5 -> 0

Sheet 4.2 Revenue Build - Other
B2: ='1. Project Summary'!B2 -> Projections - Serious Shea
B3: ='1. Project Summary'!B3 -> (in EUR, unless otherwise stated)
B5: Revenue Build | D5: Unit | H5: ='2. NPV'!H5 -> 2024 | I5: ='2. NPV'!I5 -> 2025 | J5: ='2. NPV'!J5 -> 2026 | K5: ='2. NPV'!K5 -> 2027 | L5: ='2. NPV'!L5 -> 2028 | M5: ='2. NPV'!M5 -> 2029 | N5: ='2. NPV'!N5 -> 2030 | O5: ='2. NPV'!O5 -> 2031 | ... AL5: ='2. NPV'!AL5 -> 2054
H6: =Period_Start -> 1 | I6: =H6+1 -> 2 | J6: =I6+1 -> 3 | K6: =J6+1 -> 4 | L6: =K6+1 -> 5 | M6: =L6+1 -> 6 | N6: =M6+1 -> 7 | O6: =N6+1 -> 8 | P6: =O6+1 -> 9 | ... AL6: =AK6+1 -> 31
C7: Year count | H7: 1 | I7: =+H7+1 -> 2 | J7: =+I7+1 -> 3 | K7: =+J7+1 -> 4 | L7: =+K7+1 -> 5 | M7: =+L7+1 -> 6 | N7: =+M7+1 -> 7 | O7: =+N7+1 -> 8 | P7: =+O7+1 -> 9 | ... AL7: =+AK7+1 -> 31
B9: Prices
B10: 1 | C10: ='3. Assumptions'!C8 -> Refined Oil | D10: ='3. Assumptions'!D8 -> EUR per metric ton | E10: ='3. Assumptions'!E8 -> 30000 | F10: =IF('1. Project Summary'!$F$13="Real",0,'3. Assumptions'!F8) -> 0.025
B11: ='3. Assumptions'!B9 -> 2 | C11: ='3. Assumptions'!C9 -> Moringa Leaves | D11: ='3. Assumptions'!D9 -> EUR per metric ton | E11: ='3. Assumptions'!E9 -> 5000 | F11: =IF('1. Project Summary'!$F$13="Real",0,'3. Assumptions'!F9) -> 0.025
B12: ='3. Assumptions'!B10 -> 3 | C12: ='3. Assumptions'!C10 -> Dry Mangos | D12: ='3. Assumptions'!D10 -> EUR per metric ton | E12: ='3. Assumptions'!E10 -> 3500 | F12: =IF('1. Project Summary'!$F$13="Real",0,'3. Assumptions'!F10) -> 0.025
B13: ='3. Assumptions'!B11 -> 4 | C13: ='3. Assumptions'!C11 -> Shea Butter | D13: ='3. Assumptions'!D11 -> EUR per metric ton | E13: ='3. Assumptions'!E11 -> 2000 | F13: =IF('1. Project Summary'!$F$13="Real",0,'3. Assumptions'!F11) -> 0.025
B14: ='3. Assumptions'!B12 -> 5 | C14: ='3. Assumptions'!C12 -> Fertilisers Compost | D14: ='3. Assumptions'!D12 -> EUR per metric ton | E14: ='3. Assumptions'!E12 -> 100 | F14: =IF('1. Project Summary'!$F$13="Real",0,'3. Assumptions'!F12) -> 0.025
B15: ='3. Assumptions'!B13 -> 6 | C15: ='3. Assumptions'!C13 -> Biochar | D15: ='3. Assumptions'!D13 -> EUR per metric ton | E15: ='3. Assumptions'!E13 -> 0 | F15: =IF('1. Project Summary'!$F$13="Real",0,'3. Assumptions'!F13) -> 0
B17: Volume | F17: Average
B18: =B10 -> 1 | C18: =C10 -> Refined Oil | D18: tn | F18: =AVERAGE(J18:AL18) -> 461.11034 | H18: ='3. Assumptions'!F166/1000 -> 0 | I18: ='3. Assumptions'!G166/1000 -> 0 | J18: ='3. Assumptions'!H166/1000 -> 161.5 | K18: ='3. Assumptions'!I166/1000 -> 290.7 | L18: ='3. Assumptions'!J166/1000 -> 323 | M18: ='3. Assumptions'!K166/1000 -> 484.5 | N18: ='3. Assumptions'!L166/1000 -> 484.5 | O18: ='3. Assumptions'!M166/1000 -> 484.5 | ... Q18: ='3. Assumptions'!O166/1000 -> 484.5 | R18: =Q18 -> 484.5 | S18: =R18 -> 484.5 | T18: =S18 -> 484.5 | U18: =T18 -> 484.5 | V18: =U18 -> 484.5 | W18: =V18 -> 484.5 | X18: =W18 -> 484.5 | Y18: =X18 -> 484.5 | ... AL18: =AK18 -> 484.5
B19: =B11 -> 2 | C19: =C11 -> Moringa Leaves | D19: tn | F19: =AVERAGE(I19:AL19) -> 94.316 | H19: ='3. Assumptions'!F167/1000 -> 0 | I19: ='3. Assumptions'!G167/1000 -> 58.14 | J19: ='3. Assumptions'!H167/1000 -> 58.14 | K19: ='3. Assumptions'!I167/1000 -> 96.9 | L19: ='3. Assumptions'!J167/1000 -> 96.9 | M19: ='3. Assumptions'!K167/1000 -> 96.9 | N19: ='3. Assumptions'!L167/1000 -> 96.9 | O19: ='3. Assumptions'!M167/1000 -> 96.9 | ... Q19: ='3. Assumptions'!O167/1000 -> 96.9 | R19: =Q19 -> 96.9 | S19: =R19 -> 96.9 | T19: =S19 -> 96.9 | U19: =T19 -> 96.9 | V19: =U19 -> 96.9 | W19: =V19 -> 96.9 | X19: =W19 -> 96.9 | Y19: =X19 -> 96.9 | ... AL19: =AK19 -> 96.9
B20: =B12 -> 3 | C20: =C12 -> Dry Mangos | D20: tn | F20: =AVERAGE(I20:AL20) -> 1349.4 | H20: ='3. Assumptions'!F168/1000 -> 0 | I20: ='3. Assumptions'!G168/1000 -> 173 | J20: ='3. Assumptions'!H168/1000 -> 346 | K20: ='3. Assumptions'!I168/1000 -> 519 | L20: ='3. Assumptions'!J168/1000 -> 692 | M20: ='3. Assumptions'!K168/1000 -> 865 | N20: ='3. Assumptions'!L168/1000 -> 1038 | O20: ='3. Assumptions'!M168/1000 -> 1211 | ... Q20: ='3. Assumptions'!O168/1000 -> 1557 | R20: =Q20 -> 1557 | S20: =R20 -> 1557 | T20: =S20 -> 1557 | U20: =T20 -> 1557 | V20: =U20 -> 1557 | W20: =V20 -> 1557 | X20: =W20 -> 1557 | Y20: =X20 -> 1557 | ... AL20: =AK20 -> 1557
B21: =B13 -> 4 | C21: =C13 -> Shea Butter | D21: tn | F21: =AVERAGE(J21:AL21) -> 0 | H21: ='3. Assumptions'!F169/1000 -> 0 | I21: ='3. Assumptions'!G169/1000 -> 0 | J21: ='3. Assumptions'!H169/1000 -> 0 | K21: ='3. Assumptions'!I169/1000 -> 0 | L21: ='3. Assumptions'!J169/1000 -> 0 | M21: ='3. Assumptions'!K169/1000 -> 0 | N21: ='3. Assumptions'!L169/1000 -> 0 | O21: ='3. Assumptions'!M169/1000 -> 0 | ... Q21: ='3. Assumptions'!O169/1000 -> 0 | R21: =Q21 -> 0 | S21: =R21 -> 0 | T21: =S21 -> 0 | U21: =T21 -> 0 | V21: =U21 -> 0 | W21: =V21 -> 0 | X21: =W21 -> 0 | Y21: =X21 -> 0 | ... AL21: =AK21 -> 0
B22: =B14 -> 5 | C22: =C14 -> Fertilisers Compost | D22: tn | F22: =AVERAGE(I22:AL22) -> 9360 | H22: ='3. Assumptions'!F170/1000 -> 0 | I22: ='3. Assumptions'!G170/1000 -> 1200 | J22: ='3. Assumptions'!H170/1000 -> 2400 | K22: ='3. Assumptions'!I170/1000 -> 3600 | L22: ='3. Assumptions'!J170/1000 -> 4800 | M22: ='3. Assumptions'!K170/1000 -> 6000 | N22: ='3. Assumptions'!L170/1000 -> 7200 | O22: ='3. Assumptions'!M170/1000 -> 8400 | ... Q22: ='3. Assumptions'!O170/1000 -> 10800 | R22: =Q22 -> 10800 | S22: =R22 -> 10800 | T22: =S22 -> 10800 | U22: =T22 -> 10800 | V22: =U22 -> 10800 | W22: =V22 -> 10800 | X22: =W22 -> 10800 | Y22: =X22 -> 10800 | ... AL22: =AK22 -> 10800
B23: =B15 -> 6 | C23: =C15 -> Biochar | D23: tn | F23: =AVERAGE(J23:AL23) -> 0 | H23: ='3. Assumptions'!F171/1000 -> 0 | I23: ='3. Assumptions'!G171/1000 -> 0 | J23: ='3. Assumptions'!H171/1000 -> 0 | K23: ='3. Assumptions'!I171/1000 -> 0 | L23: ='3. Assumptions'!J171/1000 -> 0 | M23: ='3. Assumptions'!K171/1000 -> 0 | N23: ='3. Assumptions'!L171/1000 -> 0 | O23: ='3. Assumptions'!M171/1000 -> 0 | ... Q23: ='3. Assumptions'!O171/1000 -> 0 | R23: =Q23 -> 0 | S23: =R23 -> 0 | T23: =S23 -> 0 | U23: =T23 -> 0 | V23: =U23 -> 0 | W23: =V23 -> 0 | X23: =W23 -> 0 | Y23: =X23 -> 0 | ... AL23: =AK23 -> 0
B25: Revenue
B26: Revenue from products
B27: =B18 -> 1 | C27: =C18 -> Refined Oil | D27: EUR | E27: ='3. Assumptions'!G8 -> 1 | H27: =H18*$E10*(1+$F10)^H$6*$E27 -> 0 | I27: =I18*$E10*(1+$F10)^I$6*$E27 -> 0 | J27: =J18*$E10*(1+$F10)^J$6*$E27 -> 5217535.1 | K27: =K18*$E10*(1+$F10)^K$6*$E27 -> 9626352.2 | L27: =L18*$E10*(1+$F10)^L$6*$E27 -> 10963346 | M27: =M18*$E10*(1+$F10)^M$6*$E27 -> 16856144 | N27: =N18*$E10*(1+$F10)^N$6*$E27 -> 17277547 | O27: =O18*$E10*(1+$F10)^O$6*$E27 -> 17709486 | ... AL27: =AL18*$E10*(1+$F10)^AL$6*$E27 -> 31250348
B28: =B19 -> 2 | C28: =C19 -> Moringa Leaves | D28: EUR | E28: ='3. Assumptions'!G9 -> 1 | H28: =H19*$E11*(1+$F11)^H$6*$E28 -> 0 | I28: =I19*$E11*(1+$F11)^I$6*$E28 -> 305416.69 | J28: =J19*$E11*(1+$F11)^J$6*$E28 -> 313052.1 | K28: =K19*$E11*(1+$F11)^K$6*$E28 -> 534797.35 | L28: =L19*$E11*(1+$F11)^L$6*$E28 -> 548167.28 | M28: =M19*$E11*(1+$F11)^M$6*$E28 -> 561871.46 | N28: =N19*$E11*(1+$F11)^N$6*$E28 -> 575918.25 | O28: =O19*$E11*(1+$F11)^O$6*$E28 -> 590316.2 | ... AL28: =AL19*$E11*(1+$F11)^AL$6*$E28 -> 1041678.3
B29: =B20 -> 3 | C29: =C20 -> Dry Mangos | D29: EUR | E29: ='3. Assumptions'!G10 -> 0.3 | H29: =H20*$E12*(1+$F12)^H$6*$E29 -> 0 | I29: =I20*$E12*(1+$F12)^I$6*$E29 -> 190846.03 | J29: =J20*$E12*(1+$F12)^J$6*$E29 -> 391234.36 | K29: =K20*$E12*(1+$F12)^K$6*$E29 -> 601522.83 | L29: =L20*$E12*(1+$F12)^L$6*$E29 -> 822081.21 | M29: =M20*$E12*(1+$F12)^M$6*$E29 -> 1053291.5 | N29: =N20*$E12*(1+$F12)^N$6*$E29 -> 1295548.6 | O29: =O20*$E12*(1+$F12)^O$6*$E29 -> 1549260.2 | ... AL29: =AL20*$E12*(1+$F12)^AL$6*$E29 -> 3514938.6
B30: =B21 -> 4 | C30: =C21 -> Shea Butter | D30: EUR | E30: ='3. Assumptions'!G11 -> 0.3 | H30: =H21*$E13*(1+$F13)^H$6*$E30 -> 0 | I30: =I21*$E13*(1+$F13)^I$6*$E30 -> 0 | J30: =J21*$E13*(1+$F13)^J$6*$E30 -> 0 | K30: =K21*$E13*(1+$F13)^K$6*$E30 -> 0 | L30: =L21*$E13*(1+$F13)^L$6*$E30 -> 0 | M30: =M21*$E13*(1+$F13)^M$6*$E30 -> 0 | N30: =N21*$E13*(1+$F13)^N$6*$E30 -> 0 | O30: =O21*$E13*(1+$F13)^O$6*$E30 -> 0 | ... AL30: =AL21*$E13*(1+$F13)^AL$6*$E30 -> 0
B31: =B22 -> 5 | C31: =C22 -> Fertilisers Compost | D31: EUR | E31: ='3. Assumptions'!G12 -> 1 | H31: =H22*$E14*(1+$F14)^H$6*$E31 -> 0 | I31: =I22*$E14*(1+$F14)^I$6*$E31 -> 126075 | J31: =J22*$E14*(1+$F14)^J$6*$E31 -> 258453.75 | K31: =K22*$E14*(1+$F14)^K$6*$E31 -> 397372.64 | L31: =L22*$E14*(1+$F14)^L$6*$E31 -> 543075.94 | M31: =M22*$E14*(1+$F14)^M$6*$E31 -> 695816.05 | N31: =N22*$E14*(1+$F14)^N$6*$E31 -> 855853.74 | O31: =O22*$E14*(1+$F14)^O$6*$E31 -> 1023458.4 | ... AL31: =AL22*$E14*(1+$F14)^AL$6*$E31 -> 2322007.3
B32: =B23 -> 6 | C32: =C23 -> Biochar | D32: EUR | E32: ='3. Assumptions'!G13 -> 0 | H32: =H23*$E15*(1+$F15)^H$6*$E32 -> 0 | I32: =I23*$E15*(1+$F15)^I$6*$E32 -> 0 | J32: =J23*$E15*(1+$F15)^J$6*$E32 -> 0 | K32: =K23*$E15*(1+$F15)^K$6*$E32 -> 0 | L32: =L23*$E15*(1+$F15)^L$6*$E32 -> 0 | M32: =M23*$E15*(1+$F15)^M$6*$E32 -> 0 | N32: =N23*$E15*(1+$F15)^N$6*$E32 -> 0 | O32: =O23*$E15*(1+$F15)^O$6*$E32 -> 0 | ... AL32: =AL23*$E15*(1+$F15)^AL$6*$E32 -> 0
B33: ="Total "&B26 -> Total Revenue from products | H33: =SUM(H27:H32) -> 0 | I33: =SUM(I27:I32) -> 622337.72 | J33: =SUM(J27:J32) -> 6180275.3 | K33: =SUM(K27:K32) -> 11160045 | L33: =SUM(L27:L32) -> 12876670 | M33: =SUM(M27:M32) -> 19167123 | N33: =SUM(N27:N32) -> 20004868 | O33: =SUM(O27:O32) -> 20872521 | ... AL33: =SUM(AL27:AL32) -> 38128973
B35: Revenue from processing fee
B36: =B29 -> 3 | C36: =C29 -> Dry Mangos | D36: EUR | E36: ='3. Assumptions'!E16 -> 100 | F36: =IF('1. Project Summary'!$F$13="Real",0,'3. Assumptions'!F16) -> 0.025 | H36: =H20*$E36*(1+$F36)^H$6 -> 0 | I36: =I20*$E36*(1+$F36)^I$6 -> 18175.812 | J36: =J20*$E36*(1+$F36)^J$6 -> 37260.416 | K36: =K20*$E36*(1+$F36)^K$6 -> 57287.889 | L36: =L20*$E36*(1+$F36)^L$6 -> 78293.448 | M36: =M20*$E36*(1+$F36)^M$6 -> 100313.48 | N36: =N20*$E36*(1+$F36)^N$6 -> 123385.58 | O36: =O20*$E36*(1+$F36)^O$6 -> 147548.59 | ... AL36: =AL20*$E36*(1+$F36)^AL$6 -> 334756.05
B37: =B30 -> 4 | C37: =C30 -> Shea Butter | D37: EUR | E37: ='3. Assumptions'!E17 -> 200 | F37: =IF('1. Project Summary'!$F$13="Real",0,'3. Assumptions'!F17) -> 0.025 | H37: =H21*$E37*(1+$F37)^H$6 -> 0 | I37: =I21*$E37*(1+$F37)^I$6 -> 0 | J37: =J21*$E37*(1+$F37)^J$6 -> 0 | K37: =K21*$E37*(1+$F37)^K$6 -> 0 | L37: =L21*$E37*(1+$F37)^L$6 -> 0 | M37: =M21*$E37*(1+$F37)^M$6 -> 0 | N37: =N21*$E37*(1+$F37)^N$6 -> 0 | O37: =O21*$E37*(1+$F37)^O$6 -> 0 | ... AL37: =AL21*$E37*(1+$F37)^AL$6 -> 0
B38: ="Total "&B35 -> Total Revenue from processing fee | H38: =SUM(H36:H37) -> 0 | I38: =SUM(I36:I37) -> 18175.812 | J38: =SUM(J36:J37) -> 37260.416 | K38: =SUM(K36:K37) -> 57287.889 | L38: =SUM(L36:L37) -> 78293.448 | M38: =SUM(M36:M37) -> 100313.48 | N38: =SUM(N36:N37) -> 123385.58 | O38: =SUM(O36:O37) -> 147548.59 | ... AL38: =SUM(AL36:AL37) -> 334756.05
B40: ="Total "&B25 -> Total Revenue | H40: =H33+H38 -> 0 | I40: =I33+I38 -> 640513.53 | J40: =J33+J38 -> 6217535.7 | K40: =K33+K38 -> 11217333 | L40: =L33+L38 -> 12954963 | M40: =M33+M38 -> 19267436 | N40: =N33+N38 -> 20128254 | O40: =O33+O38 -> 21020070 | ... AL40: =AL33+AL38 -> 38463729
B43: Combined Revenue of Serious Shea & its Partners
B44: =B27 -> 1 | C44: =C27 -> Refined Oil | D44: EUR | H44: =H27/$E27*100% -> 0 | I44: =I27/$E27*100% -> 0 | J44: =J27/$E27*100% -> 5217535.1 | K44: =K27/$E27*100% -> 9626352.2 | L44: =L27/$E27*100% -> 10963346 | M44: =M27/$E27*100% -> 16856144 | N44: =N27/$E27*100% -> 17277547 | O44: =O27/$E27*100% -> 17709486 | ... AL44: =AL27/$E27*100% -> 31250348
B45: =B28 -> 2 | C45: =C28 -> Moringa Leaves | D45: EUR | H45: =H28/$E28*100% -> 0 | I45: =I28/$E28*100% -> 305416.69 | J45: =J28/$E28*100% -> 313052.1 | K45: =K28/$E28*100% -> 534797.35 | L45: =L28/$E28*100% -> 548167.28 | M45: =M28/$E28*100% -> 561871.46 | N45: =N28/$E28*100% -> 575918.25 | O45: =O28/$E28*100% -> 590316.2 | ... AL45: =AL28/$E28*100% -> 1041678.3
B46: =B29 -> 3 | C46: =C29 -> Dry Mangos | D46: EUR | H46: =H29/$E29*100% -> 0 | I46: =I29/$E29*100% -> 636153.44 | J46: =J29/$E29*100% -> 1304114.5 | K46: =K29/$E29*100% -> 2005076.1 | L46: =L29/$E29*100% -> 2740270.7 | M46: =M29/$E29*100% -> 3510971.8 | N46: =N29/$E29*100% -> 4318495.3 | O46: =O29/$E29*100% -> 5164200.7 | ... AL46: =AL29/$E29*100% -> 11716462
B47: =B30 -> 4 | C47: =C30 -> Shea Butter | D47: EUR | H47: =H30/$E30*100% -> 0 | I47: =I30/$E30*100% -> 0 | J47: =J30/$E30*100% -> 0 | K47: =K30/$E30*100% -> 0 | L47: =L30/$E30*100% -> 0 | M47: =M30/$E30*100% -> 0 | N47: =N30/$E30*100% -> 0 | O47: =O30/$E30*100% -> 0 | ... AL47: =AL30/$E30*100% -> 0
B48: =B31 -> 5 | C48: =C31 -> Fertilisers Compost | D48: EUR | H48: =H31/$E31*100% -> 0 | I48: =I31/$E31*100% -> 126075 | J48: =J31/$E31*100% -> 258453.75 | K48: =K31/$E31*100% -> 397372.64 | L48: =L31/$E31*100% -> 543075.94 | M48: =M31/$E31*100% -> 695816.05 | N48: =N31/$E31*100% -> 855853.74 | O48: =O31/$E31*100% -> 1023458.4 | ... AL48: =AL31/$E31*100% -> 2322007.3
B49: =B32 -> 6 | C49: =C32 -> Biochar | D49: EUR | H49: =IFERROR(H32/$E32*100%,"") | I49: =IFERROR(I32/$E32*100%,"") | J49: =IFERROR(J32/$E32*100%,"") | K49: =IFERROR(K32/$E32*100%,"") | L49: =IFERROR(L32/$E32*100%,"") | M49: =IFERROR(M32/$E32*100%,"") | N49: =IFERROR(N32/$E32*100%,"") | O49: =IFERROR(O32/$E32*100%,"") | ... AL49: =IFERROR(AL32/$E32*100%,"")
B50: ="Total "&B43 -> Total Combined Revenue of Serious Shea & its Partners | H50: =SUM(H44:H49) -> 0 | I50: =SUM(I44:I49) -> 1067645.1 | J50: =SUM(J44:J49) -> 7093155.5 | K50: =SUM(K44:K49) -> 12563598 | L50: =SUM(L44:L49) -> 14794859 | M50: =SUM(M44:M49) -> 21624803 | N50: =SUM(N44:N49) -> 23027815 | O50: =SUM(O44:O49) -> 24487461 | ... AL50: =SUM(AL44:AL49) -> 46330496
C53: Variables: | E53: Low | F53: Medium | G53: High
C54: - Utilisation | E54: 0.9 | F54: 0.95 | G54: 0.98
C55: Year | D55: Y1 | E55: Y2 | F55: Y3 | G55: Y4
C56: Leaves / kg | D56: 0.3 | E56: 0.5 | F56: 0.5 | G56: 0.5
C57: Seeds /trees kg | D57: 0.5 | E57: 0.9 | F57: 1 | G57: 1.5
C59: Plantation | H59: =0 -> 0 | I59: =969000 -> 969000 | J59: =I59 -> 969000 | K59: =J59 -> 969000 | L59: =K59 -> 969000 | M59: =L59 -> 969000 | N59: =M59 -> 969000 | O59: =N59 -> 969000 | P59: =O59 -> 969000 | Q59: =P59 -> 969000 | ... AL59: =AK59 -> 969000
C61: Production Fresh Leaves
C62: Production Fresh Leaves | E62: Kg | F62: Utilization | H62: =0 -> 0 | I62: =I59*D56 -> 290700 | J62: =J59*D56 -> 290700 | K62: =K59*E56 -> 484500 | L62: =L59*F56 -> 484500 | M62: =M59*G56 -> 484500 | N62: =M62 -> 484500 | O62: =N62 -> 484500 | P62: =O62 -> 484500 | Q62: =P62 -> 484500 | R62: =Q62 -> 484500 | S62: =R62 -> 484500 | T62: =S62 -> 484500 | U62: =T62 -> 484500 | ... AL62: =AK62 -> 484500
C63: Net production | E63: Kg | F63: 0.95 | H63: =H62*$F$63 -> 0 | I63: =I62*$F$63 -> 276165 | J63: =J62*$F$63 -> 276165 | K63: =K62*$F$63 -> 460275 | L63: =M62*$F$63 -> 460275 | M63: =M62*$F$63 -> 460275 | N63: =N62*$F$63 -> 460275 | O63: =O62*$F$63 -> 460275 | P63: =P62*$F$63 -> 460275 | Q63: =Q62*$F$63 -> 460275 | R63: =R62*$F$63 -> 460275 | S63: =S62*$F$63 -> 460275 | T63: =T62*$F$63 -> 460275 | ... AL63: =AL62*$F$63 -> 460275
C65: Production Seeds
C66: Production Seeds | E66: Kg | H66: =0 -> 0 | I66: =0 -> 0 | J66: =I59*D57 -> 484500 | K66: =J59*E57 -> 872100 | L66: =K59*F57 -> 969000 | M66: =L59*G57 -> 1453500 | N66: =M66 -> 1453500 | O66: =N66 -> 1453500 | P66: =O66 -> 1453500 | Q66: =P66 -> 1453500 | R66: =Q66 -> 1453500 | S66: =R66 -> 1453500 | T66: =S66 -> 1453500 | U66: =T66 -> 1453500 | ... AL66: =AK66 -> 1453500
C67: Net production | F67: 0.95 | I67: =I66*$F$67 -> 0 | J67: =J66*$F$67 -> 460275 | K67: =K66*$F$67 -> 828495 | L67: =L66*$F$67 -> 920550 | M67: =M66*$F$67 -> 1380825 | N67: =N66*$F$67 -> 1380825 | O67: =O66*$F$67 -> 1380825 | P67: =P66*$F$67 -> 1380825 | ... AL67: =AL66*$F$67 -> 1380825
Q288: =$F288*Q$5 -> 0

Sheet 5.1 Project Dev't & Monitoring
B2: ='1. Project Summary'!B2 -> Projections - Serious Shea
B3: ='1. Project Summary'!B3 -> (in EUR, unless otherwise stated)
B5: Cost Build | D5: Unit | H5: ='2. NPV'!H5 -> 2024 | I5: ='2. NPV'!I5 -> 2025 | J5: ='2. NPV'!J5 -> 2026 | K5: ='2. NPV'!K5 -> 2027 | L5: ='2. NPV'!L5 -> 2028 | M5: ='2. NPV'!M5 -> 2029 | N5: ='2. NPV'!N5 -> 2030 | O5: ='2. NPV'!O5 -> 2031 | ... AL5: ='2. NPV'!AL5 -> 2054
B6: Project Development & Monitoring Costs | H6: ='4.1 Revenue Build - VCU'!H6 -> 1 | I6: ='4.1 Revenue Build - VCU'!I6 -> 2 | J6: ='4.1 Revenue Build - VCU'!J6 -> 3 | K6: ='4.1 Revenue Build - VCU'!K6 -> 4 | L6: ='4.1 Revenue Build - VCU'!L6 -> 5 | M6: ='4.1 Revenue Build - VCU'!M6 -> 6 | N6: ='4.1 Revenue Build - VCU'!N6 -> 7 | O6: ='4.1 Revenue Build - VCU'!O6 -> 8 | ... AL6: ='4.1 Revenue Build - VCU'!AL6 -> 31
B8: Cost Inflation | E8: ='1. Project Summary'!F15 -> 0.02 | H8: =(1+$E$8)^H6 -> 1.02 | I8: =(1+$E$8)^I6 -> 1.0404 | J8: =(1+$E$8)^J6 -> 1.061208 | K8: =(1+$E$8)^K6 -> 1.0824322 | L8: =(1+$E$8)^L6 -> 1.1040808 | M8: =(1+$E$8)^M6 -> 1.1261624 | N8: =(1+$E$8)^N6 -> 1.1486857 | O8: =(1+$E$8)^O6 -> 1.1716594 | ... AL8: =(1+$E$8)^AL6 -> 1.8475888
B10: Project Development Cost
B11: Carbon Technical Work (VCS + CCB)
C12: Feasibility assessment | D12: USD | E12: ='3. Assumptions'!F30 -> 73250 | H12: =E12 -> 73250
C13: Work plan | D13: USD | E13: ='3. Assumptions'!F31 -> 5000 | H13: =E13 -> 5000
C14: Project Description | D14: USD | E14: ='3. Assumptions'!F32 -> 200000 | H14: =$E14*H$18 -> 100000 | I14: =$E14*I$18 -> 100000
C15: Audit support to issuance | D15: USD | E15: ='3. Assumptions'!F33 -> 62500 | H15: =$E15*H$18 -> 31250 | I15: =$E15*I$18 -> 31250
C16: First MIR | D16: USD | E16: ='3. Assumptions'!F34 -> 100000 | H16: =$E16*H$18 -> 50000 | I16: =$E16*I$18 -> 50000
C17: ='3. Assumptions'!C36 -> Additional costs for CCB | D17: USD | E17: ='3. Assumptions'!F36 -> 100000 | H17: =$E17*H$18 -> 50000 | I17: =$E17*I$18 -> 50000
C18: Payment schedule | D18: % | H18: 0.5 | I18: =100%-H18 -> 0.5
B20: Validation Audit
C21: Validation Audit Fee | D21: USD | E21: ='3. Assumptions'!F35 -> 22500 | H21: =IF('4.1 Revenue Build - VCU'!H$7='5.1 Project Dev''t & Monitoring'!$E$22,$E21,0)*H8 -> 0 | I21: =IF('4.1 Revenue Build - VCU'!I$7='5.1 Project Dev''t & Monitoring'!$E$22,$E21,0)*I8 -> 23409 | J21: =IF('4.1 Revenue Build - VCU'!J$7='5.1 Project Dev''t & Monitoring'!$E$22,$E21,0)*J8 -> 0 | K21: =IF('4.1 Revenue Build - VCU'!K$7='5.1 Project Dev''t & Monitoring'!$E$22,$E21,0)*K8 -> 0 | L21: =IF('4.1 Revenue Build - VCU'!L$7='5.1 Project Dev''t & Monitoring'!$E$22,$E21,0)*L8 -> 0 | M21: =IF('4.1 Revenue Build - VCU'!M$7='5.1 Project Dev''t & Monitoring'!$E$22,$E21,0)*M8 -> 0 | N21: =IF('4.1 Revenue Build - VCU'!N$7='5.1 Project Dev''t & Monitoring'!$E$22,$E21,0)*N8 -> 0 | O21: =IF('4.1 Revenue Build - VCU'!O$7='5.1 Project Dev''t & Monitoring'!$E$22,$E21,0)*O8 -> 0 | ... AL21: =IF('4.1 Revenue Build - VCU'!AL$7='5.1 Project Dev''t & Monitoring'!$E$22,$E21,0)*AL8 -> 0
C22: Year of validation | D22: Year | E22: ='3. Assumptions'!F24 -> 2
B23: ="Total "&B10 -> Total Project Development Cost | D23: USD | E23: =SUM(H23:AL23) -> 564159 | H23: =SUM(H12:H17,H21:H22) -> 309500 | I23: =SUM(I12:I17,I21:I22) -> 254659 | J23: =SUM(J13:J16,J21:J22) -> 0 | K23: =SUM(K13:K16,K21:K22) -> 0 | L23: =SUM(L13:L16,L21:L22) -> 0 | M23: =SUM(M13:M16,M21:M22) -> 0 | N23: =SUM(N13:N16,N21:N22) -> 0 | O23: =SUM(O13:O16,O21:O22) -> 0 | P23: =SUM(P13:P16,P21:P22) -> 0 | Q23: =SUM(Q13:Q16,Q21:Q22) -> 0 | ... AL23: =SUM(AL13:AL16,AL21:AL22) -> 0
B24: =B23 -> Total Project Development Cost | D24: EUR | E24: =SUM(H24:AL24) -> 512173.4 | H24: =H23/'1. Project Summary'!$F$16 -> 280980.48 | I24: =I23/'1. Project Summary'!$F$16 -> 231192.92 | J24: =J23/'1. Project Summary'!$F$16 -> 0 | K24: =K23/'1. Project Summary'!$F$16 -> 0 | L24: =L23/'1. Project Summary'!$F$16 -> 0 | M24: =M23/'1. Project Summary'!$F$16 -> 0 | N24: =N23/'1. Project Summary'!$F$16 -> 0 | O24: =O23/'1. Project Summary'!$F$16 -> 0 | ... AL24: =AL23/'1. Project Summary'!$F$16 -> 0
B26: Project Monitoring Cost
B28: Registration Fees and Issuance Levies (VCS + CCB)
C29: Total VCU Issuance | D29: VCUs | E29: =SUM(H29:AL29) -> 8089676 | H29: ='4.1 Revenue Build - VCU'!H39 -> 0 | I29: ='4.1 Revenue Build - VCU'!I39 -> 0 | J29: ='4.1 Revenue Build - VCU'!J39 -> 45720 | K29: ='4.1 Revenue Build - VCU'!K39 -> 85356 | L29: ='4.1 Revenue Build - VCU'!L39 -> 127016 | M29: ='4.1 Revenue Build - VCU'!M39 -> 173232 | N29: ='4.1 Revenue Build - VCU'!N39 -> 219448 | O29: ='4.1 Revenue Build - VCU'!O39 -> 265664 | ... AL29: ='4.1 Revenue Build - VCU'!AL39 -> 311880
B31: 1 | C31: Verra Registry Account Opening Fee VCS | D31: USD | E31: ='3. Assumptions'!F39 -> 500 | H31: =$E31*H$8 -> 510
B33: 2 | C33: VCS Account Maintenance Fee | D33: ='3. Assumptions'!D40 -> USD per annum | E33: ='3. Assumptions'!F39 -> 500 | H33: =$E33*H$8 -> 510 | I33: =$E33*I$8 -> 520.2 | J33: =$E33*J$8 -> 530.604 | K33: =$E33*K$8 -> 541.21608 | L33: =$E33*L$8 -> 552.0404 | M33: =$E33*M$8 -> 563.08121 | N33: =$E33*N$8 -> 574.34283 | O33: =$E33*O$8 -> 585.82969 | ... AL33: =$E33*AL$8 -> 923.79441
B35: 3 | C35: VCS Pipeline Listing request fee | D35: ='3. Assumptions'!D41 -> USD | E35: ='3. Assumptions'!F41 -> 1000 | H35: =$E35*H$8 -> 1020
B37: 4 | C37: Project registeration request review fee | D37: ='3. Assumptions'!D42 -> USD | E37: ='3. Assumptions'!F42 -> 2500 | H37: =$E37*H$8 -> 2550
B39: 5 | C39: VCS Issuance Levy | D39: ='3. Assumptions'!D43 -> USD per VCU | E39: ='3. Assumptions'!F43 -> 0.2 | H39: =H29*$E39*H$8 -> 0 | I39: =I29*$E39*I$8 -> 0 | J39: =J29*$E39*J$8 -> 9703.686 | K39: =K29*$E39*K$8 -> 18478.416 | L39: =L29*$E39*L$8 -> 28047.185 | M39: =M29*$E39*M$8 -> 39017.474 | N39: =N29*$E39*N$8 -> 50415.354 | O39: =O29*$E39*O$8 -> 62253.544 | ... AL39: =AL29*$E39*AL$8 -> 115245.2
B41: 6 | C41: CCB Label Fee | D41: ='3. Assumptions'!D44 -> USD per label | E41: ='3. Assumptions'!F44 -> 0.07 | H41: =H29*$E41*H$8 -> 0 | I41: =I29*$E41*I$8 -> 0 | J41: =J29*$E41*J$8 -> 3396.2901 | K41: =K29*$E41*K$8 -> 6467.4456 | L41: =L29*$E41*L$8 -> 9816.5149 | M41: =M29*$E41*M$8 -> 13656.116 | N41: =N29*$E41*N$8 -> 17645.374 | O41: =O29*$E41*O$8 -> 21788.74 | ... AL41: =AL29*$E41*AL$8 -> 40335.82
B43: 7 | C43: VCS Verification
C44: VCS | D44: USD | E44: ='3. Assumptions'!F46 -> 15000 | H44: =(IF(H$6<'5.1 Project Dev''t & Monitoring'!$E$46,0,IF(MOD(H$6-'5.1 Project Dev''t & Monitoring'!$E$46,'5.1 Project Dev''t & Monitoring'!$E$47)=0,'5.1 Project Dev''t & Monitoring'!$E$44,0)))*H$8 -> 0 | I44: =(IF(I$6<'5.1 Project Dev''t & Monitoring'!$E$46,0,IF(MOD(I$6-'5.1 Project Dev''t & Monitoring'!$E$46,'5.1 Project Dev''t & Monitoring'!$E$47)=0,'5.1 Project Dev''t & Monitoring'!$E$44,0)))*I$8 -> 15606 | J44: =(IF(J$6<'5.1 Project Dev''t & Monitoring'!$E$46,0,IF(MOD(J$6-'5.1 Project Dev''t & Monitoring'!$E$46,'5.1 Project Dev''t & Monitoring'!$E$47)=0,'5.1 Project Dev''t & Monitoring'!$E$44,0)))*J$8 -> 0 | K44: =(IF(K$6<'5.1 Project Dev''t & Monitoring'!$E$46,0,IF(MOD(K$6-'5.1 Project Dev''t & Monitoring'!$E$46,'5.1 Project Dev''t & Monitoring'!$E$47)=0,'5.1 Project Dev''t & Monitoring'!$E$44,0)))*K$8 -> 16236.482 | L44: =(IF(L$6<'5.1 Project Dev''t & Monitoring'!$E$46,0,IF(MOD(L$6-'5.1 Project Dev''t & Monitoring'!$E$46,'5.1 Project Dev''t & Monitoring'!$E$47)=0,'5.1 Project Dev''t & Monitoring'!$E$44,0)))*L$8 -> 0 | M44: =(IF(M$6<'5.1 Project Dev''t & Monitoring'!$E$46,0,IF(MOD(M$6-'5.1 Project Dev''t & Monitoring'!$E$46,'5.1 Project Dev''t & Monitoring'!$E$47)=0,'5.1 Project Dev''t & Monitoring'!$E$44,0)))*M$8 -> 16892.436 | N44: =(IF(N$6<'5.1 Project Dev''t & Monitoring'!$E$46,0,IF(MOD(N$6-'5.1 Project Dev''t & Monitoring'!$E$46,'5.1 Project Dev''t & Monitoring'!$E$47)=0,'5.1 Project Dev''t & Monitoring'!$E$44,0)))*N$8 -> 0 | O44: =(IF(O$6<'5.1 Project Dev''t & Monitoring'!$E$46,0,IF(MOD(O$6-'5.1 Project Dev''t & Monitoring'!$E$46,'5.1 Project Dev''t & Monitoring'!$E$47)=0,'5.1 Project Dev''t & Monitoring'!$E$44,0)))*O$8 -> 17574.891 | ... AL44: =(IF(AL$6<'5.1 Project Dev''t & Monitoring'!$E$46,0,IF(MOD(AL$6-'5.1 Project Dev''t & Monitoring'!$E$46,'5.1 Project Dev''t & Monitoring'!$E$47)=0,'5.1 Project Dev''t & Monitoring'!$E$44,0)))*AL$8 -> 0
C45: CCB | D45: USD | E45: ='3. Assumptions'!F47 -> 5000 | H45: =(IF(H$6<'5.1 Project Dev''t & Monitoring'!$E$46,0,IF(MOD(H$6-'5.1 Project Dev''t & Monitoring'!$E$46,'5.1 Project Dev''t & Monitoring'!$E$47)=0,'5.1 Project Dev''t & Monitoring'!$E$45,0)))*H$8 -> 0 | I45: =(IF(I$6<'5.1 Project Dev''t & Monitoring'!$E$46,0,IF(MOD(I$6-'5.1 Project Dev''t & Monitoring'!$E$46,'5.1 Project Dev''t & Monitoring'!$E$47)=0,'5.1 Project Dev''t & Monitoring'!$E$45,0)))*I$8 -> 5202 | J45: =(IF(J$6<'5.1 Project Dev''t & Monitoring'!$E$46,0,IF(MOD(J$6-'5.1 Project Dev''t & Monitoring'!$E$46,'5.1 Project Dev''t & Monitoring'!$E$47)=0,'5.1 Project Dev''t & Monitoring'!$E$45,0)))*J$8 -> 0 | K45: =(IF(K$6<'5.1 Project Dev''t & Monitoring'!$E$46,0,IF(MOD(K$6-'5.1 Project Dev''t & Monitoring'!$E$46,'5.1 Project Dev''t & Monitoring'!$E$47)=0,'5.1 Project Dev''t & Monitoring'!$E$45,0)))*K$8 -> 5412.1608 | L45: =(IF(L$6<'5.1 Project Dev''t & Monitoring'!$E$46,0,IF(MOD(L$6-'5.1 Project Dev''t & Monitoring'!$E$46,'5.1 Project Dev''t & Monitoring'!$E$47)=0,'5.1 Project Dev''t & Monitoring'!$E$45,0)))*L$8 -> 0 | M45: =(IF(M$6<'5.1 Project Dev''t & Monitoring'!$E$46,0,IF(MOD(M$6-'5.1 Project Dev''t & Monitoring'!$E$46,'5.1 Project Dev''t & Monitoring'!$E$47)=0,'5.1 Project Dev''t & Monitoring'!$E$45,0)))*M$8 -> 5630.8121 | N45: =(IF(N$6<'5.1 Project Dev''t & Monitoring'!$E$46,0,IF(MOD(N$6-'5.1 Project Dev''t & Monitoring'!$E$46,'5.1 Project Dev''t & Monitoring'!$E$47)=0,'5.1 Project Dev''t & Monitoring'!$E$45,0)))*N$8 -> 0 | O45: =(IF(O$6<'5.1 Project Dev''t & Monitoring'!$E$46,0,IF(MOD(O$6-'5.1 Project Dev''t & Monitoring'!$E$46,'5.1 Project Dev''t & Monitoring'!$E$47)=0,'5.1 Project Dev''t & Monitoring'!$E$45,0)))*O$8 -> 5858.2969 | ... AL45: =(IF(AL$6<'5.1 Project Dev''t & Monitoring'!$E$46,0,IF(MOD(AL$6-'5.1 Project Dev''t & Monitoring'!$E$46,'5.1 Project Dev''t & Monitoring'!$E$47)=0,'5.1 Project Dev''t & Monitoring'!$E$45,0)))*AL$8 -> 0
C46: First Verification Year | D46: year | E46: ='3. Assumptions'!F25 -> 2
C47: Verification Interval Thereafter | D47: year | E47: ='3. Assumptions'!F26 -> 2
B49: 8 | C49: Revision
C50: VCS Baseline Revision and Validation | D50: USD | E50: ='3. Assumptions'!F48 -> 18000 | H50: =(IF(H$6<'5.1 Project Dev''t & Monitoring'!$E$51,0,IF(MOD(H$6-$E$52,'5.1 Project Dev''t & Monitoring'!$E$51)=0,'5.1 Project Dev''t & Monitoring'!$E$50,0)))*H8 -> 0 | I50: =(IF(I$6<'5.1 Project Dev''t & Monitoring'!$E$51,0,IF(MOD(I$6-$E$52,'5.1 Project Dev''t & Monitoring'!$E$51)=0,'5.1 Project Dev''t & Monitoring'!$E$50,0)))*I8 -> 0 | J50: =(IF(J$6<'5.1 Project Dev''t & Monitoring'!$E$51,0,IF(MOD(J$6-$E$52,'5.1 Project Dev''t & Monitoring'!$E$51)=0,'5.1 Project Dev''t & Monitoring'!$E$50,0)))*J8 -> 0 | K50: =(IF(K$6<'5.1 Project Dev''t & Monitoring'!$E$51,0,IF(MOD(K$6-$E$52,'5.1 Project Dev''t & Monitoring'!$E$51)=0,'5.1 Project Dev''t & Monitoring'!$E$50,0)))*K8 -> 0 | L50: =(IF(L$6<'5.1 Project Dev''t & Monitoring'!$E$51,0,IF(MOD(L$6-$E$52,'5.1 Project Dev''t & Monitoring'!$E$51)=0,'5.1 Project Dev''t & Monitoring'!$E$50,0)))*L8 -> 0 | M50: =(IF(M$6<'5.1 Project Dev''t & Monitoring'!$E$51,0,IF(MOD(M$6-$E$52,'5.1 Project Dev''t & Monitoring'!$E$51)=0,'5.1 Project Dev''t & Monitoring'!$E$50,0)))*M8 -> 0 | N50: =(IF(N$6<'5.1 Project Dev''t & Monitoring'!$E$51,0,IF(MOD(N$6-$E$52,'5.1 Project Dev''t & Monitoring'!$E$51)=0,'5.1 Project Dev''t & Monitoring'!$E$50,0)))*N8 -> 0 | O50: =(IF(O$6<'5.1 Project Dev''t & Monitoring'!$E$51,0,IF(MOD(O$6-$E$52,'5.1 Project Dev''t & Monitoring'!$E$51)=0,'5.1 Project Dev''t & Monitoring'!$E$50,0)))*O8 -> 21089.869 | ... AL50: =(IF(AL$6<'5.1 Project Dev''t & Monitoring'!$E$51,0,IF(MOD(AL$6-$E$52,'5.1 Project Dev''t & Monitoring'!$E$51)=0,'5.1 Project Dev''t & Monitoring'!$E$50,0)))*AL8 -> 0
C51: Frequency of Revisions | D51: year | E51: ='3. Assumptions'!F27 -> 6
C52: Year of Validation | D52: year | E52: =E22 -> 2
B54: 9 | C54: Subsequent MIRs Cost | D54: USD | E54: ='3. Assumptions'!F49 -> 50000 | H54: =0 -> 0 | I54: =$E$54*I8 -> 52020 | J54: =$E$54*J8 -> 53060.4 | K54: =$E$54*K8 -> 54121.608 | L54: =$E$54*L8 -> 55204.04 | M54: =$E$54*M8 -> 56308.121 | N54: =$E$54*N8 -> 57434.283 | O54: =$E$54*O8 -> 58582.969 | P54: =$E$54*P8 -> 59754.628 | ... AL54: =$E$54*AL8 -> 92379.441
B56: ="Total "&B26 -> Total Project Monitoring Cost | D56: USD | E56: =SUM(H56:AL56) -> 5839169.8 | H56: =+H31+H33+H35+H37+H39+H54+H44+H50+H41+H45 -> 4590 | I56: =+I31+I33+I35+I37+I39+I54+I44+I50+I41+I45 -> 73348.2 | J56: =+J31+J33+J35+J37+J39+J54+J44+J50+J41+J45 -> 66690.98 | K56: =+K31+K33+K35+K37+K39+K54+K44+K50+K41+K45 -> 101257.33 | L56: =+L31+L33+L35+L37+L39+L54+L44+L50+L41+L45 -> 93619.781 | M56: =+M31+M33+M35+M37+M39+M54+M44+M50+M41+M45 -> 132068.04 | N56: =+N31+N33+N35+N37+N39+N54+N44+N50+N41+N45 -> 126069.35 | O56: =+O31+O33+O35+O37+O39+O54+O44+O50+O41+O45 -> 187734.14 | ... AL56: =+AL31+AL33+AL35+AL37+AL39+AL54+AL44+AL50+AL41+AL45 -> 248884.26
B57: =B56 -> Total Project Monitoring Cost | D57: EUR | E57: =SUM(H57:AL57) -> 5301107.4 | H57: =H56/'1. Project Summary'!$F$16 -> 4167.0449 | I57: =I56/'1. Project Summary'!$F$16 -> 66589.378 | J57: =J56/'1. Project Summary'!$F$16 -> 60545.601 | K57: =K56/'1. Project Summary'!$F$16 -> 91926.762 | L57: =L56/'1. Project Summary'!$F$16 -> 84992.992 | M57: =M56/'1. Project Summary'!$F$16 -> 119898.36 | N57: =N56/'1. Project Summary'!$F$16 -> 114452.43 | O57: =O56/'1. Project Summary'!$F$16 -> 170434.99 | ... AL57: =AL56/'1. Project Summary'!$F$16 -> 225950.3
N88: =$F88*N$5 -> 0

Sheet 5.2 Cost Build - ARR
B2: ='1. Project Summary'!B2 -> Projections - Serious Shea
B3: ='1. Project Summary'!B3 -> (in EUR, unless otherwise stated)
B5: Cost Build | G5: Unit | H5: ='2. NPV'!H47 -> 2024 | I5: ='2. NPV'!I47 -> 2025 | J5: ='2. NPV'!J47 -> 2026 | K5: ='2. NPV'!K47 -> 2027 | L5: ='2. NPV'!L47 -> 2028 | M5: ='2. NPV'!M47 -> 2029 | N5: ='2. NPV'!N47 -> 2030 | O5: ='2. NPV'!O47 -> 2031 | ... AL5: ='2. NPV'!AL47 -> 2054
B6: ARR | H6: =Period_Start -> 1 | I6: =H6+1 -> 2 | J6: =I6+1 -> 3 | K6: =J6+1 -> 4 | L6: =K6+1 -> 5 | M6: =L6+1 -> 6 | N6: =M6+1 -> 7 | O6: =N6+1 -> 8 | P6: =O6+1 -> 9 | ... AL6: =AK6+1 -> 31
B8: Cost Inflation | E8: ='1. Project Summary'!F15 -> 0.02 | G8: Index | H8: =(1+$E8)^H$6 -> 1.02 | I8: =(1+$E8)^I$6 -> 1.0404 | J8: =(1+$E8)^J$6 -> 1.061208 | K8: =(1+$E8)^K$6 -> 1.0824322 | L8: =(1+$E8)^L$6 -> 1.1040808 | M8: =(1+$E8)^M$6 -> 1.1261624 | N8: =(1+$E8)^N$6 -> 1.1486857 | O8: =(1+$E8)^O$6 -> 1.1716594 | ... AL8: =(1+$E8)^AL$6 -> 1.8475888
B10: Nursery Cost
C12: Trees produced | G12: # of trees | H12: ='3. Assumptions'!E53 -> 1000000 | I12: ='3. Assumptions'!F53 -> 1600000 | J12: ='3. Assumptions'!G53 -> 1600000 | K12: ='3. Assumptions'!H53 -> 1600000 | L12: ='3. Assumptions'!I53 -> 1600000 | M12: ='3. Assumptions'!J53 -> 1600000 | N12: ='3. Assumptions'!K53 -> 1600000 | O12: ='3. Assumptions'!L53 -> 1600000 | ... AL12: ='3. Assumptions'!AI53 -> 0
B13: Total Trees Produced | G13: # of trees | H13: =SUM($H$12:H12) -> 1000000 | I13: =SUM($H$12:I12) -> 2600000 | J13: =SUM($H$12:J12) -> 4200000 | K13: =SUM($H$12:K12) -> 5800000 | L13: =SUM($H$12:L12) -> 7400000 | M13: =SUM($H$12:M12) -> 9000000 | N13: =SUM($H$12:N12) -> 10600000 | O13: =SUM($H$12:O12) -> 12200000 | ... AL13: =SUM($H$12:AL12) -> 12200000
C15: Nurseries to be added | G15: # of nurseries | H15: ='3. Assumptions'!E80 -> 1 | I15: ='3. Assumptions'!F80 -> 1 | J15: ='3. Assumptions'!G80 -> 0 | K15: ='3. Assumptions'!H80 -> 0 | L15: ='3. Assumptions'!I80 -> 0 | M15: ='3. Assumptions'!J80 -> 0 | N15: ='3. Assumptions'!K80 -> 0 | O15: ='3. Assumptions'!L80 -> 0 | ... AL15: ='3. Assumptions'!AI80 -> 0
B16: Total Nurseries | G16: # of nurseries | H16: =SUM($H$15:H15) -> 1 | I16: =SUM($H$15:I15) -> 2 | J16: =SUM($H$15:J15) -> 2 | K16: =SUM($H$15:K15) -> 2 | L16: =SUM($H$15:L15) -> 2 | M16: =SUM($H$15:M15) -> 2 | N16: =SUM($H$15:N15) -> 2 | O16: =SUM($H$15:O15) -> 2 | ... AL16: =SUM($H$15:AL15) -> 2
C18: Nursery Production Capacity | D18: Seedlings p.a | E18: ='3. Assumptions'!E60 -> 1000000 | G18: # of seedlings | H18: =$E$18*H16 -> 1000000 | I18: =$E$18*I16 -> 2000000 | J18: =$E$18*J16 -> 2000000 | K18: =$E$18*K16 -> 2000000 | L18: =$E$18*L16 -> 2000000 | M18: =$E$18*M16 -> 2000000 | N18: =$E$18*N16 -> 2000000 | O18: =$E$18*O16 -> 2000000 | ... AL18: =$E$18*AL16 -> 2000000
B20: Nursery CAPEX
C21: Land | D21: CAPEX per nursery | E21: ='3. Assumptions'!G64 -> 75000 | G21: EUR | H21: =$E21*H$15*H$8 -> 76500 | I21: =$E21*I$15*I$8 -> 78030 | J21: =$E21*J$15*J$8 -> 0 | K21: =$E21*K$15*K$8 -> 0 | L21: =$E21*L$15*L$8 -> 0 | M21: =$E21*M$15*M$8 -> 0 | N21: =$E21*N$15*N$8 -> 0 | O21: =$E21*O$15*O$8 -> 0 | ... AL21: =$E21*AL$15*AL$8 -> 0
C22: Buildings | D22: CAPEX per nursery | E22: =SUM('3. Assumptions'!G65:G67) -> 137000 | G22: EUR | H22: =$E22*H$15*H$8 -> 139740 | I22: =$E22*I$15*I$8 -> 142534.8 | J22: =$E22*J$15*J$8 -> 0 | K22: =$E22*K$15*K$8 -> 0 | L22: =$E22*L$15*L$8 -> 0 | M22: =$E22*M$15*M$8 -> 0 | N22: =$E22*N$15*N$8 -> 0 | O22: =$E22*O$15*O$8 -> 0 | ... AL22: =$E22*AL$15*AL$8 -> 0
C23: Vehicles | D23: CAPEX per nursery | E23: =SUM('3. Assumptions'!G74:G76) -> 85250 | G23: EUR | H23: =$E23*H$15*H$8 -> 86955 | I23: =$E23*I$15*I$8 -> 88694.1 | J23: =$E23*J$15*J$8 -> 0 | K23: =$E23*K$15*K$8 -> 0 | L23: =$E23*L$15*L$8 -> 0 | M23: =$E23*M$15*M$8 -> 0 | N23: =$E23*N$15*N$8 -> 0 | O23: =$E23*O$15*O$8 -> 0 | ... AL23: =$E23*AL$15*AL$8 -> 0
C24: Irrigation | D24: CAPEX per nursery | E24: =SUM('3. Assumptions'!G68:G72) -> 137593.75 | G24: EUR | H24: =$E24*H$15*H$8 -> 140345.62 | I24: =$E24*I$15*I$8 -> 143152.54 | J24: =$E24*J$15*J$8 -> 0 | K24: =$E24*K$15*K$8 -> 0 | L24: =$E24*L$15*L$8 -> 0 | M24: =$E24*M$15*M$8 -> 0 | N24: =$E24*N$15*N$8 -> 0 | O24: =$E24*O$15*O$8 -> 0 | ... AL24: =$E24*AL$15*AL$8 -> 0
C25: Nursery trays | D25: CAPEX per nursery | E25: ='3. Assumptions'!G73 -> 100000 | G25: EUR | H25: =$E25*H$15*H$8 -> 102000 | I25: =$E25*I$15*I$8 -> 104040 | J25: =$E25*J$15*J$8 -> 0 | K25: =$E25*K$15*K$8 -> 0 | L25: =$E25*L$15*L$8 -> 0 | M25: =$E25*M$15*M$8 -> 0 | N25: =$E25*N$15*N$8 -> 0 | O25: =$E25*O$15*O$8 -> 0 | ... AL25: =$E25*AL$15*AL$8 -> 0
B26: ="Total "&B20 -> Total Nursery CAPEX | E26: =SUM(E21:E25) -> 534843.75 | G26: EUR | H26: =SUM(H21:H25) -> 545540.62 | I26: =SUM(I21:I25) -> 556451.44 | J26: =SUM(J21:J25) -> 0 | K26: =SUM(K21:K25) -> 0 | L26: =SUM(L21:L25) -> 0 | M26: =SUM(M21:M25) -> 0 | N26: =SUM(N21:N25) -> 0 | O26: =SUM(O21:O25) -> 0 | ... AL26: =SUM(AL21:AL25) -> 0
B28: Nursery OPEX
C29: Production fees to Cooperatives | D29: Fee per tree | E29: ='3. Assumptions'!E85 -> 0.5 | G29: EUR | H29: =H$12*$E29*H$8 -> 510000 | I29: =I$12*$E29*I$8 -> 832320 | J29: =J$12*$E29*J$8 -> 848966.4 | K29: =K$12*$E29*K$8 -> 865945.73 | L29: =L$12*$E29*L$8 -> 883264.64 | M29: =M$12*$E29*M$8 -> 900929.94 | N29: =N$12*$E29*N$8 -> 918948.53 | O29: =O$12*$E29*O$8 -> 937327.5 | ... AL29: =AL$12*$E29*AL$8 -> 0
C30: Supplies | D30: Cost per tree | E30: ='3. Assumptions'!E86 -> 0.3 | G30: EUR | H30: =H$12*$E30*H$8 -> 306000 | I30: =I$12*$E30*I$8 -> 499392 | J30: =J$12*$E30*J$8 -> 509379.84 | K30: =K$12*$E30*K$8 -> 519567.44 | L30: =L$12*$E30*L$8 -> 529958.79 | M30: =M$12*$E30*M$8 -> 540557.96 | N30: =N$12*$E30*N$8 -> 551369.12 | O30: =O$12*$E30*O$8 -> 562396.5 | ... AL30: =AL$12*$E30*AL$8 -> 0
B31: ="Total "&B28 -> Total Nursery OPEX | G31: EUR | H31: =SUM(H29:H30) -> 816000 | I31: =SUM(I29:I30) -> 1331712 | J31: =SUM(J29:J30) -> 1358346.2 | K31: =SUM(K29:K30) -> 1385513.2 | L31: =SUM(L29:L30) -> 1413223.4 | M31: =SUM(M29:M30) -> 1441487.9 | N31: =SUM(N29:N30) -> 1470317.7 | O31: =SUM(O29:O30) -> 1499724 | ... AL31: =SUM(AL29:AL30) -> 0
B33: Plantation Cost
B35: Plantation & Transportation Cost | E35: Unit cost
C36: Trees to be Planted | G36: # of trees | I36: =H12 -> 1000000 | J36: =I12 -> 1600000 | K36: =J12 -> 1600000 | L36: =K12 -> 1600000 | M36: =L12 -> 1600000 | N36: =M12 -> 1600000 | O36: =N12 -> 1600000 | P36: =O12 -> 1600000 | ... AL36: =AK12 -> 0
C37: Plantation and Transport | D37: EUR per tree | E37: ='3. Assumptions'!E91 -> 0.4 | G37: EUR | H37: =H36*$E37*H8 -> 0 | I37: =I36*$E37*I8 -> 416160 | J37: =J36*$E37*J8 -> 679173.12 | K37: =K36*$E37*K8 -> 692756.58 | L37: =L36*$E37*L8 -> 706611.71 | M37: =M36*$E37*M8 -> 720743.95 | N37: =N36*$E37*N8 -> 735158.83 | O37: =O36*$E37*O8 -> 749862 | ... AL37: =AL36*$E37*AL8 -> 0
B38: ="Total "&B35 -> Total Plantation & Transportation Cost | G38: EUR | H38: =H37 -> 0 | I38: =I37 -> 416160 | J38: =J37 -> 679173.12 | K38: =K37 -> 692756.58 | L38: =L37 -> 706611.71 | M38: =M37 -> 720743.95 | N38: =N37 -> 735158.83 | O38: =O37 -> 749862 | ... AL38: =AL37 -> 0
C40: Trees Planted | G40: # of trees | I40: =I36 -> 1000000 | J40: =J36 -> 1600000 | K40: =K36 -> 1600000 | L40: =L36 -> 1600000 | M40: =M36 -> 1600000 | N40: =N36 -> 1600000 | O40: =O36 -> 1600000 | P40: =P36 -> 1600000 | ... AL40: =AL36 -> 0
C41: Tree loss | E41: ='3. Assumptions'!E56 -> 0.15 | G41: # of trees | I41: =H40*$E41 -> 0 | J41: =I40*$E41 -> 150000 | K41: =J40*$E41 -> 240000 | L41: =K40*$E41 -> 240000 | M41: =L40*$E41 -> 240000 | N41: =M40*$E41 -> 240000 | O41: =N40*$E41 -> 240000 | P41: =O40*$E41 -> 240000 | ... AL41: =AK40*$E41 -> 0
B42: Trees on the ground | G42: # of trees | H42: =H40-I41 -> 0 | I42: =I40-J41 -> 850000 | J42: =J40-K41 -> 1360000 | K42: =K40-L41 -> 1360000 | L42: =L40-M41 -> 1360000 | M42: =M40-N41 -> 1360000 | N42: =N40-O41 -> 1360000 | O42: =O40-P41 -> 1360000 | ... AL42: =AL40-AM41 -> 0
B43: Total trees on the ground | G43: # of trees | H43: =SUM($H$42:H42) -> 0 | I43: =SUM($H$42:I42) -> 850000 | J43: =SUM($H$42:J42) -> 2210000 | K43: =SUM($H$42:K42) -> 3570000 | L43: =SUM($H$42:L42) -> 4930000 | M43: =SUM($H$42:M42) -> 6290000 | N43: =SUM($H$42:N42) -> 7650000 | O43: =SUM($H$42:O42) -> 9010000 | ... AL43: =SUM($H$42:AL42) -> 10370000
B45: # of trees to be Maintained
C46: 2024 | G46: # of trees | J46: =I40-J41 -> 850000 | K46: =I40-J41 -> 850000 | L46: =K46 -> 850000
C47: =C46+1 -> 2025 | G47: # of trees | K47: =J40-K41 -> 1360000 | L47: =J40-K41 -> 1360000 | M47: =L47 -> 1360000
C48: =C47+1 -> 2026 | G48: # of trees | L48: =K40-L41 -> 1360000 | M48: =K40-L41 -> 1360000 | N48: =M48 -> 1360000
C49: =C48+1 -> 2027 | G49: # of trees | M49: =L40-M41 -> 1360000 | N49: =L40-M41 -> 1360000 | O49: =N49 -> 1360000
C50: =C49+1 -> 2028 | G50: # of trees | N50: =M40-N41 -> 1360000 | O50: =M40-N41 -> 1360000 | P50: =O50 -> 1360000
C51: =C50+1 -> 2029 | G51: # of trees | O51: =N40-O41 -> 1360000 | P51: =N40-O41 -> 1360000 | Q51: =P51 -> 1360000
C52: =C51+1 -> 2030 | G52: # of trees | P52: =O40-P41 -> 1360000 | Q52: =O40-P41 -> 1360000 | R52: =Q52 -> 1360000
C53: =C52+1 -> 2031 | G53: # of trees | Q53: =P40-Q41 -> 1360000 | R53: =P40-Q41 -> 1360000 | S53: =R53 -> 1360000
B54: ="Total "&B45 -> Total # of trees to be Maintained | G54: # of trees | H54: =SUM(H46:H53) -> 0 | I54: =SUM(I46:I53) -> 0 | J54: =SUM(J46:J53) -> 850000 | K54: =SUM(K46:K53) -> 2210000 | L54: =SUM(L46:L53) -> 3570000 | M54: =SUM(M46:M53) -> 4080000 | N54: =SUM(N46:N53) -> 4080000 | O54: =SUM(O46:O53) -> 4080000 | ... AL54: =SUM(AL46:AL53) -> 0
B56: Maintenance Cost | E56: ='3. Assumptions'!E92 -> 0.1 | G56: EUR | H56: =$E56*H54*H8 -> 0 | I56: =$E56*I54*I8 -> 0 | J56: =$E56*J54*J8 -> 90202.68 | K56: =$E56*K54*K8 -> 239217.51 | L56: =$E56*L54*L8 -> 394156.85 | M56: =$E56*M54*M8 -> 459474.27 | N56: =$E56*N54*N8 -> 468663.75 | O56: =$E56*O54*O8 -> 478037.03 | ... AL56: =$E56*AL54*AL8 -> 0
B58: Plantation Overhead
B60: Salary | D60: Annual salary | E60: CAGR
C61: Headcount
C62: ='3. Assumptions'!C98 -> Country Manager | G62: headcount | H62: ='3. Assumptions'!G98 -> 1 | I62: ='3. Assumptions'!H98 -> 1 | J62: ='3. Assumptions'!I98 -> 1 | K62: ='3. Assumptions'!J98 -> 1 | L62: ='3. Assumptions'!K98 -> 1 | M62: ='3. Assumptions'!L98 -> 1 | N62: ='3. Assumptions'!M98 -> 1 | O62: ='3. Assumptions'!N98 -> 1 | P62: ='3. Assumptions'!O98 -> 1 | Q62: =P62 -> 1 | R62: =Q62 -> 1 | S62: =R62 -> 1 | T62: =S62 -> 1 | U62: =T62 -> 1 | V62: =U62 -> 1 | W62: =V62 -> 1 | X62: =W62 -> 1 | ... AL62: =AK62 -> 1
C63: ='3. Assumptions'!C99 -> Director of Reforestation Operations | G63: headcount | H63: ='3. Assumptions'!G99 -> 0 | I63: ='3. Assumptions'!H99 -> 1 | J63: ='3. Assumptions'!I99 -> 1 | K63: ='3. Assumptions'!J99 -> 1 | L63: ='3. Assumptions'!K99 -> 1 | M63: ='3. Assumptions'!L99 -> 1 | N63: ='3. Assumptions'!M99 -> 1 | O63: ='3. Assumptions'!N99 -> 1 | P63: ='3. Assumptions'!O99 -> 1 | Q63: =P63 -> 1 | R63: =Q63 -> 1 | S63: =R63 -> 1 | T63: =S63 -> 1 | U63: =T63 -> 1 | V63: =U63 -> 1 | W63: =V63 -> 1 | X63: =W63 -> 1 | ... AL63: =AK63 -> 1
C64: ='3. Assumptions'!C100 -> CFO | G64: headcount | H64: ='3. Assumptions'!G100 -> 1 | I64: ='3. Assumptions'!H100 -> 1 | J64: ='3. Assumptions'!I100 -> 1 | K64: ='3. Assumptions'!J100 -> 1 | L64: ='3. Assumptions'!K100 -> 1 | M64: ='3. Assumptions'!L100 -> 1 | N64: ='3. Assumptions'!M100 -> 1 | O64: ='3. Assumptions'!N100 -> 1 | P64: ='3. Assumptions'!O100 -> 1 | Q64: =P64 -> 1 | R64: =Q64 -> 1 | S64: =R64 -> 1 | T64: =S64 -> 1 | U64: =T64 -> 1 | V64: =U64 -> 1 | W64: =V64 -> 1 | X64: =W64 -> 1 | ... AL64: =AK64 -> 1
C65: ='3. Assumptions'!C101 -> Director of HR | G65: headcount | H65: ='3. Assumptions'!G101 -> 0 | I65: ='3. Assumptions'!H101 -> 1 | J65: ='3. Assumptions'!I101 -> 1 | K65: ='3. Assumptions'!J101 -> 1 | L65: ='3. Assumptions'!K101 -> 1 | M65: ='3. Assumptions'!L101 -> 1 | N65: ='3. Assumptions'!M101 -> 1 | O65: ='3. Assumptions'!N101 -> 1 | P65: ='3. Assumptions'!O101 -> 1 | Q65: =P65 -> 1 | R65: =Q65 -> 1 | S65: =R65 -> 1 | T65: =S65 -> 1 | U65: =T65 -> 1 | V65: =U65 -> 1 | W65: =V65 -> 1 | X65: =W65 -> 1 | ... AL65: =AK65 -> 1
C66: ='3. Assumptions'!C102 -> Director of Partnership&ITC | G66: headcount | H66: ='3. Assumptions'!G102 -> 1 | I66: ='3. Assumptions'!H102 -> 1 | J66: ='3. Assumptions'!I102 -> 1 | K66: ='3. Assumptions'!J102 -> 1 | L66: ='3. Assumptions'!K102 -> 1 | M66: ='3. Assumptions'!L102 -> 1 | N66: ='3. Assumptions'!M102 -> 1 | O66: ='3. Assumptions'!N102 -> 1 | P66: ='3. Assumptions'!O102 -> 1 | Q66: =P66 -> 1 | R66: =Q66 -> 1 | S66: =R66 -> 1 | T66: =S66 -> 1 | U66: =T66 -> 1 | V66: =U66 -> 1 | W66: =V66 -> 1 | X66: =W66 -> 1 | ... AL66: =AK66 -> 1
C67: ='3. Assumptions'!C103 -> Managers | G67: headcount | H67: ='3. Assumptions'!G103 -> 10 | I67: ='3. Assumptions'!H103 -> 4 | J67: ='3. Assumptions'!I103 -> 4 | K67: ='3. Assumptions'!J103 -> 4 | L67: ='3. Assumptions'!K103 -> 6 | M67: ='3. Assumptions'!L103 -> 6 | N67: ='3. Assumptions'!M103 -> 8 | O67: ='3. Assumptions'!N103 -> 8 | P67: ='3. Assumptions'!O103 -> 8 | Q67: =P67 -> 8 | R67: =Q67 -> 8 | S67: =R67 -> 8 | T67: =S67 -> 8 | U67: =T67 -> 8 | V67: =U67 -> 8 | W67: =V67 -> 8 | X67: =W67 -> 8 | ... AL67: =AK67 -> 8
C68: ='3. Assumptions'!C104 -> Technical Staff | G68: headcount | H68: ='3. Assumptions'!G104 -> 4 | I68: ='3. Assumptions'!H104 -> 4 | J68: ='3. Assumptions'!I104 -> 4 | K68: ='3. Assumptions'!J104 -> 4 | L68: ='3. Assumptions'!K104 -> 6 | M68: ='3. Assumptions'!L104 -> 6 | N68: ='3. Assumptions'!M104 -> 8 | O68: ='3. Assumptions'!N104 -> 8 | P68: ='3. Assumptions'!O104 -> 8 | Q68: =P68 -> 8 | R68: =Q68 -> 8 | S68: =R68 -> 8 | T68: =S68 -> 8 | U68: =T68 -> 8 | V68: =U68 -> 8 | W68: =V68 -> 8 | X68: =W68 -> 8 | ... AL68: =AK68 -> 8
C69: ='3. Assumptions'!C105 -> Forest Engineer | G69: headcount | H69: ='3. Assumptions'!G105 -> 2 | I69: ='3. Assumptions'!H105 -> 2 | J69: ='3. Assumptions'!I105 -> 2 | K69: ='3. Assumptions'!J105 -> 2 | L69: ='3. Assumptions'!K105 -> 3 | M69: ='3. Assumptions'!L105 -> 3 | N69: ='3. Assumptions'!M105 -> 4 | O69: ='3. Assumptions'!N105 -> 4 | P69: ='3. Assumptions'!O105 -> 4 | Q69: =P69 -> 4 | R69: =Q69 -> 4 | S69: =R69 -> 4 | T69: =S69 -> 4 | U69: =T69 -> 4 | V69: =U69 -> 4 | W69: =V69 -> 4 | X69: =W69 -> 4 | ... AL69: =AK69 -> 4
C70: ='3. Assumptions'!C106 -> Employees | G70: headcount | H70: ='3. Assumptions'!G106 -> 8 | I70: ='3. Assumptions'!H106 -> 8 | J70: ='3. Assumptions'!I106 -> 8 | K70: ='3. Assumptions'!J106 -> 8 | L70: ='3. Assumptions'!K106 -> 12 | M70: ='3. Assumptions'!L106 -> 12 | N70: ='3. Assumptions'!M106 -> 16 | O70: ='3. Assumptions'!N106 -> 16 | P70: ='3. Assumptions'!O106 -> 16 | Q70: =P70 -> 16 | R70: =Q70 -> 16 | S70: =R70 -> 16 | T70: =S70 -> 16 | U70: =T70 -> 16 | V70: =U70 -> 16 | W70: =V70 -> 16 | X70: =W70 -> 16 | ... AL70: =AK70 -> 16
C71: ='3. Assumptions'!C107 -> Executive Secretary | G71: headcount | H71: ='3. Assumptions'!G107 -> 1 | I71: ='3. Assumptions'!H107 -> 1 | J71: ='3. Assumptions'!I107 -> 1 | K71: ='3. Assumptions'!J107 -> 1 | L71: ='3. Assumptions'!K107 -> 1 | M71: ='3. Assumptions'!L107 -> 1 | N71: ='3. Assumptions'!M107 -> 1 | O71: ='3. Assumptions'!N107 -> 1 | P71: ='3. Assumptions'!O107 -> 1 | Q71: =P71 -> 1 | R71: =Q71 -> 1 | S71: =R71 -> 1 | T71: =S71 -> 1 | U71: =T71 -> 1 | V71: =U71 -> 1 | W71: =V71 -> 1 | X71: =W71 -> 1 | ... AL71: =AK71 -> 1
C72: ='3. Assumptions'!C108 -> Secretaries | G72: headcount | H72: ='3. Assumptions'!G108 -> 7 | I72: ='3. Assumptions'!H108 -> 3 | J72: ='3. Assumptions'!I108 -> 3 | K72: ='3. Assumptions'!J108 -> 3 | L72: ='3. Assumptions'!K108 -> 4 | M72: ='3. Assumptions'!L108 -> 4 | N72: ='3. Assumptions'!M108 -> 5 | O72: ='3. Assumptions'!N108 -> 5 | P72: ='3. Assumptions'!O108 -> 5 | Q72: =P72 -> 5 | R72: =Q72 -> 5 | S72: =R72 -> 5 | T72: =S72 -> 5 | U72: =T72 -> 5 | V72: =U72 -> 5 | W72: =V72 -> 5 | X72: =W72 -> 5 | ... AL72: =AK72 -> 5
C73: ='3. Assumptions'!C109 -> Trainees/Students | G73: headcount | H73: ='3. Assumptions'!G109 -> 10 | I73: ='3. Assumptions'!H109 -> 10 | J73: ='3. Assumptions'!I109 -> 10 | K73: ='3. Assumptions'!J109 -> 10 | L73: ='3. Assumptions'!K109 -> 15 | M73: ='3. Assumptions'!L109 -> 15 | N73: ='3. Assumptions'!M109 -> 20 | O73: ='3. Assumptions'!N109 -> 20 | P73: ='3. Assumptions'!O109 -> 20 | Q73: =P73 -> 20 | R73: =Q73 -> 20 | S73: =R73 -> 20 | T73: =S73 -> 20 | U73: =T73 -> 20 | V73: =U73 -> 20 | W73: =V73 -> 20 | X73: =W73 -> 20 | ... AL73: =AK73 -> 20
... C78: ='3. Assumptions'!C114 -> Security | G78: headcount | H78: ='3. Assumptions'!G114 -> 8 | I78: ='3. Assumptions'!H114 -> 5 | J78: ='3. Assumptions'!I114 -> 5 | K78: ='3. Assumptions'!J114 -> 5 | L78: ='3. Assumptions'!K114 -> 7 | M78: ='3. Assumptions'!L114 -> 7 | N78: ='3. Assumptions'!M114 -> 7 | O78: ='3. Assumptions'!N114 -> 7 | P78: ='3. Assumptions'!O114 -> 7 | Q78: =P78 -> 7 | R78: =Q78 -> 7 | S78: =R78 -> 7 | T78: =S78 -> 7 | U78: =T78 -> 7 | V78: =U78 -> 7 | W78: =V78 -> 7 | X78: =W78 -> 7 | ... AL78: =AK78 -> 7
C79: ="Total "&C61 -> Total Headcount | G79: headcount | H79: =SUM(H62:H78) -> 69 | I79: =SUM(I62:I78) -> 54 | J79: =SUM(J62:J78) -> 54 | K79: =SUM(K62:K78) -> 54 | L79: =SUM(L62:L78) -> 77 | M79: =SUM(M62:M78) -> 77 | N79: =SUM(N62:N78) -> 98 | O79: =SUM(O62:O78) -> 98 | ... AL79: =SUM(AL62:AL78) -> 98
C81: Salary | D81: Annual salary | E81: CAGR
C82: =C62 -> Country Manager | D82: ='3. Assumptions'!D98 -> 50000 | E82: =IF('1. Project Summary'!$F$13="Real",0,'3. Assumptions'!E98) -> 0.02 | G82: EUR | H82: =$D82*H62*(1+$E82)^H$6 -> 51000 | I82: =$D82*I62*(1+$E82)^I$6 -> 52020 | J82: =$D82*J62*(1+$E82)^J$6 -> 53060.4 | K82: =$D82*K62*(1+$E82)^K$6 -> 54121.608 | L82: =$D82*L62*(1+$E82)^L$6 -> 55204.04 | M82: =$D82*M62*(1+$E82)^M$6 -> 56308.121 | N82: =$D82*N62*(1+$E82)^N$6 -> 57434.283 | O82: =$D82*O62*(1+$E82)^O$6 -> 58582.969 | ... AL82: =$D82*AL62*(1+$E82)^AL$6 -> 92379.441
C83: =C63 -> Director of Reforestation Operations | D83: ='3. Assumptions'!D99 -> 25000 | E83: =IF('1. Project Summary'!$F$13="Real",0,'3. Assumptions'!E99) -> 0.02 | G83: EUR | H83: =$D83*H63*(1+$E83)^H$6 -> 0 | I83: =$D83*I63*(1+$E83)^I$6 -> 26010 | J83: =$D83*J63*(1+$E83)^J$6 -> 26530.2 | K83: =$D83*K63*(1+$E83)^K$6 -> 27060.804 | L83: =$D83*L63*(1+$E83)^L$6 -> 27602.02 | M83: =$D83*M63*(1+$E83)^M$6 -> 28154.06 | N83: =$D83*N63*(1+$E83)^N$6 -> 28717.142 | O83: =$D83*O63*(1+$E83)^O$6 -> 29291.485 | ... AL83: =$D83*AL63*(1+$E83)^AL$6 -> 46189.72
C84: =C64 -> CFO | D84: ='3. Assumptions'!D100 -> 25000 | E84: =IF('1. Project Summary'!$F$13="Real",0,'3. Assumptions'!E100) -> 0.02 | G84: EUR | H84: =$D84*H64*(1+$E84)^H$6 -> 25500 | I84: =$D84*I64*(1+$E84)^I$6 -> 26010 | J84: =$D84*J64*(1+$E84)^J$6 -> 26530.2 | K84: =$D84*K64*(1+$E84)^K$6 -> 27060.804 | L84: =$D84*L64*(1+$E84)^L$6 -> 27602.02 | M84: =$D84*M64*(1+$E84)^M$6 -> 28154.06 | N84: =$D84*N64*(1+$E84)^N$6 -> 28717.142 | O84: =$D84*O64*(1+$E84)^O$6 -> 29291.485 | ... AL84: =$D84*AL64*(1+$E84)^AL$6 -> 46189.72
C85: =C65 -> Director of HR | D85: ='3. Assumptions'!D101 -> 25000 | E85: =IF('1. Project Summary'!$F$13="Real",0,'3. Assumptions'!E101) -> 0.02 | G85: EUR | H85: =$D85*H65*(1+$E85)^H$6 -> 0 | I85: =$D85*I65*(1+$E85)^I$6 -> 26010 | J85: =$D85*J65*(1+$E85)^J$6 -> 26530.2 | K85: =$D85*K65*(1+$E85)^K$6 -> 27060.804 | L85: =$D85*L65*(1+$E85)^L$6 -> 27602.02 | M85: =$D85*M65*(1+$E85)^M$6 -> 28154.06 | N85: =$D85*N65*(1+$E85)^N$6 -> 28717.142 | O85: =$D85*O65*(1+$E85)^O$6 -> 29291.485 | ... AL85: =$D85*AL65*(1+$E85)^AL$6 -> 46189.72
C86: =C66 -> Director of Partnership&ITC | D86: ='3. Assumptions'!D102 -> 25000 | E86: =IF('1. Project Summary'!$F$13="Real",0,'3. Assumptions'!E102) -> 0.02 | G86: EUR | H86: =$D86*H66*(1+$E86)^H$6 -> 25500 | I86: =$D86*I66*(1+$E86)^I$6 -> 26010 | J86: =$D86*J66*(1+$E86)^J$6 -> 26530.2 | K86: =$D86*K66*(1+$E86)^K$6 -> 27060.804 | L86: =$D86*L66*(1+$E86)^L$6 -> 27602.02 | M86: =$D86*M66*(1+$E86)^M$6 -> 28154.06 | N86: =$D86*N66*(1+$E86)^N$6 -> 28717.142 | O86: =$D86*O66*(1+$E86)^O$6 -> 29291.485 | ... AL86: =$D86*AL66*(1+$E86)^AL$6 -> 46189.72
C87: =C67 -> Managers | D87: ='3. Assumptions'!D103 -> 10000 | E87: =IF('1. Project Summary'!$F$13="Real",0,'3. Assumptions'!E103) -> 0.02 | G87: EUR | H87: =$D87*H67*(1+$E87)^H$6 -> 102000 | I87: =$D87*I67*(1+$E87)^I$6 -> 41616 | J87: =$D87*J67*(1+$E87)^J$6 -> 42448.32 | K87: =$D87*K67*(1+$E87)^K$6 -> 43297.286 | L87: =$D87*L67*(1+$E87)^L$6 -> 66244.848 | M87: =$D87*M67*(1+$E87)^M$6 -> 67569.745 | N87: =$D87*N67*(1+$E87)^N$6 -> 91894.853 | O87: =$D87*O67*(1+$E87)^O$6 -> 93732.75 | ... AL87: =$D87*AL67*(1+$E87)^AL$6 -> 147807.11
C88: =C68 -> Technical Staff | D88: ='3. Assumptions'!D104 -> 8000 | E88: =IF('1. Project Summary'!$F$13="Real",0,'3. Assumptions'!E104) -> 0.02 | G88: EUR | H88: =$D88*H68*(1+$E88)^H$6 -> 32640 | I88: =$D88*I68*(1+$E88)^I$6 -> 33292.8 | J88: =$D88*J68*(1+$E88)^J$6 -> 33958.656 | K88: =$D88*K68*(1+$E88)^K$6 -> 34637.829 | L88: =$D88*L68*(1+$E88)^L$6 -> 52995.879 | M88: =$D88*M68*(1+$E88)^M$6 -> 54055.796 | N88: =$D88*N68*(1+$E88)^N$6 -> 73515.883 | O88: =$D88*O68*(1+$E88)^O$6 -> 74986.2 | ... AL88: =$D88*AL68*(1+$E88)^AL$6 -> 118245.68
C89: =C69 -> Forest Engineer | D89: ='3. Assumptions'!D105 -> 8000 | E89: =IF('1. Project Summary'!$F$13="Real",0,'3. Assumptions'!E105) -> 0.02 | G89: EUR | H89: =$D89*H69*(1+$E89)^H$6 -> 16320 | I89: =$D89*I69*(1+$E89)^I$6 -> 16646.4 | J89: =$D89*J69*(1+$E89)^J$6 -> 16979.328 | K89: =$D89*K69*(1+$E89)^K$6 -> 17318.915 | L89: =$D89*L69*(1+$E89)^L$6 -> 26497.939 | M89: =$D89*M69*(1+$E89)^M$6 -> 27027.898 | N89: =$D89*N69*(1+$E89)^N$6 -> 36757.941 | O89: =$D89*O69*(1+$E89)^O$6 -> 37493.1 | ... AL89: =$D89*AL69*(1+$E89)^AL$6 -> 59122.842
C90: =C70 -> Employees | D90: ='3. Assumptions'!D106 -> 3000 | E90: =IF('1. Project Summary'!$F$13="Real",0,'3. Assumptions'!E106) -> 0.02 | G90: EUR | H90: =$D90*H70*(1+$E90)^H$6 -> 24480 | I90: =$D90*I70*(1+$E90)^I$6 -> 24969.6 | J90: =$D90*J70*(1+$E90)^J$6 -> 25468.992 | K90: =$D90*K70*(1+$E90)^K$6 -> 25978.372 | L90: =$D90*L70*(1+$E90)^L$6 -> 39746.909 | M90: =$D90*M70*(1+$E90)^M$6 -> 40541.847 | N90: =$D90*N70*(1+$E90)^N$6 -> 55136.912 | O90: =$D90*O70*(1+$E90)^O$6 -> 56239.65 | ... AL90: =$D90*AL70*(1+$E90)^AL$6 -> 88684.263
C91: =C71 -> Executive Secretary | D91: ='3. Assumptions'!D107 -> 4000 | E91: =IF('1. Project Summary'!$F$13="Real",0,'3. Assumptions'!E107) -> 0.02 | G91: EUR | H91: =$D91*H71*(1+$E91)^H$6 -> 4080 | I91: =$D91*I71*(1+$E91)^I$6 -> 4161.6 | J91: =$D91*J71*(1+$E91)^J$6 -> 4244.832 | K91: =$D91*K71*(1+$E91)^K$6 -> 4329.7286 | L91: =$D91*L71*(1+$E91)^L$6 -> 4416.3232 | M91: =$D91*M71*(1+$E91)^M$6 -> 4504.6497 | N91: =$D91*N71*(1+$E91)^N$6 -> 4594.7427 | O91: =$D91*O71*(1+$E91)^O$6 -> 4686.6375 | ... AL91: =$D91*AL71*(1+$E91)^AL$6 -> 7390.3553
C92: =C72 -> Secretaries | D92: ='3. Assumptions'!D108 -> 3000 | E92: =IF('1. Project Summary'!$F$13="Real",0,'3. Assumptions'!E108) -> 0.02 | G92: EUR | H92: =$D92*H72*(1+$E92)^H$6 -> 21420 | I92: =$D92*I72*(1+$E92)^I$6 -> 9363.6 | J92: =$D92*J72*(1+$E92)^J$6 -> 9550.872 | K92: =$D92*K72*(1+$E92)^K$6 -> 9741.8894 | L92: =$D92*L72*(1+$E92)^L$6 -> 13248.97 | M92: =$D92*M72*(1+$E92)^M$6 -> 13513.949 | N92: =$D92*N72*(1+$E92)^N$6 -> 17230.285 | O92: =$D92*O72*(1+$E92)^O$6 -> 17574.891 | ... AL92: =$D92*AL72*(1+$E92)^AL$6 -> 27713.832
C93: =C73 -> Trainees/Students | D93: ='3. Assumptions'!D109 -> 1200 | E93: =IF('1. Project Summary'!$F$13="Real",0,'3. Assumptions'!E109) -> 0.02 | G93: EUR | H93: =$D93*H73*(1+$E93)^H$6 -> 12240 | I93: =$D93*I73*(1+$E93)^I$6 -> 12484.8 | J93: =$D93*J73*(1+$E93)^J$6 -> 12734.496 | K93: =$D93*K73*(1+$E93)^K$6 -> 12989.186 | L93: =$D93*L73*(1+$E93)^L$6 -> 19873.454 | M93: =$D93*M73*(1+$E93)^M$6 -> 20270.924 | N93: =$D93*N73*(1+$E93)^N$6 -> 27568.456 | O93: =$D93*O73*(1+$E93)^O$6 -> 28119.825 | ... AL93: =$D93*AL73*(1+$E93)^AL$6 -> 44342.132
... C98: =C78 -> Security | D98: ='3. Assumptions'!D114 -> 1500 | E98: =IF('1. Project Summary'!$F$13="Real",0,'3. Assumptions'!E114) -> 0.02 | G98: EUR | H98: =$D98*H78*(1+$E98)^H$6 -> 12240 | I98: =$D98*I78*(1+$E98)^I$6 -> 7803 | J98: =$D98*J78*(1+$E98)^J$6 -> 7959.06 | K98: =$D98*K78*(1+$E98)^K$6 -> 8118.2412 | L98: =$D98*L78*(1+$E98)^L$6 -> 11592.848 | M98: =$D98*M78*(1+$E98)^M$6 -> 11824.705 | N98: =$D98*N78*(1+$E98)^N$6 -> 12061.2 | O98: =$D98*O78*(1+$E98)^O$6 -> 12302.424 | ... AL98: =$D98*AL78*(1+$E98)^AL$6 -> 19399.683
B99: ="Total "&B60 -> Total Salary | E99: =AVERAGE(E82:E98) -> 0.02 | G99: EUR | H99: =SUM(H82:H98) -> 360060 | I99: =SUM(I82:I98) -> 333448.2 | J99: =SUM(J82:J98) -> 340117.16 | K99: =SUM(K82:K98) -> 346919.51 | L99: =SUM(L82:L98) -> 443288.44 | M99: =SUM(M82:M98) -> 452154.21 | N99: =SUM(N82:N98) -> 550794.78 | O99: =SUM(O82:O98) -> 561810.67 | ... AL99: =SUM(AL82:AL98) -> 885918.84
B101: ='3. Assumptions'!B117 -> Production and Harvesting Service Fees for Moringa | E101: ='3. Assumptions'!E117 -> Unit cost (EUR)
C102: Production Services | E102: ='3. Assumptions'!E118 -> 0.5 | G102: EUR | H102: ='4.2 Revenue Build - Other'!H62*$E102*H8 -> 0 | I102: ='4.2 Revenue Build - Other'!I62*$E102*I8 -> 151222.14 | J102: ='4.2 Revenue Build - Other'!J62*$E102*J8 -> 154246.58 | K102: ='4.2 Revenue Build - Other'!K62*$E102*K8 -> 262219.19 | L102: ='4.2 Revenue Build - Other'!L62*$E102*L8 -> 267463.57 | M102: ='4.2 Revenue Build - Other'!M62*$E102*M8 -> 272812.85 | N102: ='4.2 Revenue Build - Other'!N62*$E102*N8 -> 278269.1 | O102: ='4.2 Revenue Build - Other'!O62*$E102*O8 -> 283834.49 | ... AL102: ='4.2 Revenue Build - Other'!AL62*$E102*AL8 -> 447578.39
C103: Harvesting Services | E103: ='3. Assumptions'!E119 -> 0.5 | G103: EUR | H103: =H102 -> 0 | I103: =I102 -> 151222.14 | J103: =J102 -> 154246.58 | K103: =K102 -> 262219.19 | L103: =L102 -> 267463.57 | M103: =M102 -> 272812.85 | N103: =N102 -> 278269.1 | O103: =O102 -> 283834.49 | ... AL103: =AL102 -> 447578.39
B104: ="Total "&B101 -> Total Production and Harvesting Service Fees for Moringa | G104: EUR | H104: =SUM(H102:H103) -> 0 | I104: =SUM(I102:I103) -> 302444.28 | J104: =SUM(J102:J103) -> 308493.17 | K104: =SUM(K102:K103) -> 524438.38 | L104: =SUM(L102:L103) -> 534927.15 | M104: =SUM(M102:M103) -> 545625.69 | N104: =SUM(N102:N103) -> 556538.21 | O104: =SUM(O102:O103) -> 567668.97 | ... AL104: =SUM(AL102:AL103) -> 895156.78
B106: ='3. Assumptions'!B121 -> Rental
C107: Office space | D107: Office rental rate (annual) | E107: CAGR | G107: sq.ft | H107: ='3. Assumptions'!G122 -> 1000 | I107: ='3. Assumptions'!H122 -> 1000 | J107: ='3. Assumptions'!I122 -> 1500 | K107: ='3. Assumptions'!J122 -> 1500 | L107: ='3. Assumptions'!K122 -> 1500 | M107: ='3. Assumptions'!L122 -> 2000 | N107: =M107 -> 2000 | O107: =N107 -> 2000 | P107: =O107 -> 2000 | Q107: =P107 -> 2000 | R107: =Q107 -> 2000 | S107: =R107 -> 2000 | T107: =S107 -> 2000 | U107: =T107 -> 2000 | ... AL107: =AK107 -> 2000
C108: Annual office rent | D108: 10 | E108: =IF('1. Project Summary'!$F$13="Real",0,'3. Assumptions'!E124) -> 0.05 | G108: EUR | H108: =$D108*H107*(1+$E108)^H$6 -> 10500 | I108: =$D108*I107*(1+$E108)^I$6 -> 11025 | J108: =$D108*J107*(1+$E108)^J$6 -> 17364.375 | K108: =$D108*K107*(1+$E108)^K$6 -> 18232.594 | L108: =$D108*L107*(1+$E108)^L$6 -> 19144.223 | M108: =$D108*M107*(1+$E108)^M$6 -> 26801.913 | N108: =$D108*N107*(1+$E108)^N$6 -> 28142.008 | O108: =$D108*O107*(1+$E108)^O$6 -> 29549.109 | ... AL108: =$D108*AL107*(1+$E108)^AL$6 -> 90760.79
B109: ="Total "&B106 -> Total Rental | G109: EUR | H109: =H108 -> 10500 | I109: =I108 -> 11025 | J109: =J108 -> 17364.375 | K109: =K108 -> 18232.594 | L109: =L108 -> 19144.223 | M109: =M108 -> 26801.913 | N109: =N108 -> 28142.008 | O109: =O108 -> 29549.109 | ... AL109: =AL108 -> 90760.79
B111: ='3. Assumptions'!B126 -> Utilities
C112: Utilities | E112: ='3. Assumptions'!E126 -> 5000 | G112: EUR | H112: =E112*H8 -> 5100 | I112: =(H112+'3. Assumptions'!$E$127)*(1+$E$8) -> 7242 | J112: =(I112+'3. Assumptions'!$E$127)*(1+$E$8) -> 9426.84 | K112: =(J112+'3. Assumptions'!$E$127)*(1+$E$8) -> 11655.377 | L112: =(K112+'3. Assumptions'!$E$127)*(1+$E$8) -> 13928.484 | M112: =(L112+'3. Assumptions'!$E$127)*(1+$E$8) -> 16247.054 | N112: =(M112+'3. Assumptions'!$E$127)*(1+$E$8) -> 18611.995 | O112: =(N112+'3. Assumptions'!$E$127)*(1+$E$8) -> 21024.235 | P112: =(O112+'3. Assumptions'!$E$127)*(1+$E$8) -> 23484.72 | ... R112: =(Q112+'3. Assumptions'!$E$127)*(1+$E$8) -> 28554.302 | S112: =(R112)*(1+$E$8) -> 29125.388 | T112: =(S112)*(1+$E$8) -> 29707.896 | U112: =(T112)*(1+$E$8) -> 30302.054 | V112: =(U112)*(1+$E$8) -> 30908.095 | W112: =(V112)*(1+$E$8) -> 31526.257 | X112: =(W112)*(1+$E$8) -> 32156.782 | Y112: =(X112)*(1+$E$8) -> 32799.918 | Z112: =(Y112)*(1+$E$8) -> 33455.916 | ... AL112: =(AK112)*(1+$E$8) -> 42430.191
B113: ="Total "&B111 -> Total Utilities | G113: EUR | H113: =SUM(H112:H112) -> 5100 | I113: =SUM(I112:I112) -> 7242 | J113: =SUM(J112:J112) -> 9426.84 | K113: =SUM(K112:K112) -> 11655.377 | L113: =SUM(L112:L112) -> 13928.484 | M113: =SUM(M112:M112) -> 16247.054 | N113: =SUM(N112:N112) -> 18611.995 | O113: =SUM(O112:O112) -> 21024.235 | ... AL113: =SUM(AL112:AL112) -> 42430.191
B115: Insurance
C116: Insurance | G116: EUR | H116: ='3. Assumptions'!G129*H8 -> 20400 | I116: ='3. Assumptions'!H129*I8 -> 20808 | J116: ='3. Assumptions'!I129*J8 -> 26530.2 | K116: ='3. Assumptions'!J129*K8 -> 27060.804 | L116: ='3. Assumptions'!$K$129*L8 -> 33122.424 | M116: ='3. Assumptions'!$K$129*M8 -> 33784.873 | N116: ='3. Assumptions'!$K$129*N8 -> 34460.57 | O116: ='3. Assumptions'!$K$129*O8 -> 35149.781 | P116: ='3. Assumptions'!$K$129*P8 -> 35852.777 | Q116: ='3. Assumptions'!$K$129*Q8 -> 36569.833 | R116: ='3. Assumptions'!$K$129*R8 -> 37301.229 | S116: ='3. Assumptions'!$K$129*S8 -> 38047.254 | ... AL116: ='3. Assumptions'!$K$129*AL8 -> 55427.664
B117: ="Total "&B115 -> Total Insurance | G117: EUR | H117: =SUM(H116:H116) -> 20400 | I117: =SUM(I116:I116) -> 20808 | J117: =SUM(J116:J116) -> 26530.2 | K117: =SUM(K116:K116) -> 27060.804 | L117: =SUM(L116:L116) -> 33122.424 | M117: =SUM(M116:M116) -> 33784.873 | N117: =SUM(N116:N116) -> 34460.57 | O117: =SUM(O116:O116) -> 35149.781 | ... AL117: =SUM(AL116:AL116) -> 55427.664
B119: Office Equipment | D119: Cost per staff | E119: CAGR
C120: Computers | D120: ='3. Assumptions'!E133 -> 1500 | E120: =IF('1. Project Summary'!$F$13="Real",0,'3. Assumptions'!$E$138) -> 0.05 | H120: ='3. Assumptions'!G133*(1+$E120)^H$6 -> 55125 | I120: ='3. Assumptions'!H133*(1+$E120)^I$6 -> -13230 | J120: ='3. Assumptions'!I133*(1+$E120)^J$6 -> 0 | K120: ='3. Assumptions'!J133*(1+$E120)^K$6 -> 0 | L120: ='3. Assumptions'!K133*(1+$E120)^L$6 -> 19144.223 | M120: ='3. Assumptions'!L133*(1+$E120)^M$6 -> 0 | N120: ='3. Assumptions'!M133*(1+$E120)^N$6 -> 21106.506 | O120: =N120*(1+$E120) -> 22161.832 | P120: =O120*(1+$E120) -> 23269.923 | Q120: =P120*(1+$E120) -> 24433.419 | R120: =Q120*(1+$E120) -> 25655.09 | S120: =R120*(1+$E120) -> 26937.845 | T120: =S120*(1+$E120) -> 28284.737 | U120: =T120*(1+$E120) -> 29698.974 | V120: =U120*(1+$E120) -> 31183.923 | ... AL120: =AK120*(1+$E120) -> 68070.592
C121: Office set | D121: ='3. Assumptions'!E134 -> 1000 | E121: =IF('1. Project Summary'!$F$13="Real",0,'3. Assumptions'!$E$138) -> 0.05 | H121: ='3. Assumptions'!G134*(1+$E121)^H$6 -> 36750 | I121: ='3. Assumptions'!H134*(1+$E121)^I$6 -> -8820 | J121: ='3. Assumptions'!I134*(1+$E121)^J$6 -> 0 | K121: ='3. Assumptions'!J134*(1+$E121)^K$6 -> 0 | L121: ='3. Assumptions'!K134*(1+$E121)^L$6 -> 12762.816 | M121: ='3. Assumptions'!L134*(1+$E121)^M$6 -> 0 | N121: ='3. Assumptions'!M134*(1+$E121)^N$6 -> 14071.004 | O121: =N121*(1+$E121) -> 14774.554 | P121: =O121*(1+$E121) -> 15513.282 | Q121: =P121*(1+$E121) -> 16288.946 | R121: =Q121*(1+$E121) -> 17103.394 | S121: =R121*(1+$E121) -> 17958.563 | T121: =S121*(1+$E121) -> 18856.491 | U121: =T121*(1+$E121) -> 19799.316 | V121: =U121*(1+$E121) -> 20789.282 | ... AL121: =AK121*(1+$E121) -> 45380.395
C122: Other furniture and IT equipment | D122: ='3. Assumptions'!E135 -> 1200 | E122: =IF('1. Project Summary'!$F$13="Real",0,'3. Assumptions'!$E$138) -> 0.05 | H122: ='3. Assumptions'!G135*(1+$E122)^H$6 -> 44100 | I122: ='3. Assumptions'!H135*(1+$E122)^I$6 -> -10584 | J122: ='3. Assumptions'!I135*(1+$E122)^J$6 -> 0 | K122: ='3. Assumptions'!J135*(1+$E122)^K$6 -> 0 | L122: ='3. Assumptions'!K135*(1+$E122)^L$6 -> 15315.379 | M122: ='3. Assumptions'!L135*(1+$E122)^M$6 -> 0 | N122: ='3. Assumptions'!M135*(1+$E122)^N$6 -> 16885.205 | O122: =N122*(1+$E122) -> 17729.465 | P122: =O122*(1+$E122) -> 18615.939 | Q122: =P122*(1+$E122) -> 19546.736 | R122: =Q122*(1+$E122) -> 20524.072 | S122: =R122*(1+$E122) -> 21550.276 | T122: =S122*(1+$E122) -> 22627.79 | U122: =T122*(1+$E122) -> 23759.179 | V122: =U122*(1+$E122) -> 24947.138 | ... AL122: =AK122*(1+$E122) -> 54456.474
C123: Software and Digital services | E123: =IF('1. Project Summary'!$F$13="Real",0,'3. Assumptions'!$E$138) -> 0.05 | H123: ='3. Assumptions'!G136 -> 125000 | I123: ='3. Assumptions'!$H$136*(1+$E$123)^I6 -> 11025 | J123: ='3. Assumptions'!$H$136*(1+$E$123)^J6 -> 11576.25 | K123: ='3. Assumptions'!$H$136*(1+$E$123)^K6 -> 12155.062 | L123: ='3. Assumptions'!$H$136*(1+$E$123)^L6 -> 12762.816 | M123: ='3. Assumptions'!$H$136*(1+$E$123)^M6 -> 13400.956 | N123: ='3. Assumptions'!$H$136*(1+$E$123)^N6 -> 14071.004 | O123: ='3. Assumptions'!$H$136*(1+$E$123)^O6 -> 14774.554 | P123: ='3. Assumptions'!$H$136*(1+$E$123)^P6 -> 15513.282 | ... AL123: ='3. Assumptions'!$H$136*(1+$E$123)^AL6 -> 45380.395
C124: Other | D124: ='3. Assumptions'!E137 -> 0.2 | E124: =IF('1. Project Summary'!$F$13="Real",0,'3. Assumptions'!$E$138) -> 0.05 | H124: =SUM(H120:H122)*$D$124 -> 27195 | I124: =SUM(I120:I122)*$D$124 -> -6526.8 | J124: =SUM(J120:J122)*$D$124 -> 0 | K124: =SUM(K120:K122)*$D$124 -> 0 | L124: =SUM(L120:L122)*$D$124 -> 9444.4836 | M124: =SUM(M120:M122)*$D$124 -> 0 | N124: =SUM(N120:N122)*$D$124 -> 10412.543 | O124: =SUM(O120:O122)*$D$124 -> 10933.17 | ... AL124: =SUM(AL120:AL122)*$D$124 -> 33581.492
B125: ="Total "&B119 -> Total Office Equipment | H125: =SUM(H120:H124) -> 288170 | I125: =SUM(I120:I124) -> -28135.8 | J125: =SUM(J120:J124) -> 11576.25 | K125: =SUM(K120:K124) -> 12155.062 | L125: =SUM(L120:L124) -> 69429.717 | M125: =SUM(M120:M124) -> 13400.956 | N125: =SUM(N120:N124) -> 76546.263 | O125: =SUM(O120:O124) -> 80373.576 | ... AL125: =SUM(AL120:AL124) -> 246869.35
B127: Vehicles | E127: Annual cost
C128: ='3. Assumptions'!C141 -> Utility vehicle management | E128: ='3. Assumptions'!E141 -> 50000 | H128: =$E128*H$8 -> 51000 | I128: =$E128*I$8 -> 52020 | J128: =$E128*J$8 -> 53060.4 | K128: =$E128*K$8 -> 54121.608 | L128: =$E128*L$8 -> 55204.04 | M128: =$E128*M$8 -> 56308.121 | N128: =$E128*N$8 -> 57434.283 | O128: =$E128*O$8 -> 58582.969 | ... AL128: =$E128*AL$8 -> 92379.441
C129: ='3. Assumptions'!C142 -> Utility vehicle management | E129: ='3. Assumptions'!E142 -> 25000 | H129: =$E129*H$8 -> 25500 | I129: =$E129*I$8 -> 26010 | J129: =$E129*J$8 -> 26530.2 | K129: =$E129*K$8 -> 27060.804 | L129: =$E129*L$8 -> 27602.02 | M129: =$E129*M$8 -> 28154.06 | N129: =$E129*N$8 -> 28717.142 | O129: =$E129*O$8 -> 29291.485 | ... AL129: =$E129*AL$8 -> 46189.72
B130: ="Total "&B127 -> Total Vehicles | H130: =SUM(H128:H129) -> 76500 | I130: =SUM(I128:I129) -> 78030 | J130: =SUM(J128:J129) -> 79590.6 | K130: =SUM(K128:K129) -> 81182.412 | L130: =SUM(L128:L129) -> 82806.06 | M130: =SUM(M128:M129) -> 84462.181 | N130: =SUM(N128:N129) -> 86151.425 | O130: =SUM(O128:O129) -> 87874.454 | ... AL130: =SUM(AL128:AL129) -> 138569.16
B132: ARR Cost Summary
...

Sheet 5.3 Cost Build - Productive
B2: ='1. Project Summary'!B2 -> Projections - Serious Shea
B3: ='1. Project Summary'!B3 -> (in EUR, unless otherwise stated)
B5: Cost Build | G5: Unit | H5: ='2. NPV'!H47 -> 2024 | I5: ='2. NPV'!I47 -> 2025 | J5: ='2. NPV'!J47 -> 2026 | K5: ='2. NPV'!K47 -> 2027 | L5: ='2. NPV'!L47 -> 2028 | M5: ='2. NPV'!M47 -> 2029 | N5: ='2. NPV'!N47 -> 2030 | O5: ='2. NPV'!O47 -> 2031 | ... AL5: ='2. NPV'!AL47 -> 2054
B6: Productive Activities | H6: =Period_Start -> 1 | I6: =H6+1 -> 2 | J6: =I6+1 -> 3 | K6: =J6+1 -> 4 | L6: =K6+1 -> 5 | M6: =L6+1 -> 6 | N6: =M6+1 -> 7 | O6: =N6+1 -> 8 | P6: =O6+1 -> 9 | ... AL6: =AK6+1 -> 31
B8: Cost Inflation | E8: ='1. Project Summary'!F15 -> 0.02 | G8: Index | H8: =(1+$E8)^H$6 -> 1.02 | I8: =(1+$E8)^I$6 -> 1.0404 | J8: =(1+$E8)^J$6 -> 1.061208 | K8: =(1+$E8)^K$6 -> 1.0824322 | L8: =(1+$E8)^L$6 -> 1.1040808 | M8: =(1+$E8)^M$6 -> 1.1261624 | N8: =(1+$E8)^N$6 -> 1.1486857 | O8: =(1+$E8)^O$6 -> 1.1716594 | ... AL8: =(1+$E8)^AL$6 -> 1.8475888
B10: Processing Centers - CAPEX
B12: # of Processing Centers to be Built
C13: Multi- Function Centers | H13: ='3. Assumptions'!F149 -> 0 | I13: ='3. Assumptions'!G149 -> 2 | J13: ='3. Assumptions'!H149 -> 2 | K13: ='3. Assumptions'!I149 -> 2 | L13: ='3. Assumptions'!J149 -> 2 | M13: ='3. Assumptions'!K149 -> 2 | N13: ='3. Assumptions'!L149 -> 2 | O13: ='3. Assumptions'!M149 -> 2 | ... AL13: ='3. Assumptions'!AJ149 -> 0
C14: Shea Collection Centers | H14: ='3. Assumptions'!F150 -> 0 | I14: ='3. Assumptions'!G150 -> 0 | J14: ='3. Assumptions'!H150 -> 0 | K14: ='3. Assumptions'!I150 -> 0 | L14: ='3. Assumptions'!J150 -> 0 | M14: ='3. Assumptions'!K150 -> 0 | N14: ='3. Assumptions'!L150 -> 0 | O14: ='3. Assumptions'!M150 -> 0 | ... AL14: ='3. Assumptions'!AJ150 -> 0
C15: Shea Processing Centers | H15: ='3. Assumptions'!F151 -> 0 | I15: ='3. Assumptions'!G151 -> 0 | J15: ='3. Assumptions'!H151 -> 0 | K15: ='3. Assumptions'!I151 -> 0 | L15: ='3. Assumptions'!J151 -> 0 | M15: ='3. Assumptions'!K151 -> 0 | N15: ='3. Assumptions'!L151 -> 0 | O15: ='3. Assumptions'!M151 -> 0 | ... AL15: ='3. Assumptions'!AJ151 -> 0
B16: ="Total "&B12 -> Total # of Processing Centers to be Built | H16: =SUM(H13:H15) -> 0 | I16: =SUM(I13:I15) -> 2 | J16: =SUM(J13:J15) -> 2 | K16: =SUM(K13:K15) -> 2 | L16: =SUM(L13:L15) -> 2 | M16: =SUM(M13:M15) -> 2 | N16: =SUM(N13:N15) -> 2 | O16: =SUM(O13:O15) -> 2 | ... AL16: =SUM(AL13:AL15) -> 0
B18: Processing Center - CAPEX | D18: CAPEX per center | E18: CAGR
C19: Multi- Function Centers | D19: =SUM(D20:D23) -> 333784 | G19: EUR | H19: =SUM(H20:H23) -> 0 | I19: =SUM(I20:I23) -> 735993.72 | J19: =SUM(J20:J23) -> 772793.41 | K19: =SUM(K20:K23) -> 811433.08 | L19: =SUM(L20:L23) -> 852004.73 | M19: =SUM(M20:M23) -> 894604.97 | N19: =SUM(N20:N23) -> 939335.21 | O19: =SUM(O20:O23) -> 986301.98 | ... AL19: =SUM(AL20:AL23) -> 0
C20: Land | D20: ='3. Assumptions'!G177 -> 10000 | E20: =IF('1. Project Summary'!$F$13="Real",0,'3. Assumptions'!$E$172) -> 0.05 | G20: EUR | H20: =$D20*H$13*(1+$E20)^H$6 -> 0 | I20: =$D20*I$13*(1+$E20)^I$6 -> 22050 | J20: =$D20*J$13*(1+$E20)^J$6 -> 23152.5 | K20: =$D20*K$13*(1+$E20)^K$6 -> 24310.125 | L20: =$D20*L$13*(1+$E20)^L$6 -> 25525.631 | M20: =$D20*M$13*(1+$E20)^M$6 -> 26801.913 | N20: =$D20*N$13*(1+$E20)^N$6 -> 28142.008 | O20: =$D20*O$13*(1+$E20)^O$6 -> 29549.109 | ... AL20: =$D20*AL$13*(1+$E20)^AL$6 -> 0
C21: Building | D21: =SUM('3. Assumptions'!G178:G183) -> 175000 | E21: =IF('1. Project Summary'!$F$13="Real",0,'3. Assumptions'!$E$172) -> 0.05 | G21: EUR | H21: =$D21*H$13*(1+$E21)^H$6 -> 0 | I21: =$D21*I$13*(1+$E21)^I$6 -> 385875 | J21: =$D21*J$13*(1+$E21)^J$6 -> 405168.75 | K21: =$D21*K$13*(1+$E21)^K$6 -> 425427.19 | L21: =$D21*L$13*(1+$E21)^L$6 -> 446698.55 | M21: =$D21*M$13*(1+$E21)^M$6 -> 469033.47 | N21: =$D21*N$13*(1+$E21)^N$6 -> 492485.15 | O21: =$D21*O$13*(1+$E21)^O$6 -> 517109.41 | ... AL21: =$D21*AL$13*(1+$E21)^AL$6 -> 0
C22: Equipment | D22: =SUM('3. Assumptions'!G184) -> 103784 | E22: =IF('1. Project Summary'!$F$13="Real",0,'3. Assumptions'!$E$172) -> 0.05 | G22: EUR | H22: =$D22*H$13*(1+$E22)^H$6 -> 0 | I22: =$D22*I$13*(1+$E22)^I$6 -> 228843.72 | J22: =$D22*J$13*(1+$E22)^J$6 -> 240285.91 | K22: =$D22*K$13*(1+$E22)^K$6 -> 252300.2 | L22: =$D22*L$13*(1+$E22)^L$6 -> 264915.21 | M22: =$D22*M$13*(1+$E22)^M$6 -> 278160.97 | N22: =$D22*N$13*(1+$E22)^N$6 -> 292069.02 | O22: =$D22*O$13*(1+$E22)^O$6 -> 306672.47 | ... AL22: =$D22*AL$13*(1+$E22)^AL$6 -> 0
C23: Vehicles | D23: ='3. Assumptions'!G198 -> 45000 | E23: =IF('1. Project Summary'!$F$13="Real",0,'3. Assumptions'!$E$172) -> 0.05 | G23: EUR | H23: =$D23*H$13*(1+$E23)^H$6 -> 0 | I23: =$D23*I$13*(1+$E23)^I$6 -> 99225 | J23: =$D23*J$13*(1+$E23)^J$6 -> 104186.25 | K23: =$D23*K$13*(1+$E23)^K$6 -> 109395.56 | L23: =$D23*L$13*(1+$E23)^L$6 -> 114865.34 | M23: =$D23*M$13*(1+$E23)^M$6 -> 120608.61 | N23: =$D23*N$13*(1+$E23)^N$6 -> 126639.04 | O23: =$D23*O$13*(1+$E23)^O$6 -> 132970.99 | ... AL23: =$D23*AL$13*(1+$E23)^AL$6 -> 0
C24: Shea Collection Centers | D24: =SUM(D25:D28) -> 417531 | G24: EUR | H24: =SUM(H25:H28) -> 0 | I24: =SUM(I25:I28) -> 0 | J24: =SUM(J25:J28) -> 0 | K24: =SUM(K25:K28) -> 0 | L24: =SUM(L25:L28) -> 0 | M24: =SUM(M25:M28) -> 0 | N24: =SUM(N25:N28) -> 0 | O24: =SUM(O25:O28) -> 0 | ... AL24: =SUM(AL25:AL28) -> 0
C25: Land | D25: =SUM('3. Assumptions'!G227) -> 10000 | E25: =IF('1. Project Summary'!$F$13="Real",0,'3. Assumptions'!$E$172) -> 0.05 | G25: EUR | H25: =$D25*H$14*(1+$E25)^H$6 -> 0 | I25: =$D25*I$14*(1+$E25)^I$6 -> 0 | J25: =$D25*J$14*(1+$E25)^J$6 -> 0 | K25: =$D25*K$14*(1+$E25)^K$6 -> 0 | L25: =$D25*L$14*(1+$E25)^L$6 -> 0 | M25: =$D25*M$14*(1+$E25)^M$6 -> 0 | N25: =$D25*N$14*(1+$E25)^N$6 -> 0 | O25: =$D25*O$14*(1+$E25)^O$6 -> 0 | ... AL25: =$D25*AL$14*(1+$E25)^AL$6 -> 0
C26: Building | D26: =SUM('3. Assumptions'!G228:G233) -> 175000 | E26: =IF('1. Project Summary'!$F$13="Real",0,'3. Assumptions'!$E$172) -> 0.05 | G26: EUR | H26: =$D26*H$14*(1+$E26)^H$6 -> 0 | I26: =$D26*I$14*(1+$E26)^I$6 -> 0 | J26: =$D26*J$14*(1+$E26)^J$6 -> 0 | K26: =$D26*K$14*(1+$E26)^K$6 -> 0 | L26: =$D26*L$14*(1+$E26)^L$6 -> 0 | M26: =$D26*M$14*(1+$E26)^M$6 -> 0 | N26: =$D26*N$14*(1+$E26)^N$6 -> 0 | O26: =$D26*O$14*(1+$E26)^O$6 -> 0 | ... AL26: =$D26*AL$14*(1+$E26)^AL$6 -> 0
C27: Equipment | D27: =SUM('3. Assumptions'!G234) -> 187531 | E27: =IF('1. Project Summary'!$F$13="Real",0,'3. Assumptions'!$E$172) -> 0.05 | G27: EUR | H27: =$D27*H$14*(1+$E27)^H$6 -> 0 | I27: =$D27*I$14*(1+$E27)^I$6 -> 0 | J27: =$D27*J$14*(1+$E27)^J$6 -> 0 | K27: =$D27*K$14*(1+$E27)^K$6 -> 0 | L27: =$D27*L$14*(1+$E27)^L$6 -> 0 | M27: =$D27*M$14*(1+$E27)^M$6 -> 0 | N27: =$D27*N$14*(1+$E27)^N$6 -> 0 | O27: =$D27*O$14*(1+$E27)^O$6 -> 0 | ... AL27: =$D27*AL$14*(1+$E27)^AL$6 -> 0
C28: Vehicles | D28: ='3. Assumptions'!G247 -> 45000 | E28: =IF('1. Project Summary'!$F$13="Real",0,'3. Assumptions'!$E$172) -> 0.05 | G28: EUR | H28: =$D28*H$14*(1+$E28)^H$6 -> 0 | I28: =$D28*I$14*(1+$E28)^I$6 -> 0 | J28: =$D28*J$14*(1+$E28)^J$6 -> 0 | K28: =$D28*K$14*(1+$E28)^K$6 -> 0 | L28: =$D28*L$14*(1+$E28)^L$6 -> 0 | M28: =$D28*M$14*(1+$E28)^M$6 -> 0 | N28: =$D28*N$14*(1+$E28)^N$6 -> 0 | O28: =$D28*O$14*(1+$E28)^O$6 -> 0 | ... AL28: =$D28*AL$14*(1+$E28)^AL$6 -> 0
C29: Shea Processing Centers | D29: =SUM(D30:D33) -> 798872 | G29: EUR | H29: =SUM(H30:H33) -> 0 | I29: =SUM(I30:I33) -> 0 | J29: =SUM(J30:J33) -> 0 | K29: =SUM(K30:K33) -> 0 | L29: =SUM(L30:L33) -> 0 | M29: =SUM(M30:M33) -> 0 | N29: =SUM(N30:N33) -> 0 | O29: =SUM(O30:O33) -> 0 | ... AL29: =SUM(AL30:AL33) -> 0
C30: Land | D30: ='3. Assumptions'!G275 -> 20000 | E30: =IF('1. Project Summary'!$F$13="Real",0,'3. Assumptions'!$E$172) -> 0.05 | G30: EUR | H30: =$D30*H$15*(1+$E30)^H$6 -> 0 | I30: =$D30*I$15*(1+$E30)^I$6 -> 0 | J30: =$D30*J$15*(1+$E30)^J$6 -> 0 | K30: =$D30*K$15*(1+$E30)^K$6 -> 0 | L30: =$D30*L$15*(1+$E30)^L$6 -> 0 | M30: =$D30*M$15*(1+$E30)^M$6 -> 0 | N30: =$D30*N$15*(1+$E30)^N$6 -> 0 | O30: =$D30*O$15*(1+$E30)^O$6 -> 0 | ... AL30: =$D30*AL$15*(1+$E30)^AL$6 -> 0
C31: Building | D31: =SUM('3. Assumptions'!G276:G281) -> 390000 | E31: =IF('1. Project Summary'!$F$13="Real",0,'3. Assumptions'!$E$172) -> 0.05 | G31: EUR | H31: =$D31*H$15*(1+$E31)^H$6 -> 0 | I31: =$D31*I$15*(1+$E31)^I$6 -> 0 | J31: =$D31*J$15*(1+$E31)^J$6 -> 0 | K31: =$D31*K$15*(1+$E31)^K$6 -> 0 | L31: =$D31*L$15*(1+$E31)^L$6 -> 0 | M31: =$D31*M$15*(1+$E31)^M$6 -> 0 | N31: =$D31*N$15*(1+$E31)^N$6 -> 0 | O31: =$D31*O$15*(1+$E31)^O$6 -> 0 | ... AL31: =$D31*AL$15*(1+$E31)^AL$6 -> 0
C32: Equipment | D32: ='3. Assumptions'!G282 -> 318872 | E32: =IF('1. Project Summary'!$F$13="Real",0,'3. Assumptions'!$E$172) -> 0.05 | G32: EUR | H32: =$D32*H$15*(1+$E32)^H$6 -> 0 | I32: =$D32*I$15*(1+$E32)^I$6 -> 0 | J32: =$D32*J$15*(1+$E32)^J$6 -> 0 | K32: =$D32*K$15*(1+$E32)^K$6 -> 0 | L32: =$D32*L$15*(1+$E32)^L$6 -> 0 | M32: =$D32*M$15*(1+$E32)^M$6 -> 0 | N32: =$D32*N$15*(1+$E32)^N$6 -> 0 | O32: =$D32*O$15*(1+$E32)^O$6 -> 0 | ... AL32: =$D32*AL$15*(1+$E32)^AL$6 -> 0
C33: Vehicles | D33: ='3. Assumptions'!G296 -> 70000 | E33: =IF('1. Project Summary'!$F$13="Real",0,'3. Assumptions'!$E$172) -> 0.05 | G33: EUR | H33: =$D33*H$15*(1+$E33)^H$6 -> 0 | I33: =$D33*I$15*(1+$E33)^I$6 -> 0 | J33: =$D33*J$15*(1+$E33)^J$6 -> 0 | K33: =$D33*K$15*(1+$E33)^K$6 -> 0 | L33: =$D33*L$15*(1+$E33)^L$6 -> 0 | M33: =$D33*M$15*(1+$E33)^M$6 -> 0 | N33: =$D33*N$15*(1+$E33)^N$6 -> 0 | O33: =$D33*O$15*(1+$E33)^O$6 -> 0 | ... AL33: =$D33*AL$15*(1+$E33)^AL$6 -> 0
B34: ="Total "&B18 -> Total Processing Center - CAPEX | G34: EUR | H34: =H29+H24+H19 -> 0 | I34: =I29+I24+I19 -> 735993.72 | J34: =J29+J24+J19 -> 772793.41 | K34: =K29+K24+K19 -> 811433.08 | L34: =L29+L24+L19 -> 852004.73 | M34: =M29+M24+M19 -> 894604.97 | N34: =N29+N24+N19 -> 939335.21 | O34: =O29+O24+O19 -> 986301.98 | ... AL34: =AL29+AL24+AL19 -> 0
B36: Processing Centers - OPEX
B38: # of Processing Centers to be Built
C39: Multi- Function Centers | G39: # | H39: =SUM($H13:H13) -> 0 | I39: =SUM($H13:I13) -> 2 | J39: =SUM($H13:J13) -> 4 | K39: =SUM($H13:K13) -> 6 | L39: =SUM($H13:L13) -> 8 | M39: =SUM($H13:M13) -> 10 | N39: =SUM($H13:N13) -> 12 | O39: =SUM($H13:O13) -> 14 | ... AL39: =SUM($H13:AL13) -> 18
C40: Shea Collection Centers | G40: # | H40: =SUM($H14:H14) -> 0 | I40: =SUM($H14:I14) -> 0 | J40: =SUM($H14:J14) -> 0 | K40: =SUM($H14:K14) -> 0 | L40: =SUM($H14:L14) -> 0 | M40: =SUM($H14:M14) -> 0 | N40: =SUM($H14:N14) -> 0 | O40: =SUM($H14:O14) -> 0 | ... AL40: =SUM($H14:AL14) -> 0
C41: Shea Processing Centers | G41: # | H41: =SUM($H15:H15) -> 0 | I41: =SUM($H15:I15) -> 0 | J41: =SUM($H15:J15) -> 0 | K41: =SUM($H15:K15) -> 0 | L41: =SUM($H15:L15) -> 0 | M41: =SUM($H15:M15) -> 0 | N41: =SUM($H15:N15) -> 0 | O41: =SUM($H15:O15) -> 0 | ... AL41: =SUM($H15:AL15) -> 0
B42: ="Total "&B38 -> Total # of Processing Centers to be Built | G42: # | H42: =SUM(H39:H41) -> 0 | I42: =SUM(I39:I41) -> 2 | J42: =SUM(J39:J41) -> 4 | K42: =SUM(K39:K41) -> 6 | L42: =SUM(L39:L41) -> 8 | M42: =SUM(M39:M41) -> 10 | N42: =SUM(N39:N41) -> 12 | O42: =SUM(O39:O41) -> 14 | ... AL42: =SUM(AL39:AL41) -> 18
B44: Spare Parts | E44: CAGR
C45: Multi- Function Centers | D45: ='3. Assumptions'!G210 -> 12551 | E45: =IF('1. Project Summary'!$F$13="Real",0,'3. Assumptions'!$E$172) -> 0.05 | G45: EUR | H45: =$D45*H39*(1+$E45)^H$6 -> 0 | I45: =$D45*I39*(1+$E45)^I$6 -> 27674.955 | J45: =$D45*J39*(1+$E45)^J$6 -> 58117.406 | K45: =$D45*K39*(1+$E45)^K$6 -> 91534.914 | L45: =$D45*L39*(1+$E45)^L$6 -> 128148.88 | M45: =$D45*M39*(1+$E45)^M$6 -> 168195.4 | N45: =$D45*N39*(1+$E45)^N$6 -> 211926.21 | O45: =$D45*O39*(1+$E45)^O$6 -> 259609.61 | ... AL45: =$D45*AL39*(1+$E45)^AL$6 -> 1025224.8
C46: Shea Collection Centers | D46: ='3. Assumptions'!G260 -> 20436 | E46: =IF('1. Project Summary'!$F$13="Real",0,'3. Assumptions'!$E$172) -> 0.05 | G46: EUR | H46: =$D46*H40*(1+$E46)^H$6 -> 0 | I46: =$D46*I40*(1+$E46)^I$6 -> 0 | J46: =$D46*J40*(1+$E46)^J$6 -> 0 | K46: =$D46*K40*(1+$E46)^K$6 -> 0 | L46: =$D46*L40*(1+$E46)^L$6 -> 0 | M46: =$D46*M40*(1+$E46)^M$6 -> 0 | N46: =$D46*N40*(1+$E46)^N$6 -> 0 | O46: =$D46*O40*(1+$E46)^O$6 -> 0 | ... AL46: =$D46*AL40*(1+$E46)^AL$6 -> 0
C47: Shea Processing Centers | D47: ='3. Assumptions'!G311 -> 24661 | E47: =IF('1. Project Summary'!$F$13="Real",0,'3. Assumptions'!$E$172) -> 0.05 | G47: EUR | H47: =$D47*H41*(1+$E47)^H$6 -> 0 | I47: =$D47*I41*(1+$E47)^I$6 -> 0 | J47: =$D47*J41*(1+$E47)^J$6 -> 0 | K47: =$D47*K41*(1+$E47)^K$6 -> 0 | L47: =$D47*L41*(1+$E47)^L$6 -> 0 | M47: =$D47*M41*(1+$E47)^M$6 -> 0 | N47: =$D47*N41*(1+$E47)^N$6 -> 0 | O47: =$D47*O41*(1+$E47)^O$6 -> 0 | ... AL47: =$D47*AL41*(1+$E47)^AL$6 -> 0
B48: ="Total "&B44 -> Total Spare Parts | G48: EUR | H48: =SUM(H45:H47) -> 0 | I48: =SUM(I45:I47) -> 27674.955 | J48: =SUM(J45:J47) -> 58117.406 | K48: =SUM(K45:K47) -> 91534.914 | L48: =SUM(L45:L47) -> 128148.88 | M48: =SUM(M45:M47) -> 168195.4 | N48: =SUM(N45:N47) -> 211926.21 | O48: =SUM(O45:O47) -> 259609.61 | ... AL48: =SUM(AL45:AL47) -> 1025224.8
B50: OPEX
C51: Transportation for Spare Parts | D51: ='3. Assumptions'!D325 -> 0.25 | G51: EUR | H51: =H48*$D$51 -> 0 | I51: =I48*$D$51 -> 6918.7388 | J51: =J48*$D$51 -> 14529.351 | K51: =K48*$D$51 -> 22883.728 | L51: =L48*$D$51 -> 32037.22 | M51: =M48*$D$51 -> 42048.851 | N51: =N48*$D$51 -> 52981.552 | O51: =O48*$D$51 -> 64902.401 | ... AL51: =AL48*$D$51 -> 256306.2
C52: External Maintenance Cost | D52: ='3. Assumptions'!D326 -> 0.05 | G52: EUR | H52: =$D52*H34 -> 0 | I52: =$D52*I34 -> 36799.686 | J52: =$D52*J34 -> 38639.67 | K52: =$D52*K34 -> 40571.654 | L52: =$D52*L34 -> 42600.237 | M52: =$D52*M34 -> 44730.248 | N52: =$D52*N34 -> 46966.761 | O52: =$D52*O34 -> 49315.099 | ... AL52: =$D52*AL34 -> 0
C53: Packing Material | D53: ='3. Assumptions'!D327 -> 0.05 | G53: EUR | H53: =$D$53*'4.2 Revenue Build - Other'!H50 -> 0 | I53: =$D$53*'4.2 Revenue Build - Other'!I50 -> 53382.256 | J53: =$D$53*'4.2 Revenue Build - Other'!J50 -> 354657.77 | K53: =$D$53*'4.2 Revenue Build - Other'!K50 -> 628179.92 | L53: =$D$53*'4.2 Revenue Build - Other'!L50 -> 739742.97 | M53: =$D$53*'4.2 Revenue Build - Other'!M50 -> 1081240.2 | N53: =$D$53*'4.2 Revenue Build - Other'!N50 -> 1151390.7 | O53: =$D$53*'4.2 Revenue Build - Other'!O50 -> 1224373.1 | ... AL53: =$D$53*'4.2 Revenue Build - Other'!AL50 -> 2316524.8
B54: ="Total "&B50 -> Total OPEX | G54: EUR | H54: =SUM(H51:H53) -> 0 | I54: =SUM(I51:I53) -> 97100.681 | J54: =SUM(J51:J53) -> 407826.8 | K54: =SUM(K51:K53) -> 691635.3 | L54: =SUM(L51:L53) -> 814380.43 | M54: =SUM(M51:M53) -> 1168019.3 | N54: =SUM(N51:N53) -> 1251339.1 | O54: =SUM(O51:O53) -> 1338590.6 | ... AL54: =SUM(AL51:AL53) -> 2572831
A56: 5000000 | B56: Overhead - Productive Activities
B58: Salary
C59: Headcount
C60: ='3. Assumptions'!C332 -> Director of Industrial Ops | G60: headcount | H60: ='3. Assumptions'!G332 -> 0 | I60: ='3. Assumptions'!H332 -> 0 | J60: ='3. Assumptions'!I332 -> 1 | K60: ='3. Assumptions'!J332 -> 1 | L60: ='3. Assumptions'!K332 -> 1 | M60: ='3. Assumptions'!L332 -> 1 | N60: ='3. Assumptions'!M332 -> 1 | O60: ='3. Assumptions'!N332 -> 1 | ... Q60: ='3. Assumptions'!P332 -> 1 | R60: =Q60 -> 1 | S60: =R60 -> 1 | T60: =S60 -> 1 | U60: =T60 -> 1 | V60: =U60 -> 1 | W60: =V60 -> 1 | X60: =W60 -> 1 | Y60: =X60 -> 1 | ... AL60: =AK60 -> 1
C61: ='3. Assumptions'!C333 -> Factory Managers - Shea Processing | G61: headcount | H61: ='3. Assumptions'!G333 -> 0 | I61: ='3. Assumptions'!H333 -> 0 | J61: ='3. Assumptions'!I333 -> 0 | K61: ='3. Assumptions'!J333 -> 0 | L61: ='3. Assumptions'!K333 -> 0 | M61: ='3. Assumptions'!L333 -> 0 | N61: ='3. Assumptions'!M333 -> 0 | O61: ='3. Assumptions'!N333 -> 0 | ... Q61: ='3. Assumptions'!P333 -> 0 | R61: =Q61 -> 0 | S61: =R61 -> 0 | T61: =S61 -> 0 | U61: =T61 -> 0 | V61: =U61 -> 0 | W61: =V61 -> 0 | X61: =W61 -> 0 | Y61: =X61 -> 0 | ... AL61: =AK61 -> 0
C62: ='3. Assumptions'!C334 -> Factory Managers - Shea Collection | G62: headcount | H62: ='3. Assumptions'!G334 -> 0 | I62: ='3. Assumptions'!H334 -> 0 | J62: ='3. Assumptions'!I334 -> 0 | K62: ='3. Assumptions'!J334 -> 0 | L62: ='3. Assumptions'!K334 -> 0 | M62: ='3. Assumptions'!L334 -> 0 | N62: ='3. Assumptions'!M334 -> 0 | O62: ='3. Assumptions'!N334 -> 0 | ... Q62: ='3. Assumptions'!P334 -> 0 | R62: =Q62 -> 0 | S62: =R62 -> 0 | T62: =S62 -> 0 | U62: =T62 -> 0 | V62: =U62 -> 0 | W62: =V62 -> 0 | X62: =W62 -> 0 | Y62: =X62 -> 0 | ... AL62: =AK62 -> 0
C63: ='3. Assumptions'!C335 -> Factory Managers - Multi Center | G63: headcount | H63: ='3. Assumptions'!G335 -> 0 | I63: ='3. Assumptions'!H335 -> 2 | J63: ='3. Assumptions'!I335 -> 4 | K63: ='3. Assumptions'!J335 -> 6 | L63: ='3. Assumptions'!K335 -> 8 | M63: ='3. Assumptions'!L335 -> 10 | N63: ='3. Assumptions'!M335 -> 12 | O63: ='3. Assumptions'!N335 -> 14 | ... Q63: ='3. Assumptions'!P335 -> 18 | R63: =Q63 -> 18 | S63: =R63 -> 18 | T63: =S63 -> 18 | U63: =T63 -> 18 | V63: =U63 -> 18 | W63: =V63 -> 18 | X63: =W63 -> 18 | Y63: =X63 -> 18 | ... AL63: =AK63 -> 18
C64: ='3. Assumptions'!C336 -> Assistant Manager | G64: headcount | H64: ='3. Assumptions'!G336 -> 0 | I64: ='3. Assumptions'!H336 -> 2 | J64: ='3. Assumptions'!I336 -> 4 | K64: ='3. Assumptions'!J336 -> 6 | L64: ='3. Assumptions'!K336 -> 8 | M64: ='3. Assumptions'!L336 -> 10 | N64: ='3. Assumptions'!M336 -> 12 | O64: ='3. Assumptions'!N336 -> 14 | ... Q64: ='3. Assumptions'!P336 -> 18 | R64: =Q64 -> 18 | S64: =R64 -> 18 | T64: =S64 -> 18 | U64: =T64 -> 18 | V64: =U64 -> 18 | W64: =V64 -> 18 | X64: =W64 -> 18 | Y64: =X64 -> 18 | ... AL64: =AK64 -> 18
C65: ='3. Assumptions'!C337 -> Technical Staff | G65: headcount | H65: ='3. Assumptions'!G337 -> 0 | I65: ='3. Assumptions'!H337 -> 4 | J65: ='3. Assumptions'!I337 -> 8 | K65: ='3. Assumptions'!J337 -> 12 | L65: ='3. Assumptions'!K337 -> 16 | M65: ='3. Assumptions'!L337 -> 20 | N65: ='3. Assumptions'!M337 -> 24 | O65: ='3. Assumptions'!N337 -> 28 | ... Q65: ='3. Assumptions'!P337 -> 36 | R65: =Q65 -> 36 | S65: =R65 -> 36 | T65: =S65 -> 36 | U65: =T65 -> 36 | V65: =U65 -> 36 | W65: =V65 -> 36 | X65: =W65 -> 36 | Y65: =X65 -> 36 | ... AL65: =AK65 -> 36
C66: ='3. Assumptions'!C338 -> Food Engineer | G66: headcount | H66: ='3. Assumptions'!G338 -> 0 | I66: ='3. Assumptions'!H338 -> 2 | J66: ='3. Assumptions'!I338 -> 4 | K66: ='3. Assumptions'!J338 -> 6 | L66: ='3. Assumptions'!K338 -> 8 | M66: ='3. Assumptions'!L338 -> 10 | N66: ='3. Assumptions'!M338 -> 12 | O66: ='3. Assumptions'!N338 -> 14 | ... Q66: ='3. Assumptions'!P338 -> 18 | R66: =Q66 -> 18 | S66: =R66 -> 18 | T66: =S66 -> 18 | U66: =T66 -> 18 | V66: =U66 -> 18 | W66: =V66 -> 18 | X66: =W66 -> 18 | Y66: =X66 -> 18 | ... AL66: =AK66 -> 18
C67: ='3. Assumptions'!C339 -> Logistics specialist | G67: headcount | H67: ='3. Assumptions'!G339 -> 0 | I67: ='3. Assumptions'!H339 -> 0 | J67: ='3. Assumptions'!I339 -> 2 | K67: ='3. Assumptions'!J339 -> 2 | L67: ='3. Assumptions'!K339 -> 4 | M67: ='3. Assumptions'!L339 -> 4 | N67: ='3. Assumptions'!M339 -> 5 | O67: ='3. Assumptions'!N339 -> 5.8 | ... Q67: ='3. Assumptions'!P339 -> 7.4 | R67: =Q67 -> 7.4 | S67: =R67 -> 7.4 | T67: =S67 -> 7.4 | U67: =T67 -> 7.4 | V67: =U67 -> 7.4 | W67: =V67 -> 7.4 | X67: =W67 -> 7.4 | Y67: =X67 -> 7.4 | ... AL67: =AK67 -> 7.4
C68: ='3. Assumptions'!C340 -> Employees | G68: headcount | H68: ='3. Assumptions'!G340 -> 0 | I68: ='3. Assumptions'!H340 -> 8 | J68: ='3. Assumptions'!I340 -> 16 | K68: ='3. Assumptions'!J340 -> 24 | L68: ='3. Assumptions'!K340 -> 32 | M68: ='3. Assumptions'!L340 -> 40 | N68: ='3. Assumptions'!M340 -> 48 | O68: ='3. Assumptions'!N340 -> 56 | ... Q68: ='3. Assumptions'!P340 -> 72 | R68: =Q68 -> 72 | S68: =R68 -> 72 | T68: =S68 -> 72 | U68: =T68 -> 72 | V68: =U68 -> 72 | W68: =V68 -> 72 | X68: =W68 -> 72 | Y68: =X68 -> 72 | ... AL68: =AK68 -> 72
C69: ='3. Assumptions'!C341 -> Executive Secretary | G69: headcount | H69: ='3. Assumptions'!G341 -> 1 | I69: ='3. Assumptions'!H341 -> 1 | J69: ='3. Assumptions'!I341 -> 1 | K69: ='3. Assumptions'!J341 -> 1 | L69: ='3. Assumptions'!K341 -> 1 | M69: ='3. Assumptions'!L341 -> 1 | N69: ='3. Assumptions'!M341 -> 1 | O69: ='3. Assumptions'!N341 -> 1 | ... Q69: ='3. Assumptions'!P341 -> 1 | R69: =Q69 -> 1 | S69: =R69 -> 1 | T69: =S69 -> 1 | U69: =T69 -> 1 | V69: =U69 -> 1 | W69: =V69 -> 1 | X69: =W69 -> 1 | Y69: =X69 -> 1 | ... AL69: =AK69 -> 1
C70: ='3. Assumptions'!C342 -> Accountant | G70: headcount | H70: ='3. Assumptions'!G342 -> 0 | I70: ='3. Assumptions'!H342 -> 2 | J70: ='3. Assumptions'!I342 -> 4 | K70: ='3. Assumptions'!J342 -> 6 | L70: ='3. Assumptions'!K342 -> 8 | M70: ='3. Assumptions'!L342 -> 10 | N70: ='3. Assumptions'!M342 -> 12 | O70: ='3. Assumptions'!N342 -> 14 | ... Q70: ='3. Assumptions'!P342 -> 18 | R70: =Q70 -> 18 | S70: =R70 -> 18 | T70: =S70 -> 18 | U70: =T70 -> 18 | V70: =U70 -> 18 | W70: =V70 -> 18 | X70: =W70 -> 18 | Y70: =X70 -> 18 | ... AL70: =AK70 -> 18
C71: ='3. Assumptions'!C343 -> Secretaries | G71: headcount | H71: ='3. Assumptions'!G343 -> 0 | I71: ='3. Assumptions'!H343 -> 2 | J71: ='3. Assumptions'!I343 -> 4 | K71: ='3. Assumptions'!J343 -> 6 | L71: ='3. Assumptions'!K343 -> 8 | M71: ='3. Assumptions'!L343 -> 10 | N71: ='3. Assumptions'!M343 -> 12 | O71: ='3. Assumptions'!N343 -> 14 | ... Q71: ='3. Assumptions'!P343 -> 18 | R71: =Q71 -> 18 | S71: =R71 -> 18 | T71: =S71 -> 18 | U71: =T71 -> 18 | V71: =U71 -> 18 | W71: =V71 -> 18 | X71: =W71 -> 18 | Y71: =X71 -> 18 | ... AL71: =AK71 -> 18
... C76: ='3. Assumptions'!C348 -> Security Personnel | G76: headcount | H76: ='3. Assumptions'!G348 -> 1 | I76: ='3. Assumptions'!H348 -> 4 | J76: ='3. Assumptions'!I348 -> 8 | K76: ='3. Assumptions'!J348 -> 12 | L76: ='3. Assumptions'!K348 -> 16 | M76: ='3. Assumptions'!L348 -> 20 | N76: ='3. Assumptions'!M348 -> 24 | O76: ='3. Assumptions'!N348 -> 28 | ... Q76: ='3. Assumptions'!P348 -> 36 | R76: =Q76 -> 36 | S76: =R76 -> 36 | T76: =S76 -> 36 | U76: =T76 -> 36 | V76: =U76 -> 36 | W76: =V76 -> 36 | X76: =W76 -> 36 | Y76: =X76 -> 36 | ... AL76: =AK76 -> 36
C77: ="Total "&C59 -> Total Headcount | G77: headcount | H77: =SUM(H60:H76) -> 3 | I77: =SUM(I60:I76) -> 47 | J77: =SUM(J60:J76) -> 96 | K77: =SUM(K60:K76) -> 142 | L77: =SUM(L60:L76) -> 190 | M77: =SUM(M60:M76) -> 236 | N77: =SUM(N60:N76) -> 283 | O77: =SUM(O60:O76) -> 329.8 | ... AL77: =SUM(AL60:AL76) -> 423.4
C79: Salary | D79: Annual salary | E79: CAGR
C80: =C60 -> Director of Industrial Ops | D80: ='3. Assumptions'!D332 -> 25000 | E80: =IF('1. Project Summary'!$F$13="Real",0,'3. Assumptions'!E332) -> 0.02 | G80: EUR | H80: =$D80*H60*(1+$E80)^H$6 -> 0 | I80: =$D80*I60*(1+$E80)^I$6 -> 0 | J80: =$D80*J60*(1+$E80)^J$6 -> 26530.2 | K80: =$D80*K60*(1+$E80)^K$6 -> 27060.804 | L80: =$D80*L60*(1+$E80)^L$6 -> 27602.02 | M80: =$D80*M60*(1+$E80)^M$6 -> 28154.06 | N80: =$D80*N60*(1+$E80)^N$6 -> 28717.142 | O80: =$D80*O60*(1+$E80)^O$6 -> 29291.485 | ... AL80: =$D80*AL60*(1+$E80)^AL$6 -> 46189.72
C81: =C61 -> Factory Managers - Shea Processing | D81: ='3. Assumptions'!D333 -> 10000 | E81: =IF('1. Project Summary'!$F$13="Real",0,'3. Assumptions'!E333) -> 0.02 | G81: EUR | H81: =$D81*H61*(1+$E81)^H$6 -> 0 | I81: =$D81*I61*(1+$E81)^I$6 -> 0 | J81: =$D81*J61*(1+$E81)^J$6 -> 0 | K81: =$D81*K61*(1+$E81)^K$6 -> 0 | L81: =$D81*L61*(1+$E81)^L$6 -> 0 | M81: =$D81*M61*(1+$E81)^M$6 -> 0 | N81: =$D81*N61*(1+$E81)^N$6 -> 0 | O81: =$D81*O61*(1+$E81)^O$6 -> 0 | ... AL81: =$D81*AL61*(1+$E81)^AL$6 -> 0
C82: =C62 -> Factory Managers - Shea Collection | D82: ='3. Assumptions'!D334 -> 10000 | E82: =IF('1. Project Summary'!$F$13="Real",0,'3. Assumptions'!E334) -> 0.02 | G82: EUR | H82: =$D82*H62*(1+$E82)^H$6 -> 0 | I82: =$D82*I62*(1+$E82)^I$6 -> 0 | J82: =$D82*J62*(1+$E82)^J$6 -> 0 | K82: =$D82*K62*(1+$E82)^K$6 -> 0 | L82: =$D82*L62*(1+$E82)^L$6 -> 0 | M82: =$D82*M62*(1+$E82)^M$6 -> 0 | N82: =$D82*N62*(1+$E82)^N$6 -> 0 | O82: =$D82*O62*(1+$E82)^O$6 -> 0 | ... AL82: =$D82*AL62*(1+$E82)^AL$6 -> 0
C83: =C63 -> Factory Managers - Multi Center | D83: ='3. Assumptions'!D335 -> 10000 | E83: =IF('1. Project Summary'!$F$13="Real",0,'3. Assumptions'!E335) -> 0.02 | G83: EUR | H83: =$D83*H63*(1+$E83)^H$6 -> 0 | I83: =$D83*I63*(1+$E83)^I$6 -> 20808 | J83: =$D83*J63*(1+$E83)^J$6 -> 42448.32 | K83: =$D83*K63*(1+$E83)^K$6 -> 64945.93 | L83: =$D83*L63*(1+$E83)^L$6 -> 88326.464 | M83: =$D83*M63*(1+$E83)^M$6 -> 112616.24 | N83: =$D83*N63*(1+$E83)^N$6 -> 137842.28 | O83: =$D83*O63*(1+$E83)^O$6 -> 164032.31 | ... AL83: =$D83*AL63*(1+$E83)^AL$6 -> 332565.99
C84: =C64 -> Assistant Manager | D84: ='3. Assumptions'!D336 -> 8000 | E84: =IF('1. Project Summary'!$F$13="Real",0,'3. Assumptions'!E336) -> 0.02 | G84: EUR | H84: =$D84*H64*(1+$E84)^H$6 -> 0 | I84: =$D84*I64*(1+$E84)^I$6 -> 16646.4 | J84: =$D84*J64*(1+$E84)^J$6 -> 33958.656 | K84: =$D84*K64*(1+$E84)^K$6 -> 51956.744 | L84: =$D84*L64*(1+$E84)^L$6 -> 70661.171 | M84: =$D84*M64*(1+$E84)^M$6 -> 90092.994 | N84: =$D84*N64*(1+$E84)^N$6 -> 110273.82 | O84: =$D84*O64*(1+$E84)^O$6 -> 131225.85 | ... AL84: =$D84*AL64*(1+$E84)^AL$6 -> 266052.79
C85: =C65 -> Technical Staff | D85: ='3. Assumptions'!D337 -> 5000 | E85: =IF('1. Project Summary'!$F$13="Real",0,'3. Assumptions'!E337) -> 0.02 | G85: EUR | H85: =$D85*H65*(1+$E85)^H$6 -> 0 | I85: =$D85*I65*(1+$E85)^I$6 -> 20808 | J85: =$D85*J65*(1+$E85)^J$6 -> 42448.32 | K85: =$D85*K65*(1+$E85)^K$6 -> 64945.93 | L85: =$D85*L65*(1+$E85)^L$6 -> 88326.464 | M85: =$D85*M65*(1+$E85)^M$6 -> 112616.24 | N85: =$D85*N65*(1+$E85)^N$6 -> 137842.28 | O85: =$D85*O65*(1+$E85)^O$6 -> 164032.31 | ... AL85: =$D85*AL65*(1+$E85)^AL$6 -> 332565.99
C86: =C66 -> Food Engineer | D86: ='3. Assumptions'!D338 -> 5000 | E86: =IF('1. Project Summary'!$F$13="Real",0,'3. Assumptions'!E338) -> 0.02 | G86: EUR | H86: =$D86*H66*(1+$E86)^H$6 -> 0 | I86: =$D86*I66*(1+$E86)^I$6 -> 10404 | J86: =$D86*J66*(1+$E86)^J$6 -> 21224.16 | K86: =$D86*K66*(1+$E86)^K$6 -> 32472.965 | L86: =$D86*L66*(1+$E86)^L$6 -> 44163.232 | M86: =$D86*M66*(1+$E86)^M$6 -> 56308.121 | N86: =$D86*N66*(1+$E86)^N$6 -> 68921.14 | O86: =$D86*O66*(1+$E86)^O$6 -> 82016.157 | ... AL86: =$D86*AL66*(1+$E86)^AL$6 -> 166282.99
C87: =C67 -> Logistics specialist | D87: ='3. Assumptions'!D339 -> 5000 | E87: =IF('1. Project Summary'!$F$13="Real",0,'3. Assumptions'!E339) -> 0.02 | G87: EUR | H87: =$D87*H67*(1+$E87)^H$6 -> 0 | I87: =$D87*I67*(1+$E87)^I$6 -> 0 | J87: =$D87*J67*(1+$E87)^J$6 -> 10612.08 | K87: =$D87*K67*(1+$E87)^K$6 -> 10824.322 | L87: =$D87*L67*(1+$E87)^L$6 -> 22081.616 | M87: =$D87*M67*(1+$E87)^M$6 -> 22523.248 | N87: =$D87*N67*(1+$E87)^N$6 -> 28717.142 | O87: =$D87*O67*(1+$E87)^O$6 -> 33978.122 | ... AL87: =$D87*AL67*(1+$E87)^AL$6 -> 68360.786
C88: =C68 -> Employees | D88: ='3. Assumptions'!D340 -> 3000 | E88: =IF('1. Project Summary'!$F$13="Real",0,'3. Assumptions'!E340) -> 0.02 | G88: EUR | H88: =$D88*H68*(1+$E88)^H$6 -> 0 | I88: =$D88*I68*(1+$E88)^I$6 -> 24969.6 | J88: =$D88*J68*(1+$E88)^J$6 -> 50937.984 | K88: =$D88*K68*(1+$E88)^K$6 -> 77935.116 | L88: =$D88*L68*(1+$E88)^L$6 -> 105991.76 | M88: =$D88*M68*(1+$E88)^M$6 -> 135139.49 | N88: =$D88*N68*(1+$E88)^N$6 -> 165410.74 | O88: =$D88*O68*(1+$E88)^O$6 -> 196838.78 | ... AL88: =$D88*AL68*(1+$E88)^AL$6 -> 399079.18
C89: =C69 -> Executive Secretary | D89: ='3. Assumptions'!D341 -> 4000 | E89: =IF('1. Project Summary'!$F$13="Real",0,'3. Assumptions'!E341) -> 0.02 | G89: EUR | H89: =$D89*H69*(1+$E89)^H$6 -> 4080 | I89: =$D89*I69*(1+$E89)^I$6 -> 4161.6 | J89: =$D89*J69*(1+$E89)^J$6 -> 4244.832 | K89: =$D89*K69*(1+$E89)^K$6 -> 4329.7286 | L89: =$D89*L69*(1+$E89)^L$6 -> 4416.3232 | M89: =$D89*M69*(1+$E89)^M$6 -> 4504.6497 | N89: =$D89*N69*(1+$E89)^N$6 -> 4594.7427 | O89: =$D89*O69*(1+$E89)^O$6 -> 4686.6375 | ... AL89: =$D89*AL69*(1+$E89)^AL$6 -> 7390.3553
C90: =C70 -> Accountant | D90: ='3. Assumptions'!D342 -> 2500 | E90: =IF('1. Project Summary'!$F$13="Real",0,'3. Assumptions'!E342) -> 0.02 | G90: EUR | H90: =$D90*H70*(1+$E90)^H$6 -> 0 | I90: =$D90*I70*(1+$E90)^I$6 -> 5202 | J90: =$D90*J70*(1+$E90)^J$6 -> 10612.08 | K90: =$D90*K70*(1+$E90)^K$6 -> 16236.482 | L90: =$D90*L70*(1+$E90)^L$6 -> 22081.616 | M90: =$D90*M70*(1+$E90)^M$6 -> 28154.06 | N90: =$D90*N70*(1+$E90)^N$6 -> 34460.57 | O90: =$D90*O70*(1+$E90)^O$6 -> 41008.078 | ... AL90: =$D90*AL70*(1+$E90)^AL$6 -> 83141.497
C91: =C71 -> Secretaries | D91: ='3. Assumptions'!D343 -> 1500 | E91: =IF('1. Project Summary'!$F$13="Real",0,'3. Assumptions'!E343) -> 0.02 | G91: EUR | H91: =$D91*H71*(1+$E91)^H$6 -> 0 | I91: =$D91*I71*(1+$E91)^I$6 -> 3121.2 | J91: =$D91*J71*(1+$E91)^J$6 -> 6367.248 | K91: =$D91*K71*(1+$E91)^K$6 -> 9741.8894 | L91: =$D91*L71*(1+$E91)^L$6 -> 13248.97 | M91: =$D91*M71*(1+$E91)^M$6 -> 16892.436 | N91: =$D91*N71*(1+$E91)^N$6 -> 20676.342 | O91: =$D91*O71*(1+$E91)^O$6 -> 24604.847 | ... AL91: =$D91*AL71*(1+$E91)^AL$6 -> 49884.898
... C96: =C76 -> Security Personnel | D96: ='3. Assumptions'!D348 -> 1500 | E96: =IF('1. Project Summary'!$F$13="Real",0,'3. Assumptions'!E348) -> 0.02 | G96: EUR | H96: =$D96*H76*(1+$E96)^H$6 -> 1530 | I96: =$D96*I76*(1+$E96)^I$6 -> 6242.4 | J96: =$D96*J76*(1+$E96)^J$6 -> 12734.496 | K96: =$D96*K76*(1+$E96)^K$6 -> 19483.779 | L96: =$D96*L76*(1+$E96)^L$6 -> 26497.939 | M96: =$D96*M76*(1+$E96)^M$6 -> 33784.873 | N96: =$D96*N76*(1+$E96)^N$6 -> 41352.684 | O96: =$D96*O76*(1+$E96)^O$6 -> 49209.694 | ... AL96: =$D96*AL76*(1+$E96)^AL$6 -> 99769.796
B97: ="Total "&B58 -> Total Salary | E97: =AVERAGE(E80:E96) -> 0.02 | G97: EUR | H97: =SUM(H80:H96) -> 7140 | I97: =SUM(I80:I96) -> 152938.8 | J97: =SUM(J80:J96) -> 344892.6 | K97: =SUM(K80:K96) -> 506578.25 | L97: =SUM(L80:L96) -> 685634.18 | M97: =SUM(M80:M96) -> 860388.09 | N97: =SUM(N80:N96) -> 1047601.3 | O97: =SUM(O80:O96) -> 1240787.3 | ... AL97: =SUM(AL80:AL96) -> 2499787.7
B99: ='3. Assumptions'!B121 -> Rental
C100: Office space | D100: Office rental rate (annual) | E100: CAGR | G100: sq.ft | H100: ='3. Assumptions'!G352 -> 1000 | I100: ='3. Assumptions'!H352 -> 1000 | J100: ='3. Assumptions'!I352 -> 1500 | K100: ='3. Assumptions'!J352 -> 1500 | L100: ='3. Assumptions'!K352 -> 1500 | M100: ='3. Assumptions'!L352 -> 2000 | N100: =M100 -> 2000 | O100: =N100 -> 2000 | P100: =O100 -> 2000 | Q100: =P100 -> 2000 | R100: =Q100 -> 2000 | S100: =R100 -> 2000 | T100: =S100 -> 2000 | U100: =T100 -> 2000 | ... AL100: =AK100 -> 2000
C101: Annual office rent | D101: ='3. Assumptions'!E353 -> 10 | E101: =IF('1. Project Summary'!$F$13="Real",0,'3. Assumptions'!E354) -> 0.05 | G101: EUR | H101: =$D101*H100*(1+$E101)^H$6 -> 10500 | I101: =$D101*I100*(1+$E101)^I$6 -> 11025 | J101: =$D101*J100*(1+$E101)^J$6 -> 17364.375 | K101: =$D101*K100*(1+$E101)^K$6 -> 18232.594 | L101: =$D101*L100*(1+$E101)^L$6 -> 19144.223 | M101: =$D101*M100*(1+$E101)^M$6 -> 26801.913 | N101: =$D101*N100*(1+$E101)^N$6 -> 28142.008 | O101: =$D101*O100*(1+$E101)^O$6 -> 29549.109 | ... AL101: =$D101*AL100*(1+$E101)^AL$6 -> 90760.79
B102: ="Total "&B99 -> Total Rental | G102: EUR | H102: =H101 -> 10500 | I102: =I101 -> 11025 | J102: =J101 -> 17364.375 | K102: =K101 -> 18232.594 | L102: =L101 -> 19144.223 | M102: =M101 -> 26801.913 | N102: =N101 -> 28142.008 | O102: =O101 -> 29549.109 | ... AL102: =AL101 -> 90760.79
B104: ='3. Assumptions'!B126 -> Utilities | E104: Starting cost
C105: Utilities | E105: ='3. Assumptions'!E356 -> 5000 | G105: EUR | H105: =E105*H8 -> 5100 | I105: =(H105+'3. Assumptions'!$E$357)*(1+$E$8) -> 7242 | J105: =(I105+'3. Assumptions'!$E$357)*(1+$E$8) -> 9426.84 | K105: =(J105+'3. Assumptions'!$E$357)*(1+$E$8) -> 11655.377 | L105: =(K105+'3. Assumptions'!$E$357)*(1+$E$8) -> 13928.484 | M105: =(L105+'3. Assumptions'!$E$357)*(1+$E$8) -> 16247.054 | N105: =(M105+'3. Assumptions'!$E$357)*(1+$E$8) -> 18611.995 | O105: =(N105+'3. Assumptions'!$E$357)*(1+$E$8) -> 21024.235 | P105: =(O105+'3. Assumptions'!$E$357)*(1+$E$8) -> 23484.72 | ... R105: =(Q105+'3. Assumptions'!$E$357)*(1+$E$8) -> 28554.302 | S105: =(R105)*(1+$E$8) -> 29125.388 | T105: =(S105)*(1+$E$8) -> 29707.896 | U105: =(T105)*(1+$E$8) -> 30302.054 | V105: =(U105)*(1+$E$8) -> 30908.095 | W105: =(V105)*(1+$E$8) -> 31526.257 | X105: =(W105)*(1+$E$8) -> 32156.782 | Y105: =(X105)*(1+$E$8) -> 32799.918 | Z105: =(Y105)*(1+$E$8) -> 33455.916 | ... AL105: =(AK105)*(1+$E$8) -> 42430.191
B106: ="Total "&B104 -> Total Utilities | G106: EUR | H106: =SUM(H105:H105) -> 5100 | I106: =SUM(I105:I105) -> 7242 | J106: =SUM(J105:J105) -> 9426.84 | K106: =SUM(K105:K105) -> 11655.377 | L106: =SUM(L105:L105) -> 13928.484 | M106: =SUM(M105:M105) -> 16247.054 | N106: =SUM(N105:N105) -> 18611.995 | O106: =SUM(O105:O105) -> 21024.235 | ... AL106: =SUM(AL105:AL105) -> 42430.191
B108: Insurance | E108: Cost per center
C109: ='3. Assumptions'!C360 -> Multi-Function Center | E109: ='3. Assumptions'!E360 -> 5000 | G109: EUR | H109: =$E109*H39*H$8 -> 0 | I109: =$E109*I39*I8 -> 10404 | J109: =$E109*J39*J8 -> 21224.16 | K109: =$E109*K39*K8 -> 32472.965 | L109: =$E109*L39*L8 -> 44163.232 | M109: =$E109*M39*M8 -> 56308.121 | N109: =$E109*N39*N8 -> 68921.14 | O109: =$E109*O39*O8 -> 82016.157 | P109: =$E109*P39*P8 -> 95607.405 | ... AL109: =$E109*AL39*AL8 -> 166282.99
C110: ='3. Assumptions'!C361 -> Shea Collection Center | E110: ='3. Assumptions'!E361 -> 5000 | G110: EUR | H110: =$E110*H40*H$8 -> 0 | I110: =$E110*I40*I$8 -> 0 | J110: =$E110*J40*J$8 -> 0 | K110: =$E110*K40*K$8 -> 0 | L110: =$E110*L40*L$8 -> 0 | M110: =$E110*M40*M$8 -> 0 | N110: =$E110*N40*N$8 -> 0 | O110: =$E110*O40*O$8 -> 0 | ... AL110: =$E110*AL40*AL$8 -> 0
C111: ='3. Assumptions'!C362 -> Shea Processing Center | E111: ='3. Assumptions'!E362 -> 10000 | G111: EUR | H111: =$E111*H41*H$8 -> 0 | I111: =$E111*I41*I$8 -> 0 | J111: =$E111*J41*J$8 -> 0 | K111: =$E111*K41*K$8 -> 0 | L111: =$E111*L41*L$8 -> 0 | M111: =$E111*M41*M$8 -> 0 | N111: =$E111*N41*N$8 -> 0 | O111: =$E111*O41*O$8 -> 0 | ... AL111: =$E111*AL41*AL$8 -> 0
B112: ="Total "&B108 -> Total Insurance | G112: EUR | H112: =SUM(H109:H111) -> 0 | I112: =SUM(I109:I111) -> 10404 | J112: =SUM(J109:J111) -> 21224.16 | K112: =SUM(K109:K111) -> 32472.965 | L112: =SUM(L109:L111) -> 44163.232 | M112: =SUM(M109:M111) -> 56308.121 | N112: =SUM(N109:N111) -> 68921.14 | O112: =SUM(O109:O111) -> 82016.157 | ... AL112: =SUM(AL109:AL111) -> 166282.99
B114: Office Equipment | D114: Cost per staff | E114: CAGR
C115: Computers | D115: ='3. Assumptions'!E133 -> 1500 | E115: =IF('1. Project Summary'!$F$13="Real",0,'3. Assumptions'!$E$172) -> 0.05 | G115: EUR | H115: ='3. Assumptions'!G366*(1+$E115)^H$6 -> 1575 | I115: ='3. Assumptions'!H366*(1+$E115)^I$6 -> 36382.5 | J115: ='3. Assumptions'!I366*(1+$E115)^J$6 -> 43410.938 | K115: ='3. Assumptions'!J366*(1+$E115)^K$6 -> 40111.706 | L115: ='3. Assumptions'!K366*(1+$E115)^L$6 -> 45946.136 | M115: ='3. Assumptions'!L366*(1+$E115)^M$6 -> 44223.156 | N115: ='3. Assumptions'!M366*(1+$E115)^N$6 -> 48544.965 | O115: ='3. Assumptions'!N366*(1+$E115)^O$6 -> 50528.976 | ... Q115: ='3. Assumptions'!P366*(1+$E115)^Q$6 -> 55708.196 | R115: =Q115*(1+$E115) -> 58493.606 | S115: =R115*(1+$E115) -> 61418.286 | T115: =S115*(1+$E115) -> 64489.201 | U115: =T115*(1+$E115) -> 67713.661 | V115: =U115*(1+$E115) -> 71099.344 | W115: =V115*(1+$E115) -> 74654.311 | X115: =W115*(1+$E115) -> 78387.026 | Y115: =X115*(1+$E115) -> 82306.378 | ... AL115: =AK115*(1+$E115) -> 155200.95
C116: Office set | D116: ='3. Assumptions'!E134 -> 1000 | E116: =IF('1. Project Summary'!$F$13="Real",0,'3. Assumptions'!$E$172) -> 0.05 | G116: EUR | H116: ='3. Assumptions'!G367*(1+$E116)^H$6 -> 1050 | I116: ='3. Assumptions'!H367*(1+$E116)^I$6 -> 24255 | J116: ='3. Assumptions'!I367*(1+$E116)^J$6 -> 28940.625 | K116: ='3. Assumptions'!J367*(1+$E116)^K$6 -> 26741.138 | L116: ='3. Assumptions'!K367*(1+$E116)^L$6 -> 30630.757 | M116: ='3. Assumptions'!L367*(1+$E116)^M$6 -> 29482.104 | N116: ='3. Assumptions'!M367*(1+$E116)^N$6 -> 32363.31 | O116: ='3. Assumptions'!N367*(1+$E116)^O$6 -> 33685.984 | ... Q116: ='3. Assumptions'!P367*(1+$E116)^Q$6 -> 37138.797 | R116: =Q116*(1+$E116) -> 38995.737 | S116: =R116*(1+$E116) -> 40945.524 | T116: =S116*(1+$E116) -> 42992.8 | U116: =T116*(1+$E116) -> 45142.44 | V116: =U116*(1+$E116) -> 47399.562 | W116: =V116*(1+$E116) -> 49769.541 | X116: =W116*(1+$E116) -> 52258.018 | Y116: =X116*(1+$E116) -> 54870.919 | ... AL116: =AK116*(1+$E116) -> 103467.3
C117: Other furniture and IT equipment | D117: ='3. Assumptions'!E135 -> 1200 | E117: =IF('1. Project Summary'!$F$13="Real",0,'3. Assumptions'!$E$172) -> 0.05 | G117: EUR | H117: ='3. Assumptions'!G368*(1+$E117)^H$6 -> 1260 | I117: ='3. Assumptions'!H368*(1+$E117)^I$6 -> 29106 | J117: ='3. Assumptions'!I368*(1+$E117)^J$6 -> 34728.75 | K117: ='3. Assumptions'!J368*(1+$E117)^K$6 -> 32089.365 | L117: ='3. Assumptions'!K368*(1+$E117)^L$6 -> 36756.909 | M117: ='3. Assumptions'!L368*(1+$E117)^M$6 -> 35378.525 | N117: ='3. Assumptions'!M368*(1+$E117)^N$6 -> 38835.972 | O117: ='3. Assumptions'!N368*(1+$E117)^O$6 -> 40423.181 | ... Q117: ='3. Assumptions'!P368*(1+$E117)^Q$6 -> 44566.557 | R117: =Q117*(1+$E117) -> 46794.885 | S117: =R117*(1+$E117) -> 49134.629 | T117: =S117*(1+$E117) -> 51591.361 | U117: =T117*(1+$E117) -> 54170.929 | V117: =U117*(1+$E117) -> 56879.475 | W117: =V117*(1+$E117) -> 59723.449 | X117: =W117*(1+$E117) -> 62709.621 | Y117: =X117*(1+$E117) -> 65845.102 | ... AL117: =AK117*(1+$E117) -> 124160.76
C118: Software and Digital services | E118: =IF('1. Project Summary'!$F$13="Real",0,'3. Assumptions'!$E$172) -> 0.05 | G118: EUR | H118: ='3. Assumptions'!G369 -> 125000 | I118: ='3. Assumptions'!$H$369*(1+$E$118)^I6 -> 11025 | J118: ='3. Assumptions'!$H$369*(1+$E$118)^J6 -> 11576.25 | K118: ='3. Assumptions'!$H$369*(1+$E$118)^K6 -> 12155.062 | L118: ='3. Assumptions'!$H$369*(1+$E$118)^L6 -> 12762.816 | M118: ='3. Assumptions'!$H$369*(1+$E$118)^M6 -> 13400.956 | N118: ='3. Assumptions'!$H$369*(1+$E$118)^N6 -> 14071.004 | O118: ='3. Assumptions'!$H$369*(1+$E$118)^O6 -> 14774.554 | P118: ='3. Assumptions'!$H$369*(1+$E$118)^P6 -> 15513.282 | ... AL118: ='3. Assumptions'!$H$369*(1+$E$118)^AL6 -> 45380.395
C119: Other | D119: ='3. Assumptions'!E137 -> 0.2 | G119: EUR | H119: =SUM(H115:H117)*$D$119 -> 777 | I119: =SUM(I115:I117)*$D$119 -> 17948.7 | J119: =SUM(J115:J117)*$D$119 -> 21416.062 | K119: =SUM(K115:K117)*$D$119 -> 19788.442 | L119: =SUM(L115:L117)*$D$119 -> 22666.761 | M119: =SUM(M115:M117)*$D$119 -> 21816.757 | N119: =SUM(N115:N117)*$D$119 -> 23948.849 | O119: =SUM(O115:O117)*$D$119 -> 24927.628 | ... AL119: =SUM(AL115:AL117)*$D$119 -> 76565.802
B120: ="Total "&B114 -> Total Office Equipment | G120: EUR | H120: =SUM(H115:H119) -> 129662 | I120: =SUM(I115:I119) -> 118717.2 | J120: =SUM(J115:J119) -> 140072.62 | K120: =SUM(K115:K119) -> 130885.71 | L120: =SUM(L115:L119) -> 148763.38 | M120: =SUM(M115:M119) -> 144301.5 | N120: =SUM(N115:N119) -> 157764.1 | O120: =SUM(O115:O119) -> 164340.32 | ... AL120: =SUM(AL115:AL119) -> 504775.21
B122: Vehicles | E122: Annual cost
C123: ='3. Assumptions'!C141 -> Utility vehicle management | E123: ='3. Assumptions'!E141 -> 50000 | G123: EUR | H123: =$E123*H$8 -> 51000 | I123: =$E123*I$8 -> 52020 | J123: =$E123*J$8 -> 53060.4 | K123: =$E123*K$8 -> 54121.608 | L123: =$E123*L$8 -> 55204.04 | M123: =$E123*M$8 -> 56308.121 | N123: =$E123*N$8 -> 57434.283 | O123: =$E123*O$8 -> 58582.969 | ... AL123: =$E123*AL$8 -> 92379.441
C124: ='3. Assumptions'!C142 -> Utility vehicle management | E124: ='3. Assumptions'!E142 -> 25000 | G124: EUR | H124: =$E124*H$8 -> 25500 | I124: =$E124*I$8 -> 26010 | J124: =$E124*J$8 -> 26530.2 | K124: =$E124*K$8 -> 27060.804 | L124: =$E124*L$8 -> 27602.02 | M124: =$E124*M$8 -> 28154.06 | N124: =$E124*N$8 -> 28717.142 | O124: =$E124*O$8 -> 29291.485 | ... AL124: =$E124*AL$8 -> 46189.72
B125: ="Total "&B122 -> Total Vehicles | G125: EUR | H125: =SUM(H123:H124) -> 76500 | I125: =SUM(I123:I124) -> 78030 | J125: =SUM(J123:J124) -> 79590.6 | K125: =SUM(K123:K124) -> 81182.412 | L125: =SUM(L123:L124) -> 82806.06 | M125: =SUM(M123:M124) -> 84462.181 | N125: =SUM(N123:N124) -> 86151.425 | O125: =SUM(O123:O124) -> 87874.454 | ... AL125: =SUM(AL123:AL124) -> 138569.16
B127: Productive Activities' Cost Summary | E127: Total
...

Sheet 6.P&L
B2: ='1. Project Summary'!B2 -> Projections - Serious Shea
B3: ='1. Project Summary'!B3 -> (in EUR, unless otherwise stated)
B5: Profit & Loss Statement | D5: Unit | H5: ='2. NPV'!H5 -> 2024 | I5: ='2. NPV'!I5 -> 2025 | J5: ='2. NPV'!J5 -> 2026 | K5: ='2. NPV'!K5 -> 2027 | L5: ='2. NPV'!L5 -> 2028 | M5: ='2. NPV'!M5 -> 2029 | N5: ='2. NPV'!N5 -> 2030 | O5: ='2. NPV'!O5 -> 2031 | ... AL5: ='2. NPV'!AL5 -> 2054
H6: =+'4.1 Revenue Build - VCU'!H$7 -> 1 | I6: =+'4.1 Revenue Build - VCU'!I$7 -> 2 | J6: =+'4.1 Revenue Build - VCU'!J$7 -> 3 | K6: =+'4.1 Revenue Build - VCU'!K$7 -> 4 | L6: =+'4.1 Revenue Build - VCU'!L$7 -> 5 | M6: =+'4.1 Revenue Build - VCU'!M$7 -> 6 | N6: =+'4.1 Revenue Build - VCU'!N$7 -> 7 | O6: =+'4.1 Revenue Build - VCU'!O$7 -> 8 | ... AL6: =+'4.1 Revenue Build - VCU'!AL$7 -> 31
C8: Revenue - ARR (VCUs) | E8: Accrued | H8: =H50+H53 -> 0 | I8: =I50+I53 -> 0 | J8: =J50+J53 -> 463550.88 | K8: =K50+K53 -> 859898.7 | L8: =L50+L53 -> 1282538 | M8: =M50+M53 -> 1766908.1 | N8: =N50+N53 -> 2292190.3 | O8: =O50+O53 -> 2754273 | ... AL8: =AL50+AL53 -> 5649274.5
C9: Revenue - Productive Activities | H9: ='2. NPV'!H10 -> 0 | I9: ='2. NPV'!I10 -> 640513.53 | J9: ='2. NPV'!J10 -> 6217535.7 | K9: ='2. NPV'!K10 -> 11217333 | L9: ='2. NPV'!L10 -> 12954963 | M9: ='2. NPV'!M10 -> 19267436 | N9: ='2. NPV'!N10 -> 20128254 | O9: ='2. NPV'!O10 -> 21020070 | ... AL9: ='2. NPV'!AL10 -> 38463729
C10: Revenue | H10: =SUM(H8:H9) -> 0 | I10: =SUM(I8:I9) -> 640513.53 | J10: =SUM(J8:J9) -> 6681086.6 | K10: =SUM(K8:K9) -> 12077232 | L10: =SUM(L8:L9) -> 14237501 | M10: =SUM(M8:M9) -> 21034345 | N10: =SUM(N8:N9) -> 22420444 | O10: =SUM(O8:O9) -> 23774343 | ... AL10: =SUM(AL8:AL9) -> 44113003
C11: Y-o-Y growth | H11: =IFERROR(H10/#REF!-1,"") | I11: =IFERROR(I10/H10-1,"") | J11: =IFERROR(J10/I10-1,"") -> 9.4308282 | K11: =IFERROR(K10/J10-1,"") -> 0.80767476 | L11: =IFERROR(L10/K10-1,"") -> 0.17887128 | M11: =IFERROR(M10/L10-1,"") -> 0.47739015 | N11: =IFERROR(N10/M10-1,"") -> 0.06589696 | O11: =IFERROR(O10/N10-1,"") -> 0.06038679 | P11: =IFERROR(P10/O10-1,"") -> 0.054976501 | ... AL11: =IFERROR(AL10/AK10-1,"") -> 0.024356946
C13: Operating Expenses
C14: Project Development and Monitoring Expenses
C15: Project Development Cost | E15: Amortized | H15: =H56 -> 16521.723 | I15: =I56 -> 16521.723 | J15: =J56 -> 16521.723 | K15: =K56 -> 16521.723 | L15: =L56 -> 16521.723 | M15: =M56 -> 16521.723 | N15: =N56 -> 16521.723 | O15: =O56 -> 16521.723 | ... AL15: =AL56 -> 16521.723
C16: Project Monitoring Cost | H16: ='2. NPV'!H19 -> 4167.0449 | I16: ='2. NPV'!I19 -> 66589.378 | J16: ='2. NPV'!J19 -> 60545.601 | K16: ='2. NPV'!K19 -> 91926.762 | L16: ='2. NPV'!L19 -> 84992.992 | M16: ='2. NPV'!M19 -> 119898.36 | N16: ='2. NPV'!N19 -> 114452.43 | O16: ='2. NPV'!O19 -> 170434.99 | ... AL16: ='2. NPV'!AL19 -> 225950.3
C17: ARR Activities
C18: ='5.2 Cost Build - ARR'!C135 -> Nursery - OPEX | H18: ='2. NPV'!H22 -> 816000 | I18: ='2. NPV'!I22 -> 1331712 | J18: ='2. NPV'!J22 -> 1358346.2 | K18: ='2. NPV'!K22 -> 1385513.2 | L18: ='2. NPV'!L22 -> 1413223.4 | M18: ='2. NPV'!M22 -> 1441487.9 | N18: ='2. NPV'!N22 -> 1470317.7 | O18: ='2. NPV'!O22 -> 1499724 | ... AL18: ='2. NPV'!AL22 -> 0
C19: ='5.2 Cost Build - ARR'!C136 -> Plantation & Transportation Cost | H19: ='2. NPV'!H23 -> 0 | I19: ='2. NPV'!I23 -> 416160 | J19: ='2. NPV'!J23 -> 679173.12 | K19: ='2. NPV'!K23 -> 692756.58 | L19: ='2. NPV'!L23 -> 706611.71 | M19: ='2. NPV'!M23 -> 720743.95 | N19: ='2. NPV'!N23 -> 735158.83 | O19: ='2. NPV'!O23 -> 749862 | ... AL19: ='2. NPV'!AL23 -> 0
C20: ='5.2 Cost Build - ARR'!C137 -> Maintenance cost | H20: ='2. NPV'!H24 -> 0 | I20: ='2. NPV'!I24 -> 0 | J20: ='2. NPV'!J24 -> 90202.68 | K20: ='2. NPV'!K24 -> 239217.51 | L20: ='2. NPV'!L24 -> 394156.85 | M20: ='2. NPV'!M24 -> 459474.27 | N20: ='2. NPV'!N24 -> 468663.75 | O20: ='2. NPV'!O24 -> 478037.03 | ... AL20: ='2. NPV'!AL24 -> 0
C21: ='5.2 Cost Build - ARR'!C138 -> Plantation Overhead | H21: ='2. NPV'!H25 -> 396060 | I21: ='2. NPV'!I25 -> 674967.48 | J21: ='2. NPV'!J25 -> 701931.74 | K21: ='2. NPV'!K25 -> 928306.66 | L21: ='2. NPV'!L25 -> 1044410.7 | M21: ='2. NPV'!M25 -> 1074613.7 | N21: ='2. NPV'!N25 -> 1188547.6 | O21: ='2. NPV'!O25 -> 1215202.8 | ... AL21: ='2. NPV'!AL25 -> 1969694.3
C22: Productive Activities
C23: ='2. NPV'!C29 -> Processing Centers - OPEX | H23: ='2. NPV'!H29 -> 0 | I23: ='2. NPV'!I29 -> 97100.681 | J23: ='2. NPV'!J29 -> 407826.8 | K23: ='2. NPV'!K29 -> 691635.3 | L23: ='2. NPV'!L29 -> 814380.43 | M23: ='2. NPV'!M29 -> 1168019.3 | N23: ='2. NPV'!N29 -> 1251339.1 | O23: ='2. NPV'!O29 -> 1338590.6 | ... AL23: ='2. NPV'!AL29 -> 2572831
C24: ='2. NPV'!C30 -> Productive Activities' Overhead | H24: ='2. NPV'!H30 -> 22740 | I24: ='2. NPV'!I30 -> 181609.8 | J24: ='2. NPV'!J30 -> 392907.97 | K24: ='2. NPV'!K30 -> 568939.19 | L24: ='2. NPV'!L30 -> 762870.12 | M24: ='2. NPV'!M30 -> 959745.18 | N24: ='2. NPV'!N30 -> 1163276.5 | O24: ='2. NPV'!O30 -> 1373376.8 | ... AL24: ='2. NPV'!AL30 -> 2799261.6
C25: Other expenses 1 | H25: ='2. NPV'!H33 -> 0 | I25: ='2. NPV'!I33 -> 0 | J25: ='2. NPV'!J33 -> 0 | K25: ='2. NPV'!K33 -> 0 | L25: ='2. NPV'!L33 -> 0 | M25: ='2. NPV'!M33 -> 0 | N25: ='2. NPV'!N33 -> 0 | O25: ='2. NPV'!O33 -> 0 | ... AL25: ='2. NPV'!AL33 -> 0
C26: Other expenses 2 | H26: ='2. NPV'!H34 -> 0 | I26: ='2. NPV'!I34 -> 0 | J26: ='2. NPV'!J34 -> 0 | K26: ='2. NPV'!K34 -> 0 | L26: ='2. NPV'!L34 -> 0 | M26: ='2. NPV'!M34 -> 0 | N26: ='2. NPV'!N34 -> 0 | O26: ='2. NPV'!O34 -> 0 | ... AL26: ='2. NPV'!AL34 -> 0
C27: Other expenses 3 | H27: ='2. NPV'!H35 -> 0 | I27: ='2. NPV'!I35 -> 0 | J27: ='2. NPV'!J35 -> 0 | K27: ='2. NPV'!K35 -> 0 | L27: ='2. NPV'!L35 -> 0 | M27: ='2. NPV'!M35 -> 0 | N27: ='2. NPV'!N35 -> 0 | O27: ='2. NPV'!O35 -> 0 | ... AL27: ='2. NPV'!AL35 -> 0
C28: EBITDA | H28: =H10-SUM(H15:H27) -> -1255488.8 | I28: =I10-SUM(I15:I27) -> -2144147.5 | J28: =J10-SUM(J15:J27) -> 2973630.7 | K28: =K10-SUM(K15:K27) -> 7462414.7 | L28: =L10-SUM(L15:L27) -> 9000333.5 | M28: =M10-SUM(M15:M27) -> 15073840 | N28: =N10-SUM(N15:N27) -> 16012166 | O28: =O10-SUM(O15:O27) -> 16932593 | ... AL28: =AL10-SUM(AL15:AL27) -> 36528744
C29: EBITDA margin | H29: =IFERROR(H28/H10,"") | I29: =IFERROR(I28/I10,"") -> -3.3475445 | J29: =IFERROR(J28/J10,"") -> 0.4450819 | K29: =IFERROR(K28/K10,"") -> 0.61789117 | L29: =IFERROR(L28/L10,"") -> 0.63215681 | M29: =IFERROR(M28/M10,"") -> 0.7166299 | N29: =IFERROR(N28/N10,"") -> 0.71417705 | O29: =IFERROR(O28/O10,"") -> 0.71222128 | ... AL29: =IFERROR(AL28/AL10,"") -> 0.82807203
C31: Depreciation & Amortization | H31: =-'10.Depn'!H116 -> #VALUE! | I31: =-'10.Depn'!I116 -> #VALUE! | J31: =-'10.Depn'!J116 -> #VALUE! | K31: =-'10.Depn'!K116 -> #VALUE! | L31: =-'10.Depn'!L116 -> #VALUE! | M31: =-'10.Depn'!M116 -> #VALUE! | N31: =-'10.Depn'!N116 -> #VALUE! | O31: =-'10.Depn'!O116 -> #VALUE! | ... AL31: =-'10.Depn'!AL116 -> #VALUE!
C32: EBIT | H32: =H28-SUM(H31:H31) -> #VALUE! | I32: =I28-SUM(I31:I31) -> #VALUE! | J32: =J28-SUM(J31:J31) -> #VALUE! | K32: =K28-SUM(K31:K31) -> #VALUE! | L32: =L28-SUM(L31:L31) -> #VALUE! | M32: =M28-SUM(M31:M31) -> #VALUE! | N32: =N28-SUM(N31:N31) -> #VALUE! | O32: =O28-SUM(O31:O31) -> #VALUE! | ... AL32: =AL28-SUM(AL31:AL31) -> #VALUE!
C33: EBIT margin | H33: =IFERROR(H32/H10,"") | I33: =IFERROR(I32/I10,"") | J33: =IFERROR(J32/J10,"") | K33: =IFERROR(K32/K10,"") | L33: =IFERROR(L32/L10,"") | M33: =IFERROR(M32/M10,"") | N33: =IFERROR(N32/N10,"") | O33: =IFERROR(O32/O10,"") | ... AL33: =IFERROR(AL32/AL10,"")
C35: Interest expenses | H35: ='9.BS Items'!H88 -> 0 | I35: ='9.BS Items'!I88 -> 175000 | J35: ='9.BS Items'!J88 -> 350000 | K35: ='9.BS Items'!K88 -> 332500 | L35: ='9.BS Items'!L88 -> 297500 | M35: ='9.BS Items'!M88 -> 262500 | N35: ='9.BS Items'!N88 -> 227500 | O35: ='9.BS Items'!O88 -> 192500 | ... AL35: ='9.BS Items'!AL88 -> 0
C36: EBT | H36: =H32-H35 -> #VALUE! | I36: =I32-I35 -> #VALUE! | J36: =J32-J35 -> #VALUE! | K36: =K32-K35 -> #VALUE! | L36: =L32-L35 -> #VALUE! | M36: =M32-M35 -> #VALUE! | N36: =N32-N35 -> #VALUE! | O36: =O32-O35 -> #VALUE! | ... AL36: =AL32-AL35 -> #VALUE!
C37: EBT margin | H37: =IFERROR(H36/H10,"") | I37: =IFERROR(I36/I10,"") | J37: =IFERROR(J36/J10,"") | K37: =IFERROR(K36/K10,"") | L37: =IFERROR(L36/L10,"") | M37: =IFERROR(M36/M10,"") | N37: =IFERROR(N36/N10,"") | O37: =IFERROR(O36/O10,"") | ... AL37: =IFERROR(AL36/AL10,"")
C39: Retained earnings (b/f) | H39: =0 -> 0 | I39: =H42 -> #VALUE! | J39: =I42 -> #VALUE! | K39: =J42 -> #VALUE! | L39: =K42 -> #VALUE! | M39: =L42 -> #VALUE! | N39: =M42 -> #VALUE! | O39: =N42 -> #VALUE! | P39: =O42 -> #VALUE! | ... AL39: =AK42 -> #VALUE!
C40: (+) Profit for the year | H40: =H36 -> #VALUE! | I40: =I36 -> #VALUE! | J40: =J36 -> #VALUE! | K40: =K36 -> #VALUE! | L40: =L36 -> #VALUE! | M40: =M36 -> #VALUE! | N40: =N36 -> #VALUE! | O40: =O36 -> #VALUE! | ... AL40: =AL36 -> #VALUE!
C41: (-) Dividends | H41: =0 -> 0 | I41: =0 -> 0 | J41: =0 -> 0 | K41: =0 -> 0 | L41: =0 -> 0 | M41: =0 -> 0 | N41: =0 -> 0 | O41: =0 -> 0 | ... AL41: =0 -> 0
C42: Retained earnings (c/f) | H42: =SUM(H39:H41) -> #VALUE! | I42: =SUM(I39:I41) -> #VALUE! | J42: =SUM(J39:J41) -> #VALUE! | K42: =SUM(K39:K41) -> #VALUE! | L42: =SUM(L39:L41) -> #VALUE! | M42: =SUM(M39:M41) -> #VALUE! | N42: =SUM(N39:N41) -> #VALUE! | O42: =SUM(O39:O41) -> #VALUE! | ... AL42: =SUM(AL39:AL41) -> #VALUE!
C44: P&L Build
C46: Revenue adjustment due to the price change
C47: Cash revenue - ARR | H47: ='4.1 Revenue Build - VCU'!H46 -> 0 | I47: ='4.1 Revenue Build - VCU'!I46 -> 0 | J47: ='4.1 Revenue Build - VCU'!J46 -> 463550.88 | K47: ='4.1 Revenue Build - VCU'!K46 -> 859898.7 | L47: ='4.1 Revenue Build - VCU'!L46 -> 1282538 | M47: ='4.1 Revenue Build - VCU'!M46 -> 1766908.1 | N47: ='4.1 Revenue Build - VCU'!N46 -> 2292190.3 | O47: ='4.1 Revenue Build - VCU'!O46 -> 2754273 | ... AL47: ='4.1 Revenue Build - VCU'!AL46 -> 5649274.5
C48: Applicable price - ARR | H48: ='4.1 Revenue Build - VCU'!H17 -> 0 | I48: ='4.1 Revenue Build - VCU'!I17 -> 0 | J48: ='4.1 Revenue Build - VCU'!J17 -> 0 | K48: ='4.1 Revenue Build - VCU'!K17 -> 0 | L48: ='4.1 Revenue Build - VCU'!L17 -> 0 | M48: ='4.1 Revenue Build - VCU'!M17 -> 0 | N48: ='4.1 Revenue Build - VCU'!N17 -> 0 | O48: ='4.1 Revenue Build - VCU'!O17 -> 0 | ... AL48: ='4.1 Revenue Build - VCU'!AL17 -> 0
C49: Issued VCU - ARR | H49: ='4.1 Revenue Build - VCU'!H36 -> 0 | I49: ='4.1 Revenue Build - VCU'!I36 -> 2028 | J49: ='4.1 Revenue Build - VCU'!J36 -> 43692 | K49: ='4.1 Revenue Build - VCU'!K36 -> 85356 | L49: ='4.1 Revenue Build - VCU'!L36 -> 127016 | M49: ='4.1 Revenue Build - VCU'!M36 -> 173232 | N49: ='4.1 Revenue Build - VCU'!N36 -> 219448 | O49: ='4.1 Revenue Build - VCU'!O36 -> 265664 | ... AL49: ='4.1 Revenue Build - VCU'!AL36 -> 311880
C50: Revenue to be recognized in P&L | H50: =H48*H49 -> 0 | I50: =I48*I49 -> 0 | J50: =J48*J49 -> 0 | K50: =K48*K49 -> 0 | L50: =L48*L49 -> 0 | M50: =M48*M49 -> 0 | N50: =N48*N49 -> 0 | O50: =O48*O49 -> 0 | ... AL50: =AL48*AL49 -> 0
C51: Cumulative accrued/unearned revenue | H51: =H50 -> 0 | I51: =H51+I50 -> 0 | J51: =I51+J50 -> 0 | K51: =J51+K50 -> 0 | L51: =K51+L50 -> 0 | M51: =L51+M50 -> 0 | N51: =M51+N50 -> 0 | O51: =N51+O50 -> 0 | P51: =O51+P50 -> 0 | ... AL51: =AK51+AL50 -> 0
C52: Cumulative cash revenue | H52: =H47 -> 0 | I52: =H52+I47 -> 0 | J52: =I52+J47 -> 463550.88 | K52: =J52+K47 -> 1323449.6 | L52: =K52+L47 -> 2605987.6 | M52: =L52+M47 -> 4372895.7 | N52: =M52+N47 -> 6665086 | O52: =N52+O47 -> 9419359 | P52: =O52+P47 -> 12556835 | ... AL52: =AK52+AL47 -> 1.143071e+08
C53: Adjustment | H53: =IF(H47>0,H52-H51-SUM(G$53:$H53),0) -> 0 | I53: =IF(I47>0,I52-I51-SUM($H$53:H53),0) -> 0 | J53: =IF(J47>0,J52-J51-SUM($H$53:I53),0) -> 463550.88 | K53: =IF(K47>0,K52-K51-SUM($H$53:J53),0) -> 859898.7 | L53: =IF(L47>0,L52-L51-SUM($H$53:K53),0) -> 1282538 | M53: =IF(M47>0,M52-M51-SUM($H$53:L53),0) -> 1766908.1 | N53: =IF(N47>0,N52-N51-SUM($H$53:M53),0) -> 2292190.3 | O53: =IF(O47>0,O52-O51-SUM($H$53:N53),0) -> 2754273 | P53: =IF(P47>0,P52-P51-SUM($H$53:O53),0) -> 3137476.5 | ... AL53: =IF(AL47>0,AL52-AL51-SUM($H$53:AK53),0) -> 5649274.5
C55: Carbon Technical Development and Monitoring Expense Amortization
C56: Project Development Costs VCS | E56: ='2. NPV'!F18 -> 512173.4 | G56: 31 | H56: =$E56/$G56 -> 16521.723 | I56: =$E56/$G56 -> 16521.723 | J56: =$E56/$G56 -> 16521.723 | K56: =$E56/$G56 -> 16521.723 | L56: =$E56/$G56 -> 16521.723 | M56: =$E56/$G56 -> 16521.723 | N56: =$E56/$G56 -> 16521.723 | O56: =$E56/$G56 -> 16521.723 | ... AL56: =$E56/$G56 -> 16521.723
Q284: =$G284*Q$5 -> 0

Sheet 7.CFS
B2: ='1. Project Summary'!B2 -> Projections - Serious Shea
B3: ='1. Project Summary'!B3 -> (in EUR, unless otherwise stated)
B5: Cash Flow Statement | D5: Unit | H5: ='2. NPV'!H5 -> 2024 | I5: ='2. NPV'!I5 -> 2025 | J5: ='2. NPV'!J5 -> 2026 | K5: ='2. NPV'!K5 -> 2027 | L5: ='2. NPV'!L5 -> 2028 | M5: ='2. NPV'!M5 -> 2029 | N5: ='2. NPV'!N5 -> 2030 | O5: ='2. NPV'!O5 -> 2031 | ... AL5: ='2. NPV'!AL5 -> 2054
H6: =+'4.1 Revenue Build - VCU'!H$6 -> 1 | I6: =+'4.1 Revenue Build - VCU'!I$6 -> 2 | J6: =+'4.1 Revenue Build - VCU'!J$6 -> 3 | K6: =+'4.1 Revenue Build - VCU'!K$6 -> 4 | L6: =+'4.1 Revenue Build - VCU'!L$6 -> 5 | M6: =+'4.1 Revenue Build - VCU'!M$6 -> 6 | N6: =+'4.1 Revenue Build - VCU'!N$6 -> 7 | O6: =+'4.1 Revenue Build - VCU'!O$6 -> 8 | ... AL6: =+'4.1 Revenue Build - VCU'!AL$6 -> 31
B8: Cash Flow from Operating Activities
C9: Revenues - VCUs | G9: =SUM('2. NPV'!G9:G9) -> 0 | H9: ='2. NPV'!H9 -> 3000000 | I9: ='2. NPV'!I9 -> 2000000 | J9: ='2. NPV'!J9 -> 2663550.9 | K9: ='2. NPV'!K9 -> 609898.7 | L9: ='2. NPV'!L9 -> 162538.01 | M9: ='2. NPV'!M9 -> 366908.13 | N9: ='2. NPV'!N9 -> 872190.27 | O9: ='2. NPV'!O9 -> 754272.96 | ... AL9: ='2. NPV'!AL9 -> 5649274.5
C10: Revenues - Productive Activities | H10: ='2. NPV'!H10 -> 0 | I10: ='2. NPV'!I10 -> 640513.53 | J10: ='2. NPV'!J10 -> 6217535.7 | K10: ='2. NPV'!K10 -> 11217333 | L10: ='2. NPV'!L10 -> 12954963 | M10: ='2. NPV'!M10 -> 19267436 | N10: ='2. NPV'!N10 -> 20128254 | O10: ='2. NPV'!O10 -> 21020070 | ... AL10: ='2. NPV'!AL10 -> 38463729
C11: (-) Carbon Technical Development and Monitoring Expenses | H11: =-SUM('2. NPV'!H18:H19) -> -285147.53 | I11: =-SUM('2. NPV'!I18:I19) -> -297782.3 | J11: =-SUM('2. NPV'!J18:J19) -> -60545.601 | K11: =-SUM('2. NPV'!K18:K19) -> -91926.762 | L11: =-SUM('2. NPV'!L18:L19) -> -84992.992 | M11: =-SUM('2. NPV'!M18:M19) -> -119898.36 | N11: =-SUM('2. NPV'!N18:N19) -> -114452.43 | O11: =-SUM('2. NPV'!O18:O19) -> -170434.99 | ... AL11: =-SUM('2. NPV'!AL18:AL19) -> -225950.3
C12: (-) Operating Expenses | H12: =-SUM('6.P&L'!H17:H27) -> -1234800 | I12: =-SUM('6.P&L'!I17:I27) -> -2701550 | J12: =-SUM('6.P&L'!J17:J27) -> -3630388.6 | K12: =-SUM('6.P&L'!K17:K27) -> -4506368.4 | L12: =-SUM('6.P&L'!L17:L27) -> -5135653.3 | M12: =-SUM('6.P&L'!M17:M27) -> -5824084.3 | N12: =-SUM('6.P&L'!N17:N27) -> -6277303.3 | O12: =-SUM('6.P&L'!O17:O27) -> -6654793.2 | ... AL12: =-SUM('6.P&L'!AL17:AL27) -> -7341786.9
C13: (-) Increase in Net Working Capital | H13: =-'9.BS Items'!H34 -> 5589.0411 | I13: =-'9.BS Items'!I34 -> -105077.16 | J13: =-'9.BS Items'!J34 -> -1457551.4 | K13: =-'9.BS Items'!K34 -> -1295934.9 | L13: =-'9.BS Items'!L34 -> -398588.24 | M13: =-'9.BS Items'!M34 -> -1648233.4 | N13: =-'9.BS Items'!N34 -> -150754.39 | O13: =-'9.BS Items'!O34 -> -155229.49 | ... AL13: =-'9.BS Items'!AL34 -> -226984.15
B14: Net cash flow from Operating Activities | H14: =SUM(H9:H13) -> 1485641.5 | I14: =SUM(I9:I13) -> -463895.89 | J14: =SUM(J9:J13) -> 3732601 | K14: =SUM(K9:K13) -> 5933001.6 | L14: =SUM(L9:L13) -> 7498267 | M14: =SUM(M9:M13) -> 12042128 | N14: =SUM(N9:N13) -> 14457934 | O14: =SUM(O9:O13) -> 14793885 | ... AL14: =SUM(AL9:AL13) -> 36318282
B16: Cash Flow from Investing Activities
C17: (-) Capital Expenditure | H17: =-'10.Depn'!H21 -> -1116372.6 | I17: =-'10.Depn'!I21 -> -1539086.6 | J17: =-'10.Depn'!J21 -> -1083623.5 | K17: =-'10.Depn'!K21 -> -1116838.7 | L17: =-'10.Depn'!L21 -> -1235809.9 | M17: =-'10.Depn'!M21 -> -1221231.8 | N17: =-'10.Depn'!N21 -> -1345948.4 | O17: =-'10.Depn'!O21 -> -1406764.8 | ... AL17: =-'10.Depn'!AL21 -> -1028782.9
B18: Net cash flow from Investing Activities | H18: =SUM(H17:H17) -> -1116372.6 | I18: =SUM(I17:I17) -> -1539086.6 | J18: =SUM(J17:J17) -> -1083623.5 | K18: =SUM(K17:K17) -> -1116838.7 | L18: =SUM(L17:L17) -> -1235809.9 | M18: =SUM(M17:M17) -> -1221231.8 | N18: =SUM(N17:N17) -> -1345948.4 | O18: =SUM(O17:O17) -> -1406764.8 | ... AL18: =SUM(AL17:AL17) -> -1028782.9
B20: Cash Flow from Financing Activities
C21: Equity Injection
C22: (-) Dividend
C23: Loan proceeds | H23: ='9.BS Items'!H84 -> 0 | I23: ='9.BS Items'!I84 -> 5000000 | J23: ='9.BS Items'!J84 -> 0 | K23: ='9.BS Items'!K84 -> 0 | L23: ='9.BS Items'!L84 -> 0 | M23: ='9.BS Items'!M84 -> 0 | N23: ='9.BS Items'!N84 -> 0 | O23: ='9.BS Items'!O84 -> 0 | ... AL23: ='9.BS Items'!AL84 -> 0
C24: (-) Loan repayments | H24: ='9.BS Items'!H85 -> 0 | I24: ='9.BS Items'!I85 -> 0 | J24: ='9.BS Items'!J85 -> 0 | K24: ='9.BS Items'!K85 -> -500000 | L24: ='9.BS Items'!L85 -> -500000 | M24: ='9.BS Items'!M85 -> -500000 | N24: ='9.BS Items'!N85 -> -500000 | O24: ='9.BS Items'!O85 -> -500000 | ... AL24: ='9.BS Items'!AL85 -> 0
C25: (-) Interest payments | H25: =-'9.BS Items'!H88 -> 0 | I25: =-'9.BS Items'!I88 -> -175000 | J25: =-'9.BS Items'!J88 -> -350000 | K25: =-'9.BS Items'!K88 -> -332500 | L25: =-'9.BS Items'!L88 -> -297500 | M25: =-'9.BS Items'!M88 -> -262500 | N25: =-'9.BS Items'!N88 -> -227500 | O25: =-'9.BS Items'!O88 -> -192500 | ... AL25: =-'9.BS Items'!AL88 -> 0
C26: Grant Funding | H26: ='2. NPV'!H11 -> 0 | I26: ='2. NPV'!I11 -> 0 | J26: ='2. NPV'!J11 -> 0 | K26: ='2. NPV'!K11 -> 0 | L26: ='2. NPV'!L11 -> 0 | M26: ='2. NPV'!M11 -> 0 | N26: ='2. NPV'!N11 -> 0 | O26: ='2. NPV'!O11 -> 0 | ... AL26: ='2. NPV'!AL11 -> 0
B27: Net cash flow from Financing Activities | H27: =SUM(H21:H26) -> 0 | I27: =SUM(I21:I26) -> 4825000 | J27: =SUM(J21:J26) -> -350000 | K27: =SUM(K21:K26) -> -832500 | L27: =SUM(L21:L26) -> -797500 | M27: =SUM(M21:M26) -> -762500 | N27: =SUM(N21:N26) -> -727500 | O27: =SUM(O21:O26) -> -692500 | ... AL27: =SUM(AL21:AL26) -> 0
B29: Net cash flow for the period | H29: =H14+H18+H27 -> 369268.89 | I29: =I14+I18+I27 -> 2822017.6 | J29: =J14+J18+J27 -> 2298977.5 | K29: =K14+K18+K27 -> 3983662.9 | L29: =L14+L18+L27 -> 5464957 | M29: =M14+M18+M27 -> 10058397 | N29: =N14+N18+N27 -> 12384485 | O29: =O14+O18+O27 -> 12694620 | ... AL29: =AL14+AL18+AL27 -> 35289499
B30: Beginning cash balance | H30: =0 -> 0 | I30: =H31 -> 369268.89 | J30: =I31 -> 3191286.4 | K30: =J31 -> 5490263.9 | L30: =K31 -> 9473926.8 | M30: =L31 -> 14938884 | N30: =M31 -> 24997281 | O30: =N31 -> 37381766 | P30: =O31 -> 50076386 | ... AL30: =AK31 -> 6.3496515e+08
B31: Ending cash balance | H31: =SUM(H29:H30) -> 369268.89 | I31: =SUM(I29:I30) -> 3191286.4 | J31: =SUM(J29:J30) -> 5490263.9 | K31: =SUM(K29:K30) -> 9473926.8 | L31: =SUM(L29:L30) -> 14938884 | M31: =SUM(M29:M30) -> 24997281 | N31: =SUM(N29:N30) -> 37381766 | O31: =SUM(O29:O30) -> 50076386 | ... AL31: =SUM(AL29:AL30) -> 6.7025465e+08
C33: Balance check | G33: ='8.BS'!G44 -> 0 | H33: ='8.BS'!H44 -> #VALUE! | I33: ='8.BS'!I44 -> #VALUE! | J33: ='8.BS'!J44 -> #VALUE! | K33: ='8.BS'!K44 -> #VALUE! | L33: ='8.BS'!L44 -> #VALUE! | M33: ='8.BS'!M44 -> #VALUE! | N33: ='8.BS'!N44 -> #VALUE! | ... AL33: ='8.BS'!AL44 -> #VALUE!
C34: Cash vs. NPV check | G34: =G31-'2. NPV'!G40-'8.BS'!G39 -> 0 | H34: =H31-'2. NPV'!H40-SUM($H$27:H27) -> 0 | I34: =I31-'2. NPV'!I40-SUM($H$27:I27) -> 0 | J34: =J31-'2. NPV'!J40-SUM($H$27:J27) -> 0 | K34: =K31-'2. NPV'!K40-SUM($H$27:K27) -> 0 | L34: =L31-'2. NPV'!L40-SUM($H$27:L27) -> 0 | M34: =M31-'2. NPV'!M40-SUM($H$27:M27) -> 0 | N34: =N31-'2. NPV'!N40-SUM($H$27:N27) -> 0 | O34: =O31-'2. NPV'!O40-SUM($H$27:O27) -> 0 | ... AL34: =AL31-'2. NPV'!AL40-SUM($H$27:AL27) -> 0
Q307: =$G307*Q$5 -> 0

Sheet 8.BS
B2: ='1. Project Summary'!B2 -> Projections - Serious Shea
B3: ='1. Project Summary'!B3 -> (in EUR, unless otherwise stated)
B5: Balance Sheet | D5: Unit | H5: ='2. NPV'!H5 -> 2024 | I5: ='2. NPV'!I5 -> 2025 | J5: ='2. NPV'!J5 -> 2026 | K5: ='2. NPV'!K5 -> 2027 | L5: ='2. NPV'!L5 -> 2028 | M5: ='2. NPV'!M5 -> 2029 | N5: ='2. NPV'!N5 -> 2030 | O5: ='2. NPV'!O5 -> 2031 | ... AL5: ='2. NPV'!AL5 -> 2054
H6: =+'4.1 Revenue Build - VCU'!H$6 -> 1 | I6: =+'4.1 Revenue Build - VCU'!I$6 -> 2 | J6: =+'4.1 Revenue Build - VCU'!J$6 -> 3 | K6: =+'4.1 Revenue Build - VCU'!K$6 -> 4 | L6: =+'4.1 Revenue Build - VCU'!L$6 -> 5 | M6: =+'4.1 Revenue Build - VCU'!M$6 -> 6 | N6: =+'4.1 Revenue Build - VCU'!N$6 -> 7 | O6: =+'4.1 Revenue Build - VCU'!O$6 -> 8 | ... AL6: =+'4.1 Revenue Build - VCU'!AL$6 -> 31
B8: Current assets
C9: Cash and cash equivalents | H9: ='7.CFS'!H31 -> 369268.89 | I9: ='7.CFS'!I31 -> 3191286.4 | J9: ='7.CFS'!J31 -> 5490263.9 | K9: ='7.CFS'!K31 -> 9473926.8 | L9: ='7.CFS'!L31 -> 14938884 | M9: ='7.CFS'!M31 -> 24997281 | N9: ='7.CFS'!N31 -> 37381766 | O9: ='7.CFS'!O31 -> 50076386 | ... AL9: ='7.CFS'!AL31 -> 6.7025465e+08
C10: Receivables | H10: ='9.BS Items'!H19 -> 0 | I10: ='9.BS Items'!I19 -> 28813.031 | J10: ='9.BS Items'!J19 -> 495767.25 | K10: ='9.BS Items'!K19 -> 909860.87 | L10: ='9.BS Items'!L19 -> 1031969.1 | M10: ='9.BS Items'!M19 -> 1559851.2 | N10: ='9.BS Items'!N19 -> 1600678.5 | O10: ='9.BS Items'!O19 -> 1642572.3 | ... AL10: ='9.BS Items'!AL19 -> 2905124.5
C11: Inventory | H11: ='9.BS Items'!H26 -> 0 | I11: ='9.BS Items'!I26 -> 107471.36 | J11: ='9.BS Items'!J26 -> 1128693.5 | K11: ='9.BS Items'!K26 -> 2044138.3 | L11: ='9.BS Items'!L26 -> 2357422.2 | M11: ='9.BS Items'!M26 -> 3518013.5 | N11: ='9.BS Items'!N26 -> 3671868.8 | O11: ='9.BS Items'!O26 -> 3833089.3 | ... AL11: ='9.BS Items'!AL26 -> 7426450.3
C12: Accrued income | G12: ='9.BS Items'!G41 -> 0 | H12: ='9.BS Items'!H43 -> 0 | I12: ='9.BS Items'!I43 -> 0 | J12: ='9.BS Items'!J43 -> 0 | K12: ='9.BS Items'!K43 -> 0 | L12: ='9.BS Items'!L43 -> 0 | M12: ='9.BS Items'!M43 -> 0 | N12: ='9.BS Items'!N43 -> 0 | O12: ='9.BS Items'!O43 -> 0 | ... AL12: ='9.BS Items'!AL43 -> 2000000
C13: Prepayments | G13: ='9.BS Items'!G52 -> 0 | H13: ='9.BS Items'!H52 -> 16521.723 | I13: ='9.BS Items'!I52 -> 16521.723 | J13: ='9.BS Items'!J52 -> 16521.723 | K13: ='9.BS Items'!K52 -> 16521.723 | L13: ='9.BS Items'!L52 -> 16521.723 | M13: ='9.BS Items'!M52 -> 16521.723 | N13: ='9.BS Items'!N52 -> 16521.723 | ... AL13: ='9.BS Items'!AL52 -> 0
B14: Total current assets | H14: =SUM(H9:H13) -> 385790.61 | I14: =SUM(I9:I13) -> 3344092.6 | J14: =SUM(J9:J13) -> 7131246.4 | K14: =SUM(K9:K13) -> 12444448 | L14: =SUM(L9:L13) -> 18344797 | M14: =SUM(M9:M13) -> 30091667 | N14: =SUM(N9:N13) -> 42670835 | O14: =SUM(O9:O13) -> 55568569 | ... AL14: =SUM(AL9:AL13) -> 6.8258623e+08
B16: Non-current assets
C17: ='10.Depn'!C137 -> Land | H17: ='10.Depn'!H137 -> 76500 | I17: ='10.Depn'!I137 -> 176580 | J17: ='10.Depn'!J137 -> 199732.5 | K17: ='10.Depn'!K137 -> 224042.62 | L17: ='10.Depn'!L137 -> 249568.26 | M17: ='10.Depn'!M137 -> 276370.17 | N17: ='10.Depn'!N137 -> 304512.18 | O17: ='10.Depn'!O137 -> 334061.29 | ... AL17: ='10.Depn'!AL137 -> 397665.74
C18: ='10.Depn'!C138 -> Buildings & Infrastructure | H18: ='10.Depn'!H138 -> 0 | I18: ='10.Depn'!I138 -> 0 | J18: ='10.Depn'!J138 -> 0 | K18: ='10.Depn'!K138 -> 0 | L18: ='10.Depn'!L138 -> 0 | M18: ='10.Depn'!M138 -> 0 | N18: ='10.Depn'!N138 -> 0 | O18: ='10.Depn'!O138 -> 0 | ... AL18: ='10.Depn'!AL138 -> 0
C19: ='10.Depn'!C139 -> Vehicles | H19: ='10.Depn'!H139 -> 0 | I19: ='10.Depn'!I139 -> 0 | J19: ='10.Depn'!J139 -> 0 | K19: ='10.Depn'!K139 -> 0 | L19: ='10.Depn'!L139 -> 0 | M19: ='10.Depn'!M139 -> 0 | N19: ='10.Depn'!N139 -> 0 | O19: ='10.Depn'!O139 -> 0 | ... AL19: ='10.Depn'!AL139 -> 0
C20: ='10.Depn'!C140 -> Equipment | H20: ='10.Depn'!H140 -> 0 | I20: ='10.Depn'!I140 -> 0 | J20: ='10.Depn'!J140 -> 0 | K20: ='10.Depn'!K140 -> 0 | L20: ='10.Depn'!L140 -> 0 | M20: ='10.Depn'!M140 -> 0 | N20: ='10.Depn'!N140 -> 0 | O20: ='10.Depn'!O140 -> 0 | ... AL20: ='10.Depn'!AL140 -> 0
C21: ='10.Depn'!C141 -> Plantation | H21: ='10.Depn'!H141 -> 0 | I21: ='10.Depn'!I141 -> 0 | J21: ='10.Depn'!J141 -> 0 | K21: ='10.Depn'!K141 -> 0 | L21: ='10.Depn'!L141 -> 0 | M21: ='10.Depn'!M141 -> 0 | N21: ='10.Depn'!N141 -> 0 | O21: ='10.Depn'!O141 -> 0 | ... AL21: ='10.Depn'!AL141 -> 0
C22: ='10.Depn'!C142 -> Office Equipment | H22: ='10.Depn'!H142 -> 0 | I22: ='10.Depn'!I142 -> 0 | J22: ='10.Depn'!J142 -> 0 | K22: ='10.Depn'!K142 -> 0 | L22: ='10.Depn'!L142 -> 0 | M22: ='10.Depn'!M142 -> 0 | N22: ='10.Depn'!N142 -> 0 | O22: ='10.Depn'!O142 -> 0 | ... AL22: ='10.Depn'!AL142 -> 0
C23: Long-term prepayments | H23: ='9.BS Items'!H53 -> 247937.04 | I23: ='9.BS Items'!I53 -> 462608.23 | J23: ='9.BS Items'!J53 -> 446086.51 | K23: ='9.BS Items'!K53 -> 429564.79 | L23: ='9.BS Items'!L53 -> 413043.06 | M23: ='9.BS Items'!M53 -> 396521.34 | N23: ='9.BS Items'!N53 -> 379999.62 | O23: ='9.BS Items'!O53 -> 363477.9 | ... AL23: ='9.BS Items'!AL53 -> -3.5652192e-10
B24: Total non-current assets | H24: =SUM(H17:H23) -> 324437.04 | I24: =SUM(I17:I23) -> 639188.23 | J24: =SUM(J17:J23) -> 645819.01 | K24: =SUM(K17:K23) -> 653607.41 | L24: =SUM(L17:L23) -> 662611.32 | M24: =SUM(M17:M23) -> 672891.51 | N24: =SUM(N17:N23) -> 684511.8 | O24: =SUM(O17:O23) -> 697539.18 | ... AL24: =SUM(AL17:AL23) -> 397665.74
B26: Total assets | D26: =D14+D24 -> 0 | E26: =E14+E24 -> 0 | F26: =F14+F24 -> 0 | G26: =G14+G24 -> 0 | H26: =H14+H24 -> 710227.65 | I26: =I14+I24 -> 3983280.8 | J26: =J14+J24 -> 7777065.4 | K26: =K14+K24 -> 13098055 | ... AL26: =AL14+AL24 -> 6.8298389e+08
B28: Current liabilities
C29: Payables | H29: ='9.BS Items'!H31 -> 5589.0411 | I29: ='9.BS Items'!I31 -> 36796.27 | J29: ='9.BS Items'!J31 -> 67421.147 | K29: ='9.BS Items'!K31 -> 101024.73 | L29: ='9.BS Items'!L31 -> 137828.49 | M29: ='9.BS Items'!M31 -> 178068.61 | N29: ='9.BS Items'!N31 -> 221996.88 | O29: ='9.BS Items'!O31 -> 269881.69 | ... AL29: ='9.BS Items'!AL31 -> 1025224.8
C30: Short-term loan | E30: ='9.BS Items'!E90 -> 0 | F30: ='9.BS Items'!F90 -> 0 | G30: ='9.BS Items'!G90 -> 0 | H30: ='9.BS Items'!H90 -> 0 | I30: ='9.BS Items'!I90 -> 0 | J30: ='9.BS Items'!J90 -> 500000 | K30: ='9.BS Items'!K90 -> 500000 | L30: ='9.BS Items'!L90 -> 500000 | ... AL30: ='9.BS Items'!AL90 -> 0
C31: Unearned revenue | H31: ='9.BS Items'!H44 -> 3000000 | I31: ='9.BS Items'!I44 -> 5000000 | J31: ='9.BS Items'!J44 -> 7200000 | K31: ='9.BS Items'!K44 -> 6950000 | L31: ='9.BS Items'!L44 -> 5830000 | M31: ='9.BS Items'!M44 -> 4430000 | N31: ='9.BS Items'!N44 -> 3010000 | O31: ='9.BS Items'!O44 -> 1010000 | ... AL31: ='9.BS Items'!AL44 -> 0
B32: Total current liabilities | E32: =SUM(E30:E30) -> 0 | F32: =SUM(F30:F30) -> 0 | G32: =SUM(G30:G30) -> 0 | H32: =SUM(H29:H31) -> 3005589 | I32: =SUM(I29:I31) -> 5036796.3 | J32: =SUM(J29:J31) -> 7767421.1 | K32: =SUM(K29:K31) -> 7551024.7 | L32: =SUM(L29:L31) -> 6467828.5 | M32: =SUM(M29:M31) -> 5108068.6 | N32: =SUM(N29:N31) -> 3731996.9 | O32: =SUM(O29:O31) -> 1779881.7 | ... AL32: =SUM(AL29:AL31) -> 1025224.8
B34: Non-current liabilities
C35: Long-term loan | E35: ='9.BS Items'!E91 -> 0 | F35: ='9.BS Items'!F91 -> 0 | G35: ='9.BS Items'!G91 -> 0 | H35: ='9.BS Items'!H91 -> 0 | I35: ='9.BS Items'!I91 -> 5000000 | J35: ='9.BS Items'!J91 -> 4500000 | K35: ='9.BS Items'!K91 -> 4000000 | L35: ='9.BS Items'!L91 -> 3500000 | ... AL35: ='9.BS Items'!AL91 -> 0
B36: Total non-current liabilities | E36: =SUM(E35:E35) -> 0 | F36: =SUM(F35:F35) -> 0 | G36: =SUM(G35:G35) -> 0 | H36: =SUM(H35:H35) -> 0 | I36: =SUM(I35:I35) -> 5000000 | J36: =SUM(J35:J35) -> 4500000 | K36: =SUM(K35:K35) -> 4000000 | L36: =SUM(L35:L35) -> 3500000 | ... AL36: =SUM(AL35:AL35) -> 0
B38: Equity
C39: Share capital | E39: =SUM('7.CFS'!E21:$H21) -> 0 | F39: =SUM('7.CFS'!F21:$H21) -> 0 | G39: =SUM('7.CFS'!G21:$H21) -> 0 | H39: =SUM('7.CFS'!$H21:H21) -> 0 | I39: =SUM('7.CFS'!$H21:I21) -> 0 | J39: =SUM('7.CFS'!$H21:J21) -> 0 | K39: =SUM('7.CFS'!$H21:K21) -> 0 | L39: =SUM('7.CFS'!$H21:L21) -> 0 | M39: =SUM('7.CFS'!$H21:M21) -> 0 | N39: =SUM('7.CFS'!$H21:N21) -> 0 | O39: =SUM('7.CFS'!$H21:O21) -> 0 | ... AL39: =SUM('7.CFS'!$H21:AL21) -> 0
C40: Retained earnings | E40: ='6.P&L'!E42 -> 0 | F40: ='6.P&L'!F42 -> 0 | G40: ='6.P&L'!G42 -> 0 | H40: ='6.P&L'!H42 -> #VALUE! | I40: ='6.P&L'!I42 -> #VALUE! | J40: ='6.P&L'!J42 -> #VALUE! | K40: ='6.P&L'!K42 -> #VALUE! | L40: ='6.P&L'!L42 -> #VALUE! | ... AL40: ='6.P&L'!AL42 -> #VALUE!
B41: Total equity | E41: =SUM(E39:E40) -> 0 | F41: =SUM(F39:F40) -> 0 | G41: =SUM(G39:G40) -> 0 | H41: =SUM(H39:H40) -> #VALUE! | I41: =SUM(I39:I40) -> #VALUE! | J41: =SUM(J39:J40) -> #VALUE! | K41: =SUM(K39:K40) -> #VALUE! | L41: =SUM(L39:L40) -> #VALUE! | ... AL41: =SUM(AL39:AL40) -> #VALUE!
B43: Total liabilities & Equity | H43: =H32+H36+H41 -> #VALUE! | I43: =I32+I36+I41 -> #VALUE! | J43: =J32+J36+J41 -> #VALUE! | K43: =K32+K36+K41 -> #VALUE! | L43: =L32+L36+L41 -> #VALUE! | M43: =M32+M36+M41 -> #VALUE! | N43: =N32+N36+N41 -> #VALUE! | O43: =O32+O36+O41 -> #VALUE! | ... AL43: =AL32+AL36+AL41 -> #VALUE!
C44: Check | H44: =H26-H43 -> #VALUE! | I44: =I26-I43 -> #VALUE! | J44: =J26-J43 -> #VALUE! | K44: =K26-K43 -> #VALUE! | L44: =L26-L43 -> #VALUE! | M44: =M26-M43 -> #VALUE! | N44: =N26-N43 -> #VALUE! | O44: =O26-O43 -> #VALUE! | ... AL44: =AL26-AL43 -> #VALUE!
Q315: =$F315*Q$5 -> 0

Sheet 9.BS Items
B2: ='1. Project Summary'!B2 -> Projections - Serious Shea
B3: ='1. Project Summary'!B3 -> (in EUR, unless otherwise stated)
B5: Working Capital Calculation | D5: Unit | H5: ='2. NPV'!H5 -> 2024 | I5: ='2. NPV'!I5 -> 2025 | J5: ='2. NPV'!J5 -> 2026 | K5: ='2. NPV'!K5 -> 2027 | L5: ='2. NPV'!L5 -> 2028 | M5: ='2. NPV'!M5 -> 2029 | N5: ='2. NPV'!N5 -> 2030 | O5: ='2. NPV'!O5 -> 2031 | ... AL5: ='2. NPV'!AL5 -> 2054
H6: =+'4.1 Revenue Build - VCU'!H$7 -> 1 | I6: =+'4.1 Revenue Build - VCU'!I$7 -> 2 | J6: =+'4.1 Revenue Build - VCU'!J$7 -> 3 | K6: =+'4.1 Revenue Build - VCU'!K$7 -> 4 | L6: =+'4.1 Revenue Build - VCU'!L$7 -> 5 | M6: =+'4.1 Revenue Build - VCU'!M$7 -> 6 | N6: =+'4.1 Revenue Build - VCU'!N$7 -> 7 | O6: =+'4.1 Revenue Build - VCU'!O$7 -> 8 | ... AL6: =+'4.1 Revenue Build - VCU'!AL$7 -> 31
B8: Revenue from Productive Activities
C9: ='4.2 Revenue Build - Other'!C27 -> Refined Oil | H9: ='4.2 Revenue Build - Other'!H27 -> 0 | I9: ='4.2 Revenue Build - Other'!I27 -> 0 | J9: ='4.2 Revenue Build - Other'!J27 -> 5217535.1 | K9: ='4.2 Revenue Build - Other'!K27 -> 9626352.2 | L9: ='4.2 Revenue Build - Other'!L27 -> 10963346 | M9: ='4.2 Revenue Build - Other'!M27 -> 16856144 | N9: ='4.2 Revenue Build - Other'!N27 -> 17277547 | O9: ='4.2 Revenue Build - Other'!O27 -> 17709486 | ... AL9: ='4.2 Revenue Build - Other'!AL27 -> 31250348
C10: ='4.2 Revenue Build - Other'!C28 -> Moringa Leaves | H10: ='4.2 Revenue Build - Other'!H28 -> 0 | I10: ='4.2 Revenue Build - Other'!I28 -> 305416.69 | J10: ='4.2 Revenue Build - Other'!J28 -> 313052.1 | K10: ='4.2 Revenue Build - Other'!K28 -> 534797.35 | L10: ='4.2 Revenue Build - Other'!L28 -> 548167.28 | M10: ='4.2 Revenue Build - Other'!M28 -> 561871.46 | N10: ='4.2 Revenue Build - Other'!N28 -> 575918.25 | O10: ='4.2 Revenue Build - Other'!O28 -> 590316.2 | ... AL10: ='4.2 Revenue Build - Other'!AL28 -> 1041678.3
C11: ='4.2 Revenue Build - Other'!C31 -> Fertilisers Compost | H11: ='4.2 Revenue Build - Other'!H31 -> 0 | I11: ='4.2 Revenue Build - Other'!I31 -> 126075 | J11: ='4.2 Revenue Build - Other'!J31 -> 258453.75 | K11: ='4.2 Revenue Build - Other'!K31 -> 397372.64 | L11: ='4.2 Revenue Build - Other'!L31 -> 543075.94 | M11: ='4.2 Revenue Build - Other'!M31 -> 695816.05 | N11: ='4.2 Revenue Build - Other'!N31 -> 855853.74 | O11: ='4.2 Revenue Build - Other'!O31 -> 1023458.4 | ... AL11: ='4.2 Revenue Build - Other'!AL31 -> 2322007.3
C12: Processing fees | H12: ='4.2 Revenue Build - Other'!H38 -> 0 | I12: ='4.2 Revenue Build - Other'!I38 -> 18175.812 | J12: ='4.2 Revenue Build - Other'!J38 -> 37260.416 | K12: ='4.2 Revenue Build - Other'!K38 -> 57287.889 | L12: ='4.2 Revenue Build - Other'!L38 -> 78293.448 | M12: ='4.2 Revenue Build - Other'!M38 -> 100313.48 | N12: ='4.2 Revenue Build - Other'!N38 -> 123385.58 | O12: ='4.2 Revenue Build - Other'!O38 -> 147548.59 | ... AL12: ='4.2 Revenue Build - Other'!AL38 -> 334756.05
B13: Procurement for nurseries | H13: ='5.2 Cost Build - ARR'!H31 -> 816000 | I13: ='5.2 Cost Build - ARR'!I31 -> 1331712 | J13: ='5.2 Cost Build - ARR'!J31 -> 1358346.2 | K13: ='5.2 Cost Build - ARR'!K31 -> 1385513.2 | L13: ='5.2 Cost Build - ARR'!L31 -> 1413223.4 | M13: ='5.2 Cost Build - ARR'!M31 -> 1441487.9 | N13: ='5.2 Cost Build - ARR'!N31 -> 1470317.7 | O13: ='5.2 Cost Build - ARR'!O31 -> 1499724 | ... AL13: ='5.2 Cost Build - ARR'!AL31 -> 0
B15: Receivables | D15: Min Days | E15: Max Days
C16: =C9 -> Refined Oil | D16: =20 -> 20 | E16: 45 | H16: =H9*AVERAGE($D16,$E16)/365 -> 0 | I16: =I9*AVERAGE($D16,$E16)/365 -> 0 | J16: =J9*AVERAGE($D16,$E16)/365 -> 464575.04 | K16: =K9*AVERAGE($D16,$E16)/365 -> 857140.95 | L16: =L9*AVERAGE($D16,$E16)/365 -> 976188.31 | M16: =M9*AVERAGE($D16,$E16)/365 -> 1500889.5 | N16: =N9*AVERAGE($D16,$E16)/365 -> 1538411.8 | O16: =O9*AVERAGE($D16,$E16)/365 -> 1576872.1 | ... AL16: =AL9*AVERAGE($D16,$E16)/365 -> 2782565.3
C17: =C10 -> Moringa Leaves | D17: =D16 -> 20 | E17: =E16 -> 45 | H17: =H10*AVERAGE($D17,$E17)/365 -> 0 | I17: =I10*AVERAGE($D17,$E17)/365 -> 27194.637 | J17: =J10*AVERAGE($D17,$E17)/365 -> 27874.502 | K17: =K10*AVERAGE($D17,$E17)/365 -> 47618.942 | L17: =L10*AVERAGE($D17,$E17)/365 -> 48809.415 | M17: =M10*AVERAGE($D17,$E17)/365 -> 50029.651 | N17: =N10*AVERAGE($D17,$E17)/365 -> 51280.392 | O17: =O10*AVERAGE($D17,$E17)/365 -> 52562.402 | ... AL17: =AL10*AVERAGE($D17,$E17)/365 -> 92752.176
C18: =C11 -> Fertilisers Compost | D18: =D17 -> 20 | E18: =E17 -> 45 | H18: =H12*AVERAGE($D18,$E18)/365 -> 0 | I18: =I12*AVERAGE($D18,$E18)/365 -> 1618.3943 | J18: =J12*AVERAGE($D18,$E18)/365 -> 3317.7082 | K18: =K12*AVERAGE($D18,$E18)/365 -> 5100.9764 | L18: =L12*AVERAGE($D18,$E18)/365 -> 6971.3344 | M18: =M12*AVERAGE($D18,$E18)/365 -> 8932.0223 | N18: =N12*AVERAGE($D18,$E18)/365 -> 10986.387 | O18: =O12*AVERAGE($D18,$E18)/365 -> 13137.888 | ... AL18: =AL12*AVERAGE($D18,$E18)/365 -> 29807.046
C19: Total Receivables | H19: =SUM(H16:H18) -> 0 | I19: =SUM(I16:I18) -> 28813.031 | J19: =SUM(J16:J18) -> 495767.25 | K19: =SUM(K16:K18) -> 909860.87 | L19: =SUM(L16:L18) -> 1031969.1 | M19: =SUM(M16:M18) -> 1559851.2 | N19: =SUM(N16:N18) -> 1600678.5 | O19: =SUM(O16:O18) -> 1642572.3 | ... AL19: =SUM(AL16:AL18) -> 2905124.5
B21: Inventory | D21: Min Days | E21: Max Days
C22: =C16 -> Refined Oil | D22: 45 | E22: 90 | H22: =H9*AVERAGE($D22,$E22)/365 -> 0 | I22: =I9*AVERAGE($D22,$E22)/365 -> 0 | J22: =J9*AVERAGE($D22,$E22)/365 -> 964886.62 | K22: =K9*AVERAGE($D22,$E22)/365 -> 1780215.8 | L22: =L9*AVERAGE($D22,$E22)/365 -> 2027468 | M22: =M9*AVERAGE($D22,$E22)/365 -> 3117232.1 | N22: =N9*AVERAGE($D22,$E22)/365 -> 3195162.9 | O22: =O9*AVERAGE($D22,$E22)/365 -> 3275042 | ... AL22: =AL9*AVERAGE($D22,$E22)/365 -> 5779174
C23: =C17 -> Moringa Leaves | D23: =D22 -> 45 | E23: =E22 -> 90 | H23: =H10*AVERAGE($D23,$E23)/365 -> 0 | I23: =I10*AVERAGE($D23,$E23)/365 -> 56481.168 | J23: =J10*AVERAGE($D23,$E23)/365 -> 57893.197 | K23: =K10*AVERAGE($D23,$E23)/365 -> 98900.879 | L23: =L10*AVERAGE($D23,$E23)/365 -> 101373.4 | M23: =M10*AVERAGE($D23,$E23)/365 -> 103907.74 | N23: =N10*AVERAGE($D23,$E23)/365 -> 106505.43 | O23: =O10*AVERAGE($D23,$E23)/365 -> 109168.07 | ... AL23: =AL10*AVERAGE($D23,$E23)/365 -> 192639.13
C24: =C18 -> Fertilisers Compost | D24: =D23 -> 45 | E24: =E23 -> 90 | H24: =H11*AVERAGE($D24,$E24)/365 -> 0 | I24: =I11*AVERAGE($D24,$E24)/365 -> 23315.24 | J24: =J11*AVERAGE($D24,$E24)/365 -> 47796.241 | K24: =K11*AVERAGE($D24,$E24)/365 -> 73486.721 | L24: =L11*AVERAGE($D24,$E24)/365 -> 100431.85 | M24: =M11*AVERAGE($D24,$E24)/365 -> 128678.31 | N24: =N11*AVERAGE($D24,$E24)/365 -> 158274.32 | O24: =O11*AVERAGE($D24,$E24)/365 -> 189269.71 | ... AL24: =AL11*AVERAGE($D24,$E24)/365 -> 429412.31
C25: Spare parts | H25: ='5.3 Cost Build - Productive'!H129 -> 0 | I25: ='5.3 Cost Build - Productive'!I129 -> 27674.955 | J25: ='5.3 Cost Build - Productive'!J129 -> 58117.406 | K25: ='5.3 Cost Build - Productive'!K129 -> 91534.914 | L25: ='5.3 Cost Build - Productive'!L129 -> 128148.88 | M25: ='5.3 Cost Build - Productive'!M129 -> 168195.4 | N25: ='5.3 Cost Build - Productive'!N129 -> 211926.21 | O25: ='5.3 Cost Build - Productive'!O129 -> 259609.61 | ... AL25: ='5.3 Cost Build - Productive'!AL129 -> 1025224.8
C26: Total Inventory | H26: =SUM(H22:H25) -> 0 | I26: =SUM(I22:I25) -> 107471.36 | J26: =SUM(J22:J25) -> 1128693.5 | K26: =SUM(K22:K25) -> 2044138.3 | L26: =SUM(L22:L25) -> 2357422.2 | M26: =SUM(M22:M25) -> 3518013.5 | N26: =SUM(N22:N25) -> 3671868.8 | O26: =SUM(O22:O25) -> 3833089.3 | ... AL26: =SUM(AL22:AL25) -> 7426450.3
B28: Payables | D28: Min Days | E28: Max Days
C29: Payables for Nursery costs | D29: 0 | E29: 5 | H29: =H13*AVERAGE($D29,$E29)/365 -> 5589.0411 | I29: =I13*AVERAGE($D29,$E29)/365 -> 9121.3151 | J29: =J13*AVERAGE($D29,$E29)/365 -> 9303.7414 | K29: =K13*AVERAGE($D29,$E29)/365 -> 9489.8162 | L29: =L13*AVERAGE($D29,$E29)/365 -> 9679.6125 | M29: =M13*AVERAGE($D29,$E29)/365 -> 9873.2048 | N29: =N13*AVERAGE($D29,$E29)/365 -> 10070.669 | O29: =O13*AVERAGE($D29,$E29)/365 -> 10272.082 | ... AL29: =AL13*AVERAGE($D29,$E29)/365 -> 0
C30: Other payables | H30: =H25 -> 0 | I30: =I25 -> 27674.955 | J30: =J25 -> 58117.406 | K30: =K25 -> 91534.914 | L30: =L25 -> 128148.88 | M30: =M25 -> 168195.4 | N30: =N25 -> 211926.21 | O30: =O25 -> 259609.61 | ... AL30: =AL25 -> 1025224.8
C31: Ending balance | H31: =SUM(H29:H30) -> 5589.0411 | I31: =SUM(I29:I30) -> 36796.27 | J31: =SUM(J29:J30) -> 67421.147 | K31: =SUM(K29:K30) -> 101024.73 | L31: =SUM(L29:L30) -> 137828.49 | M31: =SUM(M29:M30) -> 178068.61 | N31: =SUM(N29:N30) -> 221996.88 | O31: =SUM(O29:O30) -> 269881.69 | ... AL31: =SUM(AL29:AL30) -> 1025224.8
B33: Working Capital Required | H33: =H19+H26-H31 -> -5589.0411 | I33: =I19+I26-I31 -> 99488.124 | J33: =J19+J26-J31 -> 1557039.6 | K33: =K19+K26-K31 -> 2852974.5 | L33: =L19+L26-L31 -> 3251562.7 | M33: =M19+M26-M31 -> 4899796.1 | N33: =N19+N26-N31 -> 5050550.5 | O33: =O19+O26-O31 -> 5205780 | ... AL33: =AL19+AL26-AL31 -> 9306349.9
B34: Net Working Capital Changes | H34: =H33 -> -5589.0411 | I34: =I33-H33 -> 105077.16 | J34: =J33-I33 -> 1457551.4 | K34: =K33-J33 -> 1295934.9 | L34: =L33-K33 -> 398588.24 | M34: =M33-L33 -> 1648233.4 | N34: =N33-M33 -> 150754.39 | O34: =O33-N33 -> 155229.49 | P34: =P33-O33 -> 170311.64 | ... AL34: =AL33-AK33 -> 226984.15
C35: Working Capital Days to Sales | H35: =H33/'6.P&L'!H10*365 -> #DIV/0! | I35: =I33/'6.P&L'!I10*365 -> 56.69383 | J35: =J33/'6.P&L'!J10*365 -> 85.063924 | K35: =K33/'6.P&L'!K10*365 -> 86.223045 | L35: =L33/'6.P&L'!L10*365 -> 83.358755 | M35: =M33/'6.P&L'!M10*365 -> 85.02407 | N35: =N33/'6.P&L'!N10*365 -> 82.221875 | O35: =O33/'6.P&L'!O10*365 -> 79.922702 | ... AL35: =AL33/'6.P&L'!AL10*365 -> 77.002641
B37: Accrued income Or Unearned Revenue
C38: Beginning balance | H38: =0 -> 0 | I38: =H41 -> -3000000 | J38: =I41 -> -5000000 | K38: =J41 -> -7200000 | L38: =K41 -> -6950000 | M38: =L41 -> -5830000 | N38: =M41 -> -4430000 | O38: =N41 -> -3010000 | P38: =O41 -> -1010000 | ... AL38: =AK41 -> 2000000
C39: (+) Recognized in P&L | H39: ='6.P&L'!H8 -> 0 | I39: ='6.P&L'!I8 -> 0 | J39: ='6.P&L'!J8 -> 463550.88 | K39: ='6.P&L'!K8 -> 859898.7 | L39: ='6.P&L'!L8 -> 1282538 | M39: ='6.P&L'!M8 -> 1766908.1 | N39: ='6.P&L'!N8 -> 2292190.3 | O39: ='6.P&L'!O8 -> 2754273 | ... AL39: ='6.P&L'!AL8 -> 5649274.5
